Workbook

Sheet Summary
A1: PA-07 House Election Winner — Tracker
A2: Pennsylvania's 7th Congressional District, general election 3 Nov 2026. Green = pulled from another sheet, black = calculated, blue = entered fact, yellow = key output or assumption. Built 2026-10-12 02:24 UTC.
A4: HEADLINE
A5: Consensus Democratic win probability | B5: =AVERAGE(Polymarket!D19,Kalshi!E17) | D5: Equal-weighted mean of the two venue mids. Not liquidity-weighted — Polymarket carries the larger book.
A6: Consensus Republican win probability | B6: =AVERAGE(Polymarket!D20,Kalshi!E18) | D6: Bob Brooks (D) vs incumbent Ryan Mackenzie (R).
A7: Market-implied margin (D−R) | B7: ='Margin of Victory'!B31 | D7: Expected margin from Polymarket's bracket ladder.
A9: RACE AT A GLANCE
A10: District | B10: Pennsylvania 7th (Lehigh Valley: Lehigh, Northampton, part of Monroe)
A11: Election date | B11: 46329
A12: Days until election | B12: =DATE(2026,11,3)-TODAY()
A13: Republican nominee | B13: Ryan Mackenzie (incumbent, serving since 3 Jan 2025)
A14: Democratic nominee | B14: Bob Brooks (president, PA Professional Fire Fighters Association)
A15: Democratic primary | B15: 19 May 2026 — Brooks won with ~41.4% over Crosswell, McClure, Obando-Derstine
A16: Republican primary | B16: 19 May 2026 — Mackenzie unopposed
A17: 2024 House result | B17: Mackenzie (R) 50.4% – Wild (D) 49.4% (R+1.0; narrowest PA House margin of 2024)
A18: Cook PVI | B18: R+1
A19: 2024 presidential | B19: Trump +1 (2026 GBAO sample recall: 47–46)
A20: Cook Political Report | B20: Toss Up
A21: Sabato's Crystal Ball | B21: Toss-up (moved from Lean D on 1 Feb 2026)
A22: Inside Elections | B22: Toss-up
A24: LIVE MARKET SNAPSHOT — WINNER
A25: Venue | B25: Dem Mid | C25: Rep Mid | D25: Sum of Mids | E25: Overround (vig) | F25: Dem Bid-Ask | G25: Dem Normalised | H25: Depth / Volume
A26: Polymarket | B26: =Polymarket!D19 | C26: =Polymarket!D20 | D26: =Polymarket!D21 | E26: =B26+C26-1 | F26: =Polymarket!E19 | G26: =IFERROR(B26/D26,"") | H26: =Polymarket!B12+Polymarket!C12
A27: Kalshi | B27: =Kalshi!E17 | C27: =Kalshi!E18 | D27: =Kalshi!E19 | E27: =B27+C27-1 | F27: =Kalshi!F17 | G27: =IFERROR(B27/D27,"") | H27: =Kalshi!G17+Kalshi!G18
A28: Consensus (equal weight) | B28: =AVERAGE(B26:B27) | C28: =AVERAGE(C26:C27) | D28: =AVERAGE(D26:D27) | E28: =AVERAGE(E26:E27) | F28: =AVERAGE(F26:F27) | G28: =AVERAGE(G26:G27) | H28: =SUM(H26:H27)
A30: OTHER SUBJECTS TRACKED
A31: Subject | B31: Venue | C31: Key figure | D31: Value | E31: Sheet
A32: Winner (party) | B32: Polymarket + Kalshi | C32: Consensus P(Dem) | D32: =B5 | E32: Polymarket / Kalshi
A33: Margin of victory | B33: Polymarket only | C33: Expected margin (D−R) | D33: ='Margin of Victory'!B31 | E33: Margin of Victory
A34: Margin of victory | B34: Polymarket only | C34: P(margin under 3 pts) | D34: ='Margin of Victory'!B32 | E34: Margin of Victory
A35: Voter turnout | B35: Kalshi only | C35: Expected ballots cast | D35: ='Voter Turnout'!B25 | E35: Voter Turnout
A36: PA Democratic seats | B36: Kalshi only | C36: Expected seats of 17 | D36: ='PA Seat Count'!B24 | E36: PA Seat Count
A37: Dem primary (settled) | B37: Kalshi + polls | C37: Brooks actual result | D37: =Polls!H49 | E37: Polls
A38: Kalshi also quotes a margin-of-victory ladder (KXMIDTERMMOV-PA07D/R), but too thinly to use: most rungs have no two-sided quote, so it is collected and not shown. Turnout is Kalshi-only. PA-07 still has no entry in Kalshi's closest-race market, and its PA-07 nominee and 2024 events return no tradeable markets. Full inventory on Notes & Sources.
A40: CROSS-VENUE ARBITRAGE CHECK (live, executable prices)
A41: Cheapest Dem YES ask | B41: =MIN(Polymarket!C19,Kalshi!D17) | C41: =IF(Polymarket!C19<=Kalshi!D17,"Polymarket","Kalshi")
A42: Cheapest Rep YES ask | B42: =MIN(Polymarket!C20,Kalshi!D18) | C42: =IF(Polymarket!C20<=Kalshi!D18,"Polymarket","Kalshi")
A43: Total cost of both legs | B43: =B41+B42
A44: Gross edge per $1 payout | B44: =1-B43
A45: Arbitrage present? | B45: =IF(B44>0,"YES — gross, before fees","No")
A47: MOMENTUM — Polymarket Democratic price
A48: Latest | B48: =IFERROR(IF(INDEX(Polymarket!$B$25:$B$303,MATCH(Polymarket!$A$303-0,Polymarket!$A$25:$A$303,1))=0,"",INDEX(Polymarket!$B$25:$B$303,MATCH(Polymarket!$A$303-0,Polymarket!$A$25:$A$303,1))),"") | C48: change vs latest | D48: =IFERROR(IF(INDEX(Polymarket!$A$25:$A$303,MATCH(Polymarket!$A$303-0,Polymarket!$A$25:$A$303,1))=0,"",INDEX(Polymarket!$A$25:$A$303,MATCH(Polymarket!$A$303-0,Polymarket!$A$25:$A$303,1))),"") | E48: date actually used
A49: 7 days ago | B49: =IFERROR(IF(INDEX(Polymarket!$B$25:$B$303,MATCH(Polymarket!$A$303-7,Polymarket!$A$25:$A$303,1))=0,"",INDEX(Polymarket!$B$25:$B$303,MATCH(Polymarket!$A$303-7,Polymarket!$A$25:$A$303,1))),"") | C49: =IF(AND(ISNUMBER(B48),ISNUMBER(B49)),B48-B49,"") | D49: =IFERROR(IF(INDEX(Polymarket!$A$25:$A$303,MATCH(Polymarket!$A$303-7,Polymarket!$A$25:$A$303,1))=0,"",INDEX(Polymarket!$A$25:$A$303,MATCH(Polymarket!$A$303-7,Polymarket!$A$25:$A$303,1))),"")
A50: 30 days ago | B50: =IFERROR(IF(INDEX(Polymarket!$B$25:$B$303,MATCH(Polymarket!$A$303-30,Polymarket!$A$25:$A$303,1))=0,"",INDEX(Polymarket!$B$25:$B$303,MATCH(Polymarket!$A$303-30,Polymarket!$A$25:$A$303,1))),"") | C50: =IF(AND(ISNUMBER(B48),ISNUMBER(B50)),B48-B50,"") | D50: =IFERROR(IF(INDEX(Polymarket!$A$25:$A$303,MATCH(Polymarket!$A$303-30,Polymarket!$A$25:$A$303,1))=0,"",INDEX(Polymarket!$A$25:$A$303,MATCH(Polymarket!$A$303-30,Polymarket!$A$25:$A$303,1))),"")
A51: 90 days ago | B51: =IFERROR(IF(INDEX(Polymarket!$B$25:$B$303,MATCH(Polymarket!$A$303-90,Polymarket!$A$25:$A$303,1))=0,"",INDEX(Polymarket!$B$25:$B$303,MATCH(Polymarket!$A$303-90,Polymarket!$A$25:$A$303,1))),"") | C51: =IF(AND(ISNUMBER(B48),ISNUMBER(B51)),B48-B51,"") | D51: =IFERROR(IF(INDEX(Polymarket!$A$25:$A$303,MATCH(Polymarket!$A$303-90,Polymarket!$A$25:$A$303,1))=0,"",INDEX(Polymarket!$A$25:$A$303,MATCH(Polymarket!$A$303-90,Polymarket!$A$25:$A$303,1))),"")
A52: Series high | B52: =MAX(Polymarket!B25:B303)
A53: Series low | B53: =MIN(Polymarket!B25:B303)
A54: Series start (17 Dec 2025) | B54: =Polymarket!B25 | C54: =IF(AND(ISNUMBER(B48),ISNUMBER(B54)),B48-B54,"")
A56: MARKETS vs POLLS
A57: Weighted poll margin (D−R) | B57: =Polls!B35
A58: House-effect adjusted poll margin | B58: =Polls!B37
A59: Market-implied margin (ladder) | B59: ='Margin of Victory'!B31
A60: Market − polls (raw) | B60: =IFERROR(B59/100-B57,"")
A61: Market − polls (adjusted) | B61: =IFERROR(B59/100-B58,"")
A62: Read | B62: =IF(B61="","",IF(B61>0,"Markets more bullish on Brooks than the adjusted polls","Markets less bullish on Brooks than the adjusted polls"))
A63: Polls in average | B63: =COUNT(Polls!L12:L24)
A64: Days since most recent poll | B64: =IFERROR(TODAY()-MAX(Polls!E12:E24),"")
A65: The ladder's expected margin is in percentage points, so it is divided by 100 to compare with the poll margin, which is stored as a fraction. One public general-election poll exists and it is Democratic-sponsored, so the adjusted line is the fairer comparison.
A67: DATA FRESHNESS
A68: Snapshot pulled | B68: 2026-10-12 02:24 UTC
A69: Polymarket winner history | B69: =TEXT(Polymarket!A25,"yyyy-mm-dd")&" to "&TEXT(Polymarket!A303,"yyyy-mm-dd")&" ("&COUNT(Polymarket!A25:A303)&" days)"
A70: Kalshi winner history | B70: =TEXT(Kalshi!A31,"yyyy-mm-dd")&" to "&TEXT(Kalshi!A485,"yyyy-mm-dd")&" ("&COUNT(Kalshi!A31:A485)&" days)"
A71: Polls source | B71: house.csv (NYT / 538 house-poll file) — PA-07 rows: 1 general, 4 primary
A72: Refresh | B72: See Notes & Sources for the exact API call behind every blue cell.

Sheet Charts
A1: Charts — Race Trajectory
A2: Every chart is bound to the cell ranges on the data sheets, so all of them redraw automatically each time the tracker refreshes. Built 2026-10-12 02:24 UTC.
A207: Chart 7 — the PollsMax model against Polymarket, matched day by day. The two answer the same question by different means, so a persistent gap is a claim that one of them is mispriced.
A208: Chart 1 — the headline. The dashed grey line is even odds; both venues have held Brooks above it since late April 2026.
A209: Chart 2 — a persistent gap is normal: different fees, capital costs and user bases. It is not tradeable unless the two ASK prices sum below 100%, which is the check on the Summary sheet.
A210: Chart 3 — the gap between the two lines is the bid-ask spread. A narrowing band means the market is getting more confident and more liquid.
A211: Chart 5 — a fair pair of prices sums to 100%. Below that, buying both sides locks in a profit; above it, the venue is charging a spread.

Sheet Distributions
A1: Charts — Distributions & Polls
A2: What the market thinks the result will look like, and how that squares with the polling. Built 2026-10-12 02:24 UTC.
A178: MARKETS vs POLLS — margin in percentage points
A179: Weighted poll margin | B179: =Polls!B35*100 | C179: Positive favours Brooks (D). Poll margins are scaled from fractions to points so all three bars share one axis.
A180: Adjusted poll margin | B180: =Polls!B37*100
A181: Market-implied margin | B181: ='Margin of Victory'!B31
A183: DEMOCRATIC PRIMARY — what the polls said vs what happened
A184: =Polls!A45&" ("&TEXT(Polls!E45,"d mmm")&")" | B184: =Polls!H45
A185: =Polls!A46&" ("&TEXT(Polls!E46,"d mmm")&")" | B185: =Polls!H46
A186: =Polls!A47&" ("&TEXT(Polls!E47,"d mmm")&")" | B186: =Polls!H47
A187: =Polls!A48&" ("&TEXT(Polls!E48,"d mmm")&")" | B187: =Polls!H48
A188: ACTUAL RESULT | B188: =Polls!H49
A190: Every primary poll understated Brooks, the last of them by 15 points, because 31-53% of respondents were undecided. Worth remembering when reading the single general-election poll.
A191: Chart 11 is deliberately a curve, not bars: turnout thresholds are nested, so bars would imply an exclusivity the market does not have.
A192: The margin chart mixes sources on purpose: the poll bars come from one Democratic-sponsored survey, the market bar from Polymarket's bracket ladder. Treat the gap as a question, not a signal.

Sheet Polymarket
A1: Polymarket — PA-07 House Election Winner
A2: Source: Polymarket CLOB API (clob.polymarket.com) + Gamma API. Prices are per-$1 contracts; price = implied probability. Pulled 2026-10-12 02:24 UTC.
A4: MARKET METADATA
A5: Field | B5: Democratic Party | C5: Republican Party
A6: Question | B6: Will the Democratic Party win the PA-07 House seat? | C6: Will the Republican Party win the PA-07 House seat?
A7: Market slug | B7: will-the-democratic-party-win-the-pa-07-house-seat | C7: will-the-republican-party-win-the-pa-07-house-seat
A8: CLOB token ID | B8: 37713776886536763857380242322222367371582682723176215910322979366716585040762 | C8: 56412855186822728853119072474894085602768054645914780515455268260878947887549
A9: Condition ID | B9: 0x863ec10c7b201b57ff3ca07ddbc74c5c464bb9ac732d2e003786b8455658592a | C9: 0x1a8fadca151b214722192338aa6ea3ec4122902576fb4192d7f6da3dd3a8f9ec
A10: Market opened | B10: 2025-12-16 | C10: 2025-12-16
A11: Resolution date | B11: 2026-11-04 | C11: 2026-11-04
A12: Volume ($) | B12: 25905.074 | C12: 8864.5331
A13: Liquidity ($) | B13: 22485.817 | C13: 44428.705
A14: Last trade | B14: 0.87 | C14: 0.1
A15: 24h price change
A17: LIVE ORDER BOOK SNAPSHOT
A18: Outcome | B18: Best Bid | C18: Best Ask | D18: Mid | E18: Bid-Ask Spread | F18: Bid Size ($) | G18: Ask Size ($) | H18: Implied Prob (normalised)
A19: Democratic Party | B19: 0.85 | C19: 0.87 | D19: =(B19+C19)/2 | E19: =C19-B19 | F19: 397.04 | G19: 72.57 | H19: =IFERROR(D19/$D$21,"")
A20: Republican Party | B20: 0.13 | C20: 0.14 | D20: =(B20+C20)/2 | E20: =C20-B20 | F20: 698.31 | G20: 514.7 | H20: =IFERROR(D20/$D$21,"")
A21: Sum of mids (100% = no vig) | D21: =SUM(D19:D20) | E21: =D21-1 | H21: =SUM(H19:H20)
A23: DAILY PRICE HISTORY
A24: Date | B24: Dem YES Price | C24: Rep YES Price | D24: Sum (D+R) | E24: Dem Normalised | F24: Rep Normalised | G24: Dem − Rep Spread | H24: Dem 7d Change | I24: Dem 30d Change | J24: Days to Election | K24: Axis label
A25: 46008 | B25: 0.48 | C25: 0.5 | D25: =IF(COUNT(B25:C25)=2,B25+C25,"") | E25: =IF(ISNUMBER(B25),IFERROR(B25/$D25,""),"") | F25: =IF(ISNUMBER(C25),IFERROR(C25/$D25,""),"") | G25: =IF(COUNT(B25:C25)=2,B25-C25,"") | H25: =IFERROR(IF(AND(ISNUMBER(B25),INDEX($B$25:$B25,MATCH($A25-7,$A$25:$A25,1))<>0,INDEX($A$25:$A25,MATCH($A25-7,$A$25:$A25,1))<>0,$A25-INDEX($A$25:$A25,MATCH($A25-7,$A$25:$A25,1))<=10),B25-INDEX($B$25:$B25,MATCH($A25-7,$A$25:$A25,1)),""),"") | I25: =IFERROR(IF(AND(ISNUMBER(B25),INDEX($B$25:$B25,MATCH($A25-30,$A$25:$A25,1))<>0,INDEX($A$25:$A25,MATCH($A25-30,$A$25:$A25,1))<>0,$A25-INDEX($A$25:$A25,MATCH($A25-30,$A$25:$A25,1))<=33),B25-INDEX($B$25:$B25,MATCH($A25-30,$A$25:$A25,1)),""),"") | J25: =DATE(2026,11,3)-A25 | K25: 17 Dec
A26: 46009 | B26: 0.48 | C26: 0.5 | D26: =IF(COUNT(B26:C26)=2,B26+C26,"") | E26: =IF(ISNUMBER(B26),IFERROR(B26/$D26,""),"") | F26: =IF(ISNUMBER(C26),IFERROR(C26/$D26,""),"") | G26: =IF(COUNT(B26:C26)=2,B26-C26,"") | H26: =IFERROR(IF(AND(ISNUMBER(B26),INDEX($B$25:$B26,MATCH($A26-7,$A$25:$A26,1))<>0,INDEX($A$25:$A26,MATCH($A26-7,$A$25:$A26,1))<>0,$A26-INDEX($A$25:$A26,MATCH($A26-7,$A$25:$A26,1))<=10),B26-INDEX($B$25:$B26,MATCH($A26-7,$A$25:$A26,1)),""),"") | I26: =IFERROR(IF(AND(ISNUMBER(B26),INDEX($B$25:$B26,MATCH($A26-30,$A$25:$A26,1))<>0,INDEX($A$25:$A26,MATCH($A26-30,$A$25:$A26,1))<>0,$A26-INDEX($A$25:$A26,MATCH($A26-30,$A$25:$A26,1))<=33),B26-INDEX($B$25:$B26,MATCH($A26-30,$A$25:$A26,1)),""),"") | J26: =DATE(2026,11,3)-A26 | K26: 18 Dec
A27: 46010 | B27: 0.485 | C27: 0.49 | D27: =IF(COUNT(B27:C27)=2,B27+C27,"") | E27: =IF(ISNUMBER(B27),IFERROR(B27/$D27,""),"") | F27: =IF(ISNUMBER(C27),IFERROR(C27/$D27,""),"") | G27: =IF(COUNT(B27:C27)=2,B27-C27,"") | H27: =IFERROR(IF(AND(ISNUMBER(B27),INDEX($B$25:$B27,MATCH($A27-7,$A$25:$A27,1))<>0,INDEX($A$25:$A27,MATCH($A27-7,$A$25:$A27,1))<>0,$A27-INDEX($A$25:$A27,MATCH($A27-7,$A$25:$A27,1))<=10),B27-INDEX($B$25:$B27,MATCH($A27-7,$A$25:$A27,1)),""),"") | I27: =IFERROR(IF(AND(ISNUMBER(B27),INDEX($B$25:$B27,MATCH($A27-30,$A$25:$A27,1))<>0,INDEX($A$25:$A27,MATCH($A27-30,$A$25:$A27,1))<>0,$A27-INDEX($A$25:$A27,MATCH($A27-30,$A$25:$A27,1))<=33),B27-INDEX($B$25:$B27,MATCH($A27-30,$A$25:$A27,1)),""),"") | J27: =DATE(2026,11,3)-A27 | K27: 19 Dec
A28: 46011 | B28: 0.49 | C28: 0.495 | D28: =IF(COUNT(B28:C28)=2,B28+C28,"") | E28: =IF(ISNUMBER(B28),IFERROR(B28/$D28,""),"") | F28: =IF(ISNUMBER(C28),IFERROR(C28/$D28,""),"") | G28: =IF(COUNT(B28:C28)=2,B28-C28,"") | H28: =IFERROR(IF(AND(ISNUMBER(B28),INDEX($B$25:$B28,MATCH($A28-7,$A$25:$A28,1))<>0,INDEX($A$25:$A28,MATCH($A28-7,$A$25:$A28,1))<>0,$A28-INDEX($A$25:$A28,MATCH($A28-7,$A$25:$A28,1))<=10),B28-INDEX($B$25:$B28,MATCH($A28-7,$A$25:$A28,1)),""),"") | I28: =IFERROR(IF(AND(ISNUMBER(B28),INDEX($B$25:$B28,MATCH($A28-30,$A$25:$A28,1))<>0,INDEX($A$25:$A28,MATCH($A28-30,$A$25:$A28,1))<>0,$A28-INDEX($A$25:$A28,MATCH($A28-30,$A$25:$A28,1))<=33),B28-INDEX($B$25:$B28,MATCH($A28-30,$A$25:$A28,1)),""),"") | J28: =DATE(2026,11,3)-A28 | K28: 20 Dec
A29: 46012 | B29: 0.49 | C29: 0.495 | D29: =IF(COUNT(B29:C29)=2,B29+C29,"") | E29: =IF(ISNUMBER(B29),IFERROR(B29/$D29,""),"") | F29: =IF(ISNUMBER(C29),IFERROR(C29/$D29,""),"") | G29: =IF(COUNT(B29:C29)=2,B29-C29,"") | H29: =IFERROR(IF(AND(ISNUMBER(B29),INDEX($B$25:$B29,MATCH($A29-7,$A$25:$A29,1))<>0,INDEX($A$25:$A29,MATCH($A29-7,$A$25:$A29,1))<>0,$A29-INDEX($A$25:$A29,MATCH($A29-7,$A$25:$A29,1))<=10),B29-INDEX($B$25:$B29,MATCH($A29-7,$A$25:$A29,1)),""),"") | I29: =IFERROR(IF(AND(ISNUMBER(B29),INDEX($B$25:$B29,MATCH($A29-30,$A$25:$A29,1))<>0,INDEX($A$25:$A29,MATCH($A29-30,$A$25:$A29,1))<>0,$A29-INDEX($A$25:$A29,MATCH($A29-30,$A$25:$A29,1))<=33),B29-INDEX($B$25:$B29,MATCH($A29-30,$A$25:$A29,1)),""),"") | J29: =DATE(2026,11,3)-A29 | K29: 21 Dec
A30: 46013 | B30: 0.485 | C30: 0.5 | D30: =IF(COUNT(B30:C30)=2,B30+C30,"") | E30: =IF(ISNUMBER(B30),IFERROR(B30/$D30,""),"") | F30: =IF(ISNUMBER(C30),IFERROR(C30/$D30,""),"") | G30: =IF(COUNT(B30:C30)=2,B30-C30,"") | H30: =IFERROR(IF(AND(ISNUMBER(B30),INDEX($B$25:$B30,MATCH($A30-7,$A$25:$A30,1))<>0,INDEX($A$25:$A30,MATCH($A30-7,$A$25:$A30,1))<>0,$A30-INDEX($A$25:$A30,MATCH($A30-7,$A$25:$A30,1))<=10),B30-INDEX($B$25:$B30,MATCH($A30-7,$A$25:$A30,1)),""),"") | I30: =IFERROR(IF(AND(ISNUMBER(B30),INDEX($B$25:$B30,MATCH($A30-30,$A$25:$A30,1))<>0,INDEX($A$25:$A30,MATCH($A30-30,$A$25:$A30,1))<>0,$A30-INDEX($A$25:$A30,MATCH($A30-30,$A$25:$A30,1))<=33),B30-INDEX($B$25:$B30,MATCH($A30-30,$A$25:$A30,1)),""),"") | J30: =DATE(2026,11,3)-A30 | K30: 22 Dec
A31: 46014 | B31: 0.495 | C31: 0.5 | D31: =IF(COUNT(B31:C31)=2,B31+C31,"") | E31: =IF(ISNUMBER(B31),IFERROR(B31/$D31,""),"") | F31: =IF(ISNUMBER(C31),IFERROR(C31/$D31,""),"") | G31: =IF(COUNT(B31:C31)=2,B31-C31,"") | H31: =IFERROR(IF(AND(ISNUMBER(B31),INDEX($B$25:$B31,MATCH($A31-7,$A$25:$A31,1))<>0,INDEX($A$25:$A31,MATCH($A31-7,$A$25:$A31,1))<>0,$A31-INDEX($A$25:$A31,MATCH($A31-7,$A$25:$A31,1))<=10),B31-INDEX($B$25:$B31,MATCH($A31-7,$A$25:$A31,1)),""),"") | I31: =IFERROR(IF(AND(ISNUMBER(B31),INDEX($B$25:$B31,MATCH($A31-30,$A$25:$A31,1))<>0,INDEX($A$25:$A31,MATCH($A31-30,$A$25:$A31,1))<>0,$A31-INDEX($A$25:$A31,MATCH($A31-30,$A$25:$A31,1))<=33),B31-INDEX($B$25:$B31,MATCH($A31-30,$A$25:$A31,1)),""),"") | J31: =DATE(2026,11,3)-A31 | K31: 23 Dec
A32: 46015 | B32: 0.49 | C32: 0.5 | D32: =IF(COUNT(B32:C32)=2,B32+C32,"") | E32: =IF(ISNUMBER(B32),IFERROR(B32/$D32,""),"") | F32: =IF(ISNUMBER(C32),IFERROR(C32/$D32,""),"") | G32: =IF(COUNT(B32:C32)=2,B32-C32,"") | H32: =IFERROR(IF(AND(ISNUMBER(B32),INDEX($B$25:$B32,MATCH($A32-7,$A$25:$A32,1))<>0,INDEX($A$25:$A32,MATCH($A32-7,$A$25:$A32,1))<>0,$A32-INDEX($A$25:$A32,MATCH($A32-7,$A$25:$A32,1))<=10),B32-INDEX($B$25:$B32,MATCH($A32-7,$A$25:$A32,1)),""),"") | I32: =IFERROR(IF(AND(ISNUMBER(B32),INDEX($B$25:$B32,MATCH($A32-30,$A$25:$A32,1))<>0,INDEX($A$25:$A32,MATCH($A32-30,$A$25:$A32,1))<>0,$A32-INDEX($A$25:$A32,MATCH($A32-30,$A$25:$A32,1))<=33),B32-INDEX($B$25:$B32,MATCH($A32-30,$A$25:$A32,1)),""),"") | J32: =DATE(2026,11,3)-A32 | K32: 24 Dec
A33: 46016 | B33: 0.49 | C33: 0.49 | D33: =IF(COUNT(B33:C33)=2,B33+C33,"") | E33: =IF(ISNUMBER(B33),IFERROR(B33/$D33,""),"") | F33: =IF(ISNUMBER(C33),IFERROR(C33/$D33,""),"") | G33: =IF(COUNT(B33:C33)=2,B33-C33,"") | H33: =IFERROR(IF(AND(ISNUMBER(B33),INDEX($B$25:$B33,MATCH($A33-7,$A$25:$A33,1))<>0,INDEX($A$25:$A33,MATCH($A33-7,$A$25:$A33,1))<>0,$A33-INDEX($A$25:$A33,MATCH($A33-7,$A$25:$A33,1))<=10),B33-INDEX($B$25:$B33,MATCH($A33-7,$A$25:$A33,1)),""),"") | I33: =IFERROR(IF(AND(ISNUMBER(B33),INDEX($B$25:$B33,MATCH($A33-30,$A$25:$A33,1))<>0,INDEX($A$25:$A33,MATCH($A33-30,$A$25:$A33,1))<>0,$A33-INDEX($A$25:$A33,MATCH($A33-30,$A$25:$A33,1))<=33),B33-INDEX($B$25:$B33,MATCH($A33-30,$A$25:$A33,1)),""),"") | J33: =DATE(2026,11,3)-A33 | K33: 25 Dec
A34: 46017 | B34: 0.49 | C34: 0.495 | D34: =IF(COUNT(B34:C34)=2,B34+C34,"") | E34: =IF(ISNUMBER(B34),IFERROR(B34/$D34,""),"") | F34: =IF(ISNUMBER(C34),IFERROR(C34/$D34,""),"") | G34: =IF(COUNT(B34:C34)=2,B34-C34,"") | H34: =IFERROR(IF(AND(ISNUMBER(B34),INDEX($B$25:$B34,MATCH($A34-7,$A$25:$A34,1))<>0,INDEX($A$25:$A34,MATCH($A34-7,$A$25:$A34,1))<>0,$A34-INDEX($A$25:$A34,MATCH($A34-7,$A$25:$A34,1))<=10),B34-INDEX($B$25:$B34,MATCH($A34-7,$A$25:$A34,1)),""),"") | I34: =IFERROR(IF(AND(ISNUMBER(B34),INDEX($B$25:$B34,MATCH($A34-30,$A$25:$A34,1))<>0,INDEX($A$25:$A34,MATCH($A34-30,$A$25:$A34,1))<>0,$A34-INDEX($A$25:$A34,MATCH($A34-30,$A$25:$A34,1))<=33),B34-INDEX($B$25:$B34,MATCH($A34-30,$A$25:$A34,1)),""),"") | J34: =DATE(2026,11,3)-A34 | K34: 26 Dec
A35: 46018 | B35: 0.495 | C35: 0.5 | D35: =IF(COUNT(B35:C35)=2,B35+C35,"") | E35: =IF(ISNUMBER(B35),IFERROR(B35/$D35,""),"") | F35: =IF(ISNUMBER(C35),IFERROR(C35/$D35,""),"") | G35: =IF(COUNT(B35:C35)=2,B35-C35,"") | H35: =IFERROR(IF(AND(ISNUMBER(B35),INDEX($B$25:$B35,MATCH($A35-7,$A$25:$A35,1))<>0,INDEX($A$25:$A35,MATCH($A35-7,$A$25:$A35,1))<>0,$A35-INDEX($A$25:$A35,MATCH($A35-7,$A$25:$A35,1))<=10),B35-INDEX($B$25:$B35,MATCH($A35-7,$A$25:$A35,1)),""),"") | I35: =IFERROR(IF(AND(ISNUMBER(B35),INDEX($B$25:$B35,MATCH($A35-30,$A$25:$A35,1))<>0,INDEX($A$25:$A35,MATCH($A35-30,$A$25:$A35,1))<>0,$A35-INDEX($A$25:$A35,MATCH($A35-30,$A$25:$A35,1))<=33),B35-INDEX($B$25:$B35,MATCH($A35-30,$A$25:$A35,1)),""),"") | J35: =DATE(2026,11,3)-A35 | K35: 27 Dec
A36: 46019 | B36: 0.485 | C36: 0.495 | D36: =IF(COUNT(B36:C36)=2,B36+C36,"") | E36: =IF(ISNUMBER(B36),IFERROR(B36/$D36,""),"") | F36: =IF(ISNUMBER(C36),IFERROR(C36/$D36,""),"") | G36: =IF(COUNT(B36:C36)=2,B36-C36,"") | H36: =IFERROR(IF(AND(ISNUMBER(B36),INDEX($B$25:$B36,MATCH($A36-7,$A$25:$A36,1))<>0,INDEX($A$25:$A36,MATCH($A36-7,$A$25:$A36,1))<>0,$A36-INDEX($A$25:$A36,MATCH($A36-7,$A$25:$A36,1))<=10),B36-INDEX($B$25:$B36,MATCH($A36-7,$A$25:$A36,1)),""),"") | I36: =IFERROR(IF(AND(ISNUMBER(B36),INDEX($B$25:$B36,MATCH($A36-30,$A$25:$A36,1))<>0,INDEX($A$25:$A36,MATCH($A36-30,$A$25:$A36,1))<>0,$A36-INDEX($A$25:$A36,MATCH($A36-30,$A$25:$A36,1))<=33),B36-INDEX($B$25:$B36,MATCH($A36-30,$A$25:$A36,1)),""),"") | J36: =DATE(2026,11,3)-A36 | K36: 28 Dec
... A128: 46121 | B128: 0.735 | C128: 0.265 | D128: =IF(COUNT(B128:C128)=2,B128+C128,"") | E128: =IF(ISNUMBER(B128),IFERROR(B128/$D128,""),"") | F128: =IF(ISNUMBER(C128),IFERROR(C128/$D128,""),"") | G128: =IF(COUNT(B128:C128)=2,B128-C128,"") | H128: =IFERROR(IF(AND(ISNUMBER(B128),INDEX($B$25:$B128,MATCH($A128-7,$A$25:$A128,1))<>0,INDEX($A$25:$A128,MATCH($A128-7,$A$25:$A128,1))<>0,$A128-INDEX($A$25:$A128,MATCH($A128-7,$A$25:$A128,1))<=10),B128-INDEX($B$25:$B128,MATCH($A128-7,$A$25:$A128,1)),""),"") | I128: =IFERROR(IF(AND(ISNUMBER(B128),INDEX($B$25:$B128,MATCH($A128-30,$A$25:$A128,1))<>0,INDEX($A$25:$A128,MATCH($A128-30,$A$25:$A128,1))<>0,$A128-INDEX($A$25:$A128,MATCH($A128-30,$A$25:$A128,1))<=33),B128-INDEX($B$25:$B128,MATCH($A128-30,$A$25:$A128,1)),""),"") | J128: =DATE(2026,11,3)-A128 | K128: 09 Apr
A129: 46130 | B129: 0.745 | D129: =IF(COUNT(B129:C129)=2,B129+C129,"") | E129: =IF(ISNUMBER(B129),IFERROR(B129/$D129,""),"") | F129: =IF(ISNUMBER(C129),IFERROR(C129/$D129,""),"") | G129: =IF(COUNT(B129:C129)=2,B129-C129,"") | H129: =IFERROR(IF(AND(ISNUMBER(B129),INDEX($B$25:$B129,MATCH($A129-7,$A$25:$A129,1))<>0,INDEX($A$25:$A129,MATCH($A129-7,$A$25:$A129,1))<>0,$A129-INDEX($A$25:$A129,MATCH($A129-7,$A$25:$A129,1))<=10),B129-INDEX($B$25:$B129,MATCH($A129-7,$A$25:$A129,1)),""),"") | I129: =IFERROR(IF(AND(ISNUMBER(B129),INDEX($B$25:$B129,MATCH($A129-30,$A$25:$A129,1))<>0,INDEX($A$25:$A129,MATCH($A129-30,$A$25:$A129,1))<>0,$A129-INDEX($A$25:$A129,MATCH($A129-30,$A$25:$A129,1))<=33),B129-INDEX($B$25:$B129,MATCH($A129-30,$A$25:$A129,1)),""),"") | J129: =DATE(2026,11,3)-A129 | K129: 18 Apr
A130: 46134 | B130: 0.715 | C130: 0.29 | D130: =IF(COUNT(B130:C130)=2,B130+C130,"") | E130: =IF(ISNUMBER(B130),IFERROR(B130/$D130,""),"") | F130: =IF(ISNUMBER(C130),IFERROR(C130/$D130,""),"") | G130: =IF(COUNT(B130:C130)=2,B130-C130,"") | H130: =IFERROR(IF(AND(ISNUMBER(B130),INDEX($B$25:$B130,MATCH($A130-7,$A$25:$A130,1))<>0,INDEX($A$25:$A130,MATCH($A130-7,$A$25:$A130,1))<>0,$A130-INDEX($A$25:$A130,MATCH($A130-7,$A$25:$A130,1))<=10),B130-INDEX($B$25:$B130,MATCH($A130-7,$A$25:$A130,1)),""),"") | I130: =IFERROR(IF(AND(ISNUMBER(B130),INDEX($B$25:$B130,MATCH($A130-30,$A$25:$A130,1))<>0,INDEX($A$25:$A130,MATCH($A130-30,$A$25:$A130,1))<>0,$A130-INDEX($A$25:$A130,MATCH($A130-30,$A$25:$A130,1))<=33),B130-INDEX($B$25:$B130,MATCH($A130-30,$A$25:$A130,1)),""),"") | J130: =DATE(2026,11,3)-A130 | K130: 22 Apr
A131: 46135 | B131: 0.67 | C131: 0.24 | D131: =IF(COUNT(B131:C131)=2,B131+C131,"") | E131: =IF(ISNUMBER(B131),IFERROR(B131/$D131,""),"") | F131: =IF(ISNUMBER(C131),IFERROR(C131/$D131,""),"") | G131: =IF(COUNT(B131:C131)=2,B131-C131,"") | H131: =IFERROR(IF(AND(ISNUMBER(B131),INDEX($B$25:$B131,MATCH($A131-7,$A$25:$A131,1))<>0,INDEX($A$25:$A131,MATCH($A131-7,$A$25:$A131,1))<>0,$A131-INDEX($A$25:$A131,MATCH($A131-7,$A$25:$A131,1))<=10),B131-INDEX($B$25:$B131,MATCH($A131-7,$A$25:$A131,1)),""),"") | I131: =IFERROR(IF(AND(ISNUMBER(B131),INDEX($B$25:$B131,MATCH($A131-30,$A$25:$A131,1))<>0,INDEX($A$25:$A131,MATCH($A131-30,$A$25:$A131,1))<>0,$A131-INDEX($A$25:$A131,MATCH($A131-30,$A$25:$A131,1))<=33),B131-INDEX($B$25:$B131,MATCH($A131-30,$A$25:$A131,1)),""),"") | J131: =DATE(2026,11,3)-A131 | K131: 23 Apr
A132: 46136 | B132: 0.685 | C132: 0.245 | D132: =IF(COUNT(B132:C132)=2,B132+C132,"") | E132: =IF(ISNUMBER(B132),IFERROR(B132/$D132,""),"") | F132: =IF(ISNUMBER(C132),IFERROR(C132/$D132,""),"") | G132: =IF(COUNT(B132:C132)=2,B132-C132,"") | H132: =IFERROR(IF(AND(ISNUMBER(B132),INDEX($B$25:$B132,MATCH($A132-7,$A$25:$A132,1))<>0,INDEX($A$25:$A132,MATCH($A132-7,$A$25:$A132,1))<>0,$A132-INDEX($A$25:$A132,MATCH($A132-7,$A$25:$A132,1))<=10),B132-INDEX($B$25:$B132,MATCH($A132-7,$A$25:$A132,1)),""),"") | I132: =IFERROR(IF(AND(ISNUMBER(B132),INDEX($B$25:$B132,MATCH($A132-30,$A$25:$A132,1))<>0,INDEX($A$25:$A132,MATCH($A132-30,$A$25:$A132,1))<>0,$A132-INDEX($A$25:$A132,MATCH($A132-30,$A$25:$A132,1))<=33),B132-INDEX($B$25:$B132,MATCH($A132-30,$A$25:$A132,1)),""),"") | J132: =DATE(2026,11,3)-A132 | K132: 24 Apr
A133: 46137 | B133: 0.725 | C133: 0.28 | D133: =IF(COUNT(B133:C133)=2,B133+C133,"") | E133: =IF(ISNUMBER(B133),IFERROR(B133/$D133,""),"") | F133: =IF(ISNUMBER(C133),IFERROR(C133/$D133,""),"") | G133: =IF(COUNT(B133:C133)=2,B133-C133,"") | H133: =IFERROR(IF(AND(ISNUMBER(B133),INDEX($B$25:$B133,MATCH($A133-7,$A$25:$A133,1))<>0,INDEX($A$25:$A133,MATCH($A133-7,$A$25:$A133,1))<>0,$A133-INDEX($A$25:$A133,MATCH($A133-7,$A$25:$A133,1))<=10),B133-INDEX($B$25:$B133,MATCH($A133-7,$A$25:$A133,1)),""),"") | I133: =IFERROR(IF(AND(ISNUMBER(B133),INDEX($B$25:$B133,MATCH($A133-30,$A$25:$A133,1))<>0,INDEX($A$25:$A133,MATCH($A133-30,$A$25:$A133,1))<>0,$A133-INDEX($A$25:$A133,MATCH($A133-30,$A$25:$A133,1))<=33),B133-INDEX($B$25:$B133,MATCH($A133-30,$A$25:$A133,1)),""),"") | J133: =DATE(2026,11,3)-A133 | K133: 25 Apr
A134: 46138 | B134: 0.705 | C134: 0.28 | D134: =IF(COUNT(B134:C134)=2,B134+C134,"") | E134: =IF(ISNUMBER(B134),IFERROR(B134/$D134,""),"") | F134: =IF(ISNUMBER(C134),IFERROR(C134/$D134,""),"") | G134: =IF(COUNT(B134:C134)=2,B134-C134,"") | H134: =IFERROR(IF(AND(ISNUMBER(B134),INDEX($B$25:$B134,MATCH($A134-7,$A$25:$A134,1))<>0,INDEX($A$25:$A134,MATCH($A134-7,$A$25:$A134,1))<>0,$A134-INDEX($A$25:$A134,MATCH($A134-7,$A$25:$A134,1))<=10),B134-INDEX($B$25:$B134,MATCH($A134-7,$A$25:$A134,1)),""),"") | I134: =IFERROR(IF(AND(ISNUMBER(B134),INDEX($B$25:$B134,MATCH($A134-30,$A$25:$A134,1))<>0,INDEX($A$25:$A134,MATCH($A134-30,$A$25:$A134,1))<>0,$A134-INDEX($A$25:$A134,MATCH($A134-30,$A$25:$A134,1))<=33),B134-INDEX($B$25:$B134,MATCH($A134-30,$A$25:$A134,1)),""),"") | J134: =DATE(2026,11,3)-A134 | K134: 26 Apr
A135: 46139 | B135: 0.72 | C135: 0.285 | D135: =IF(COUNT(B135:C135)=2,B135+C135,"") | E135: =IF(ISNUMBER(B135),IFERROR(B135/$D135,""),"") | F135: =IF(ISNUMBER(C135),IFERROR(C135/$D135,""),"") | G135: =IF(COUNT(B135:C135)=2,B135-C135,"") | H135: =IFERROR(IF(AND(ISNUMBER(B135),INDEX($B$25:$B135,MATCH($A135-7,$A$25:$A135,1))<>0,INDEX($A$25:$A135,MATCH($A135-7,$A$25:$A135,1))<>0,$A135-INDEX($A$25:$A135,MATCH($A135-7,$A$25:$A135,1))<=10),B135-INDEX($B$25:$B135,MATCH($A135-7,$A$25:$A135,1)),""),"") | I135: =IFERROR(IF(AND(ISNUMBER(B135),INDEX($B$25:$B135,MATCH($A135-30,$A$25:$A135,1))<>0,INDEX($A$25:$A135,MATCH($A135-30,$A$25:$A135,1))<>0,$A135-INDEX($A$25:$A135,MATCH($A135-30,$A$25:$A135,1))<=33),B135-INDEX($B$25:$B135,MATCH($A135-30,$A$25:$A135,1)),""),"") | J135: =DATE(2026,11,3)-A135 | K135: 27 Apr
A136: 46140 | B136: 0.725 | C136: 0.275 | D136: =IF(COUNT(B136:C136)=2,B136+C136,"") | E136: =IF(ISNUMBER(B136),IFERROR(B136/$D136,""),"") | F136: =IF(ISNUMBER(C136),IFERROR(C136/$D136,""),"") | G136: =IF(COUNT(B136:C136)=2,B136-C136,"") | H136: =IFERROR(IF(AND(ISNUMBER(B136),INDEX($B$25:$B136,MATCH($A136-7,$A$25:$A136,1))<>0,INDEX($A$25:$A136,MATCH($A136-7,$A$25:$A136,1))<>0,$A136-INDEX($A$25:$A136,MATCH($A136-7,$A$25:$A136,1))<=10),B136-INDEX($B$25:$B136,MATCH($A136-7,$A$25:$A136,1)),""),"") | I136: =IFERROR(IF(AND(ISNUMBER(B136),INDEX($B$25:$B136,MATCH($A136-30,$A$25:$A136,1))<>0,INDEX($A$25:$A136,MATCH($A136-30,$A$25:$A136,1))<>0,$A136-INDEX($A$25:$A136,MATCH($A136-30,$A$25:$A136,1))<=33),B136-INDEX($B$25:$B136,MATCH($A136-30,$A$25:$A136,1)),""),"") | J136: =DATE(2026,11,3)-A136 | K136: 28 Apr
A137: 46141 | B137: 0.705 | C137: 0.24 | D137: =IF(COUNT(B137:C137)=2,B137+C137,"") | E137: =IF(ISNUMBER(B137),IFERROR(B137/$D137,""),"") | F137: =IF(ISNUMBER(C137),IFERROR(C137/$D137,""),"") | G137: =IF(COUNT(B137:C137)=2,B137-C137,"") | H137: =IFERROR(IF(AND(ISNUMBER(B137),INDEX($B$25:$B137,MATCH($A137-7,$A$25:$A137,1))<>0,INDEX($A$25:$A137,MATCH($A137-7,$A$25:$A137,1))<>0,$A137-INDEX($A$25:$A137,MATCH($A137-7,$A$25:$A137,1))<=10),B137-INDEX($B$25:$B137,MATCH($A137-7,$A$25:$A137,1)),""),"") | I137: =IFERROR(IF(AND(ISNUMBER(B137),INDEX($B$25:$B137,MATCH($A137-30,$A$25:$A137,1))<>0,INDEX($A$25:$A137,MATCH($A137-30,$A$25:$A137,1))<>0,$A137-INDEX($A$25:$A137,MATCH($A137-30,$A$25:$A137,1))<=33),B137-INDEX($B$25:$B137,MATCH($A137-30,$A$25:$A137,1)),""),"") | J137: =DATE(2026,11,3)-A137 | K137: 29 Apr
A138: 46142 | B138: 0.495 | C138: 0.185 | D138: =IF(COUNT(B138:C138)=2,B138+C138,"") | E138: =IF(ISNUMBER(B138),IFERROR(B138/$D138,""),"") | F138: =IF(ISNUMBER(C138),IFERROR(C138/$D138,""),"") | G138: =IF(COUNT(B138:C138)=2,B138-C138,"") | H138: =IFERROR(IF(AND(ISNUMBER(B138),INDEX($B$25:$B138,MATCH($A138-7,$A$25:$A138,1))<>0,INDEX($A$25:$A138,MATCH($A138-7,$A$25:$A138,1))<>0,$A138-INDEX($A$25:$A138,MATCH($A138-7,$A$25:$A138,1))<=10),B138-INDEX($B$25:$B138,MATCH($A138-7,$A$25:$A138,1)),""),"") | I138: =IFERROR(IF(AND(ISNUMBER(B138),INDEX($B$25:$B138,MATCH($A138-30,$A$25:$A138,1))<>0,INDEX($A$25:$A138,MATCH($A138-30,$A$25:$A138,1))<>0,$A138-INDEX($A$25:$A138,MATCH($A138-30,$A$25:$A138,1))<=33),B138-INDEX($B$25:$B138,MATCH($A138-30,$A$25:$A138,1)),""),"") | J138: =DATE(2026,11,3)-A138 | K138: 30 Apr
A139: 46143 | B139: 0.715 | C139: 0.295 | D139: =IF(COUNT(B139:C139)=2,B139+C139,"") | E139: =IF(ISNUMBER(B139),IFERROR(B139/$D139,""),"") | F139: =IF(ISNUMBER(C139),IFERROR(C139/$D139,""),"") | G139: =IF(COUNT(B139:C139)=2,B139-C139,"") | H139: =IFERROR(IF(AND(ISNUMBER(B139),INDEX($B$25:$B139,MATCH($A139-7,$A$25:$A139,1))<>0,INDEX($A$25:$A139,MATCH($A139-7,$A$25:$A139,1))<>0,$A139-INDEX($A$25:$A139,MATCH($A139-7,$A$25:$A139,1))<=10),B139-INDEX($B$25:$B139,MATCH($A139-7,$A$25:$A139,1)),""),"") | I139: =IFERROR(IF(AND(ISNUMBER(B139),INDEX($B$25:$B139,MATCH($A139-30,$A$25:$A139,1))<>0,INDEX($A$25:$A139,MATCH($A139-30,$A$25:$A139,1))<>0,$A139-INDEX($A$25:$A139,MATCH($A139-30,$A$25:$A139,1))<=33),B139-INDEX($B$25:$B139,MATCH($A139-30,$A$25:$A139,1)),""),"") | J139: =DATE(2026,11,3)-A139 | K139: 01 May
A140: 46144 | B140: 0.7 | C140: 0.29 | D140: =IF(COUNT(B140:C140)=2,B140+C140,"") | E140: =IF(ISNUMBER(B140),IFERROR(B140/$D140,""),"") | F140: =IF(ISNUMBER(C140),IFERROR(C140/$D140,""),"") | G140: =IF(COUNT(B140:C140)=2,B140-C140,"") | H140: =IFERROR(IF(AND(ISNUMBER(B140),INDEX($B$25:$B140,MATCH($A140-7,$A$25:$A140,1))<>0,INDEX($A$25:$A140,MATCH($A140-7,$A$25:$A140,1))<>0,$A140-INDEX($A$25:$A140,MATCH($A140-7,$A$25:$A140,1))<=10),B140-INDEX($B$25:$B140,MATCH($A140-7,$A$25:$A140,1)),""),"") | I140: =IFERROR(IF(AND(ISNUMBER(B140),INDEX($B$25:$B140,MATCH($A140-30,$A$25:$A140,1))<>0,INDEX($A$25:$A140,MATCH($A140-30,$A$25:$A140,1))<>0,$A140-INDEX($A$25:$A140,MATCH($A140-30,$A$25:$A140,1))<=33),B140-INDEX($B$25:$B140,MATCH($A140-30,$A$25:$A140,1)),""),"") | J140: =DATE(2026,11,3)-A140 | K140: 02 May
A141: 46145 | B141: 0.56 | C141: 0.295 | D141: =IF(COUNT(B141:C141)=2,B141+C141,"") | E141: =IF(ISNUMBER(B141),IFERROR(B141/$D141,""),"") | F141: =IF(ISNUMBER(C141),IFERROR(C141/$D141,""),"") | G141: =IF(COUNT(B141:C141)=2,B141-C141,"") | H141: =IFERROR(IF(AND(ISNUMBER(B141),INDEX($B$25:$B141,MATCH($A141-7,$A$25:$A141,1))<>0,INDEX($A$25:$A141,MATCH($A141-7,$A$25:$A141,1))<>0,$A141-INDEX($A$25:$A141,MATCH($A141-7,$A$25:$A141,1))<=10),B141-INDEX($B$25:$B141,MATCH($A141-7,$A$25:$A141,1)),""),"") | I141: =IFERROR(IF(AND(ISNUMBER(B141),INDEX($B$25:$B141,MATCH($A141-30,$A$25:$A141,1))<>0,INDEX($A$25:$A141,MATCH($A141-30,$A$25:$A141,1))<>0,$A141-INDEX($A$25:$A141,MATCH($A141-30,$A$25:$A141,1))<=33),B141-INDEX($B$25:$B141,MATCH($A141-30,$A$25:$A141,1)),""),"") | J141: =DATE(2026,11,3)-A141 | K141: 03 May
... A227: 46231 | B227: 0.735 | C227: 0.24 | D227: =IF(COUNT(B227:C227)=2,B227+C227,"") | E227: =IF(ISNUMBER(B227),IFERROR(B227/$D227,""),"") | F227: =IF(ISNUMBER(C227),IFERROR(C227/$D227,""),"") | G227: =IF(COUNT(B227:C227)=2,B227-C227,"") | H227: =IFERROR(IF(AND(ISNUMBER(B227),INDEX($B$25:$B227,MATCH($A227-7,$A$25:$A227,1))<>0,INDEX($A$25:$A227,MATCH($A227-7,$A$25:$A227,1))<>0,$A227-INDEX($A$25:$A227,MATCH($A227-7,$A$25:$A227,1))<=10),B227-INDEX($B$25:$B227,MATCH($A227-7,$A$25:$A227,1)),""),"") | I227: =IFERROR(IF(AND(ISNUMBER(B227),INDEX($B$25:$B227,MATCH($A227-30,$A$25:$A227,1))<>0,INDEX($A$25:$A227,MATCH($A227-30,$A$25:$A227,1))<>0,$A227-INDEX($A$25:$A227,MATCH($A227-30,$A$25:$A227,1))<=33),B227-INDEX($B$25:$B227,MATCH($A227-30,$A$25:$A227,1)),""),"") | J227: =DATE(2026,11,3)-A227 | K227: 28 Jul
A228: 46232 | C228: 0.24 | D228: =IF(COUNT(B228:C228)=2,B228+C228,"") | E228: =IF(ISNUMBER(B228),IFERROR(B228/$D228,""),"") | F228: =IF(ISNUMBER(C228),IFERROR(C228/$D228,""),"") | G228: =IF(COUNT(B228:C228)=2,B228-C228,"") | H228: =IFERROR(IF(AND(ISNUMBER(B228),INDEX($B$25:$B228,MATCH($A228-7,$A$25:$A228,1))<>0,INDEX($A$25:$A228,MATCH($A228-7,$A$25:$A228,1))<>0,$A228-INDEX($A$25:$A228,MATCH($A228-7,$A$25:$A228,1))<=10),B228-INDEX($B$25:$B228,MATCH($A228-7,$A$25:$A228,1)),""),"") | I228: =IFERROR(IF(AND(ISNUMBER(B228),INDEX($B$25:$B228,MATCH($A228-30,$A$25:$A228,1))<>0,INDEX($A$25:$A228,MATCH($A228-30,$A$25:$A228,1))<>0,$A228-INDEX($A$25:$A228,MATCH($A228-30,$A$25:$A228,1))<=33),B228-INDEX($B$25:$B228,MATCH($A228-30,$A$25:$A228,1)),""),"") | J228: =DATE(2026,11,3)-A228 | K228: 29 Jul
A229: 46233 | B229: 0.74 | C229: 0.24 | D229: =IF(COUNT(B229:C229)=2,B229+C229,"") | E229: =IF(ISNUMBER(B229),IFERROR(B229/$D229,""),"") | F229: =IF(ISNUMBER(C229),IFERROR(C229/$D229,""),"") | G229: =IF(COUNT(B229:C229)=2,B229-C229,"") | H229: =IFERROR(IF(AND(ISNUMBER(B229),INDEX($B$25:$B229,MATCH($A229-7,$A$25:$A229,1))<>0,INDEX($A$25:$A229,MATCH($A229-7,$A$25:$A229,1))<>0,$A229-INDEX($A$25:$A229,MATCH($A229-7,$A$25:$A229,1))<=10),B229-INDEX($B$25:$B229,MATCH($A229-7,$A$25:$A229,1)),""),"") | I229: =IFERROR(IF(AND(ISNUMBER(B229),INDEX($B$25:$B229,MATCH($A229-30,$A$25:$A229,1))<>0,INDEX($A$25:$A229,MATCH($A229-30,$A$25:$A229,1))<>0,$A229-INDEX($A$25:$A229,MATCH($A229-30,$A$25:$A229,1))<=33),B229-INDEX($B$25:$B229,MATCH($A229-30,$A$25:$A229,1)),""),"") | J229: =DATE(2026,11,3)-A229 | K229: 30 Jul
A230: 46234 | B230: 0.735 | C230: 0.245 | D230: =IF(COUNT(B230:C230)=2,B230+C230,"") | E230: =IF(ISNUMBER(B230),IFERROR(B230/$D230,""),"") | F230: =IF(ISNUMBER(C230),IFERROR(C230/$D230,""),"") | G230: =IF(COUNT(B230:C230)=2,B230-C230,"") | H230: =IFERROR(IF(AND(ISNUMBER(B230),INDEX($B$25:$B230,MATCH($A230-7,$A$25:$A230,1))<>0,INDEX($A$25:$A230,MATCH($A230-7,$A$25:$A230,1))<>0,$A230-INDEX($A$25:$A230,MATCH($A230-7,$A$25:$A230,1))<=10),B230-INDEX($B$25:$B230,MATCH($A230-7,$A$25:$A230,1)),""),"") | I230: =IFERROR(IF(AND(ISNUMBER(B230),INDEX($B$25:$B230,MATCH($A230-30,$A$25:$A230,1))<>0,INDEX($A$25:$A230,MATCH($A230-30,$A$25:$A230,1))<>0,$A230-INDEX($A$25:$A230,MATCH($A230-30,$A$25:$A230,1))<=33),B230-INDEX($B$25:$B230,MATCH($A230-30,$A$25:$A230,1)),""),"") | J230: =DATE(2026,11,3)-A230 | K230: 31 Jul
A231: 46235 | B231: 0.77 | C231: 0.24 | D231: =IF(COUNT(B231:C231)=2,B231+C231,"") | E231: =IF(ISNUMBER(B231),IFERROR(B231/$D231,""),"") | F231: =IF(ISNUMBER(C231),IFERROR(C231/$D231,""),"") | G231: =IF(COUNT(B231:C231)=2,B231-C231,"") | H231: =IFERROR(IF(AND(ISNUMBER(B231),INDEX($B$25:$B231,MATCH($A231-7,$A$25:$A231,1))<>0,INDEX($A$25:$A231,MATCH($A231-7,$A$25:$A231,1))<>0,$A231-INDEX($A$25:$A231,MATCH($A231-7,$A$25:$A231,1))<=10),B231-INDEX($B$25:$B231,MATCH($A231-7,$A$25:$A231,1)),""),"") | I231: =IFERROR(IF(AND(ISNUMBER(B231),INDEX($B$25:$B231,MATCH($A231-30,$A$25:$A231,1))<>0,INDEX($A$25:$A231,MATCH($A231-30,$A$25:$A231,1))<>0,$A231-INDEX($A$25:$A231,MATCH($A231-30,$A$25:$A231,1))<=33),B231-INDEX($B$25:$B231,MATCH($A231-30,$A$25:$A231,1)),""),"") | J231: =DATE(2026,11,3)-A231 | K231: 01 Aug
A232: 46236 | B232: 0.77 | C232: 0.24 | D232: =IF(COUNT(B232:C232)=2,B232+C232,"") | E232: =IF(ISNUMBER(B232),IFERROR(B232/$D232,""),"") | F232: =IF(ISNUMBER(C232),IFERROR(C232/$D232,""),"") | G232: =IF(COUNT(B232:C232)=2,B232-C232,"") | H232: =IFERROR(IF(AND(ISNUMBER(B232),INDEX($B$25:$B232,MATCH($A232-7,$A$25:$A232,1))<>0,INDEX($A$25:$A232,MATCH($A232-7,$A$25:$A232,1))<>0,$A232-INDEX($A$25:$A232,MATCH($A232-7,$A$25:$A232,1))<=10),B232-INDEX($B$25:$B232,MATCH($A232-7,$A$25:$A232,1)),""),"") | I232: =IFERROR(IF(AND(ISNUMBER(B232),INDEX($B$25:$B232,MATCH($A232-30,$A$25:$A232,1))<>0,INDEX($A$25:$A232,MATCH($A232-30,$A$25:$A232,1))<>0,$A232-INDEX($A$25:$A232,MATCH($A232-30,$A$25:$A232,1))<=33),B232-INDEX($B$25:$B232,MATCH($A232-30,$A$25:$A232,1)),""),"") | J232: =DATE(2026,11,3)-A232 | K232: 02 Aug
A233: 46237 | B233: 0.77 | C233: 0.235 | D233: =IF(COUNT(B233:C233)=2,B233+C233,"") | E233: =IF(ISNUMBER(B233),IFERROR(B233/$D233,""),"") | F233: =IF(ISNUMBER(C233),IFERROR(C233/$D233,""),"") | G233: =IF(COUNT(B233:C233)=2,B233-C233,"") | H233: =IFERROR(IF(AND(ISNUMBER(B233),INDEX($B$25:$B233,MATCH($A233-7,$A$25:$A233,1))<>0,INDEX($A$25:$A233,MATCH($A233-7,$A$25:$A233,1))<>0,$A233-INDEX($A$25:$A233,MATCH($A233-7,$A$25:$A233,1))<=10),B233-INDEX($B$25:$B233,MATCH($A233-7,$A$25:$A233,1)),""),"") | I233: =IFERROR(IF(AND(ISNUMBER(B233),INDEX($B$25:$B233,MATCH($A233-30,$A$25:$A233,1))<>0,INDEX($A$25:$A233,MATCH($A233-30,$A$25:$A233,1))<>0,$A233-INDEX($A$25:$A233,MATCH($A233-30,$A$25:$A233,1))<=33),B233-INDEX($B$25:$B233,MATCH($A233-30,$A$25:$A233,1)),""),"") | J233: =DATE(2026,11,3)-A233 | K233: 03 Aug
A234: 46238 | B234: 0.765 | C234: 0.235 | D234: =IF(COUNT(B234:C234)=2,B234+C234,"") | E234: =IF(ISNUMBER(B234),IFERROR(B234/$D234,""),"") | F234: =IF(ISNUMBER(C234),IFERROR(C234/$D234,""),"") | G234: =IF(COUNT(B234:C234)=2,B234-C234,"") | H234: =IFERROR(IF(AND(ISNUMBER(B234),INDEX($B$25:$B234,MATCH($A234-7,$A$25:$A234,1))<>0,INDEX($A$25:$A234,MATCH($A234-7,$A$25:$A234,1))<>0,$A234-INDEX($A$25:$A234,MATCH($A234-7,$A$25:$A234,1))<=10),B234-INDEX($B$25:$B234,MATCH($A234-7,$A$25:$A234,1)),""),"") | I234: =IFERROR(IF(AND(ISNUMBER(B234),INDEX($B$25:$B234,MATCH($A234-30,$A$25:$A234,1))<>0,INDEX($A$25:$A234,MATCH($A234-30,$A$25:$A234,1))<>0,$A234-INDEX($A$25:$A234,MATCH($A234-30,$A$25:$A234,1))<=33),B234-INDEX($B$25:$B234,MATCH($A234-30,$A$25:$A234,1)),""),"") | J234: =DATE(2026,11,3)-A234 | K234: 04 Aug
A235: 46239 | B235: 0.775 | C235: 0.23 | D235: =IF(COUNT(B235:C235)=2,B235+C235,"") | E235: =IF(ISNUMBER(B235),IFERROR(B235/$D235,""),"") | F235: =IF(ISNUMBER(C235),IFERROR(C235/$D235,""),"") | G235: =IF(COUNT(B235:C235)=2,B235-C235,"") | H235: =IFERROR(IF(AND(ISNUMBER(B235),INDEX($B$25:$B235,MATCH($A235-7,$A$25:$A235,1))<>0,INDEX($A$25:$A235,MATCH($A235-7,$A$25:$A235,1))<>0,$A235-INDEX($A$25:$A235,MATCH($A235-7,$A$25:$A235,1))<=10),B235-INDEX($B$25:$B235,MATCH($A235-7,$A$25:$A235,1)),""),"") | I235: =IFERROR(IF(AND(ISNUMBER(B235),INDEX($B$25:$B235,MATCH($A235-30,$A$25:$A235,1))<>0,INDEX($A$25:$A235,MATCH($A235-30,$A$25:$A235,1))<>0,$A235-INDEX($A$25:$A235,MATCH($A235-30,$A$25:$A235,1))<=33),B235-INDEX($B$25:$B235,MATCH($A235-30,$A$25:$A235,1)),""),"") | J235: =DATE(2026,11,3)-A235 | K235: 05 Aug
A236: 46240 | B236: 0.76 | C236: 0.23 | D236: =IF(COUNT(B236:C236)=2,B236+C236,"") | E236: =IF(ISNUMBER(B236),IFERROR(B236/$D236,""),"") | F236: =IF(ISNUMBER(C236),IFERROR(C236/$D236,""),"") | G236: =IF(COUNT(B236:C236)=2,B236-C236,"") | H236: =IFERROR(IF(AND(ISNUMBER(B236),INDEX($B$25:$B236,MATCH($A236-7,$A$25:$A236,1))<>0,INDEX($A$25:$A236,MATCH($A236-7,$A$25:$A236,1))<>0,$A236-INDEX($A$25:$A236,MATCH($A236-7,$A$25:$A236,1))<=10),B236-INDEX($B$25:$B236,MATCH($A236-7,$A$25:$A236,1)),""),"") | I236: =IFERROR(IF(AND(ISNUMBER(B236),INDEX($B$25:$B236,MATCH($A236-30,$A$25:$A236,1))<>0,INDEX($A$25:$A236,MATCH($A236-30,$A$25:$A236,1))<>0,$A236-INDEX($A$25:$A236,MATCH($A236-30,$A$25:$A236,1))<=33),B236-INDEX($B$25:$B236,MATCH($A236-30,$A$25:$A236,1)),""),"") | J236: =DATE(2026,11,3)-A236 | K236: 06 Aug
A237: 46241 | B237: 0.76 | C237: 0.245 | D237: =IF(COUNT(B237:C237)=2,B237+C237,"") | E237: =IF(ISNUMBER(B237),IFERROR(B237/$D237,""),"") | F237: =IF(ISNUMBER(C237),IFERROR(C237/$D237,""),"") | G237: =IF(COUNT(B237:C237)=2,B237-C237,"") | H237: =IFERROR(IF(AND(ISNUMBER(B237),INDEX($B$25:$B237,MATCH($A237-7,$A$25:$A237,1))<>0,INDEX($A$25:$A237,MATCH($A237-7,$A$25:$A237,1))<>0,$A237-INDEX($A$25:$A237,MATCH($A237-7,$A$25:$A237,1))<=10),B237-INDEX($B$25:$B237,MATCH($A237-7,$A$25:$A237,1)),""),"") | I237: =IFERROR(IF(AND(ISNUMBER(B237),INDEX($B$25:$B237,MATCH($A237-30,$A$25:$A237,1))<>0,INDEX($A$25:$A237,MATCH($A237-30,$A$25:$A237,1))<>0,$A237-INDEX($A$25:$A237,MATCH($A237-30,$A$25:$A237,1))<=33),B237-INDEX($B$25:$B237,MATCH($A237-30,$A$25:$A237,1)),""),"") | J237: =DATE(2026,11,3)-A237 | K237: 07 Aug
A238: 46242 | B238: 0.76 | C238: 0.245 | D238: =IF(COUNT(B238:C238)=2,B238+C238,"") | E238: =IF(ISNUMBER(B238),IFERROR(B238/$D238,""),"") | F238: =IF(ISNUMBER(C238),IFERROR(C238/$D238,""),"") | G238: =IF(COUNT(B238:C238)=2,B238-C238,"") | H238: =IFERROR(IF(AND(ISNUMBER(B238),INDEX($B$25:$B238,MATCH($A238-7,$A$25:$A238,1))<>0,INDEX($A$25:$A238,MATCH($A238-7,$A$25:$A238,1))<>0,$A238-INDEX($A$25:$A238,MATCH($A238-7,$A$25:$A238,1))<=10),B238-INDEX($B$25:$B238,MATCH($A238-7,$A$25:$A238,1)),""),"") | I238: =IFERROR(IF(AND(ISNUMBER(B238),INDEX($B$25:$B238,MATCH($A238-30,$A$25:$A238,1))<>0,INDEX($A$25:$A238,MATCH($A238-30,$A$25:$A238,1))<>0,$A238-INDEX($A$25:$A238,MATCH($A238-30,$A$25:$A238,1))<=33),B238-INDEX($B$25:$B238,MATCH($A238-30,$A$25:$A238,1)),""),"") | J238: =DATE(2026,11,3)-A238 | K238: 08 Aug
A239: 46243 | B239: 0.76 | C239: 0.24 | D239: =IF(COUNT(B239:C239)=2,B239+C239,"") | E239: =IF(ISNUMBER(B239),IFERROR(B239/$D239,""),"") | F239: =IF(ISNUMBER(C239),IFERROR(C239/$D239,""),"") | G239: =IF(COUNT(B239:C239)=2,B239-C239,"") | H239: =IFERROR(IF(AND(ISNUMBER(B239),INDEX($B$25:$B239,MATCH($A239-7,$A$25:$A239,1))<>0,INDEX($A$25:$A239,MATCH($A239-7,$A$25:$A239,1))<>0,$A239-INDEX($A$25:$A239,MATCH($A239-7,$A$25:$A239,1))<=10),B239-INDEX($B$25:$B239,MATCH($A239-7,$A$25:$A239,1)),""),"") | I239: =IFERROR(IF(AND(ISNUMBER(B239),INDEX($B$25:$B239,MATCH($A239-30,$A$25:$A239,1))<>0,INDEX($A$25:$A239,MATCH($A239-30,$A$25:$A239,1))<>0,$A239-INDEX($A$25:$A239,MATCH($A239-30,$A$25:$A239,1))<=33),B239-INDEX($B$25:$B239,MATCH($A239-30,$A$25:$A239,1)),""),"") | J239: =DATE(2026,11,3)-A239 | K239: 09 Aug
A240: 46244 | B240: 0.76 | C240: 0.24 | D240: =IF(COUNT(B240:C240)=2,B240+C240,"") | E240: =IF(ISNUMBER(B240),IFERROR(B240/$D240,""),"") | F240: =IF(ISNUMBER(C240),IFERROR(C240/$D240,""),"") | G240: =IF(COUNT(B240:C240)=2,B240-C240,"") | H240: =IFERROR(IF(AND(ISNUMBER(B240),INDEX($B$25:$B240,MATCH($A240-7,$A$25:$A240,1))<>0,INDEX($A$25:$A240,MATCH($A240-7,$A$25:$A240,1))<>0,$A240-INDEX($A$25:$A240,MATCH($A240-7,$A$25:$A240,1))<=10),B240-INDEX($B$25:$B240,MATCH($A240-7,$A$25:$A240,1)),""),"") | I240: =IFERROR(IF(AND(ISNUMBER(B240),INDEX($B$25:$B240,MATCH($A240-30,$A$25:$A240,1))<>0,INDEX($A$25:$A240,MATCH($A240-30,$A$25:$A240,1))<>0,$A240-INDEX($A$25:$A240,MATCH($A240-30,$A$25:$A240,1))<=33),B240-INDEX($B$25:$B240,MATCH($A240-30,$A$25:$A240,1)),""),"") | J240: =DATE(2026,11,3)-A240 | K240: 10 Aug
... A303: 46307 | B303: 0.86 | C303: 0.135 | D303: =IF(COUNT(B303:C303)=2,B303+C303,"") | E303: =IF(ISNUMBER(B303),IFERROR(B303/$D303,""),"") | F303: =IF(ISNUMBER(C303),IFERROR(C303/$D303,""),"") | G303: =IF(COUNT(B303:C303)=2,B303-C303,"") | H303: =IFERROR(IF(AND(ISNUMBER(B303),INDEX($B$25:$B303,MATCH($A303-7,$A$25:$A303,1))<>0,INDEX($A$25:$A303,MATCH($A303-7,$A$25:$A303,1))<>0,$A303-INDEX($A$25:$A303,MATCH($A303-7,$A$25:$A303,1))<=10),B303-INDEX($B$25:$B303,MATCH($A303-7,$A$25:$A303,1)),""),"") | I303: =IFERROR(IF(AND(ISNUMBER(B303),INDEX($B$25:$B303,MATCH($A303-30,$A$25:$A303,1))<>0,INDEX($A$25:$A303,MATCH($A303-30,$A$25:$A303,1))<>0,$A303-INDEX($A$25:$A303,MATCH($A303-30,$A$25:$A303,1))<=33),B303-INDEX($B$25:$B303,MATCH($A303-30,$A$25:$A303,1)),""),"") | J303: =DATE(2026,11,3)-A303 | K303: 12 Oct

Sheet Kalshi
A1: Kalshi — PA-07 House Race Winner (HOUSEPA7-26)
A2: Source: Kalshi Trade API v2 (api.elections.kalshi.com), RSA-signed requests. Prices are per-$1 contracts; price = implied probability. Pulled 2026-10-12 02:24 UTC.
A4: MARKET METADATA
A5: Field | B5: Democratic (YES) | C5: Republican (YES)
A6: Market ticker | B6: HOUSEPA7-26-D | C6: HOUSEPA7-26-R
A7: Event ticker | B7: HOUSEPA7-26 | C7: HOUSEPA7-26
A8: Question | B8: Will Democratic win the House race for PA-7? | C8: Will Republican win the House race for PA-7?
A9: Candidate | B9: Bob Brooks | C9: Ryan Mackenzie
A10: Status | B10: active | C10: active
A11: Opened | B11: 2025-07-01 | C11: 2025-07-01
A12: Close time | B12: 2027-11-03 | C12: 2027-11-03
A13: Candlesticks pulled | B13: 442 | C13: 429
A15: LIVE ORDER BOOK SNAPSHOT
A16: Outcome | B16: YES Best Bid | C16: NO Best Bid | D16: YES Best Ask (1−NO bid) | E16: Mid | F16: Bid-Ask Spread | G16: YES Bid Size ($) | H16: Implied Prob (normalised)
A17: Democratic — Bob Brooks | B17: 0.86 | C17: 0.13 | D17: =1-C17 | E17: =(B17+D17)/2 | F17: =D17-B17 | G17: 14 | H17: =IFERROR(E17/$E$19,"")
A18: Republican — Ryan Mackenzie | B18: 0.12 | C18: 0.86 | D18: =1-C18 | E18: =(B18+D18)/2 | F18: =D18-B18 | G18: 10080 | H18: =IFERROR(E18/$E$19,"")
A19: Sum of mids (100% = no vig) | E19: =SUM(E17:E18) | F19: =E19-1 | H19: =SUM(H17:H18)
A21: ORDER BOOK DEPTH (top 5 levels each side)
A22: Level | B22: Dem YES Bid | C22: Dem YES Size ($) | D22: Dem NO Bid | E22: Dem NO Size ($) | F22: Rep YES Bid | G22: Rep YES Size ($) | H22: Rep NO Bid | I22: Rep NO Size ($)
A23: 1 | B23: 0.86 | C23: 14 | D23: 0.13 | E23: 99.89 | F23: 0.12 | G23: 10080 | H23: 0.86 | I23: 50065.28
A24: 2 | B24: 0.85 | C24: 50065.32 | D24: 0.12 | E24: 10560 | F24: 0.11 | G24: 539 | H24: 0.85 | I24: 10
A25: 3 | B25: 0.84 | C25: 1171.55 | D25: 0.11 | E25: 50478.69 | F25: 0.1 | G25: 50400 | H25: 0.84 | I25: 1415
A26: 4 | B26: 0.83 | C26: 73.93 | D26: 0.1 | E26: 79 | F26: 0.09 | G26: 1000 | H26: 0.83 | I26: 5107
A27: 5 | B27: 0.82 | C27: 15268 | D27: 0.091 | E27: 50 | F27: 0.075 | G27: 5000 | H27: 0.82 | I27: 10050
A29: DAILY PRICE HISTORY (1-day candlesticks)
A30: Date | B30: Dem YES Bid | C30: Dem YES Ask | D30: Dem Mid | E30: Rep YES Bid | F30: Rep YES Ask | G30: Rep Mid | H30: Sum of Mids | I30: Dem Normalised | J30: Dem − Rep Spread | K30: Volume (contracts) | L30: Open Interest | M30: Axis label
A31: 45840 | B31: 0.61 | C31: 0.66 | D31: =IF(COUNT(B31:C31)=2,(B31+C31)/2,"") | E31: 0.3 | F31: 0.35 | G31: =IF(COUNT(E31:F31)=2,(E31+F31)/2,"") | H31: =IF(AND(ISNUMBER(D31),ISNUMBER(G31)),D31+G31,"") | I31: =IFERROR(D31/H31,"") | J31: =IF(AND(ISNUMBER(D31),ISNUMBER(G31)),D31-G31,"") | K31: 0 | L31: 0 | M31: 02 Jul
A32: 45841 | B32: 0.61 | C32: 0.66 | D32: =IF(COUNT(B32:C32)=2,(B32+C32)/2,"") | E32: 0.3 | F32: 0.35 | G32: =IF(COUNT(E32:F32)=2,(E32+F32)/2,"") | H32: =IF(AND(ISNUMBER(D32),ISNUMBER(G32)),D32+G32,"") | I32: =IFERROR(D32/H32,"") | J32: =IF(AND(ISNUMBER(D32),ISNUMBER(G32)),D32-G32,"") | K32: 0 | L32: 0 | M32: 03 Jul
A33: 45842 | B33: 0.61 | C33: 0.66 | D33: =IF(COUNT(B33:C33)=2,(B33+C33)/2,"") | E33: 0.3 | F33: 0.35 | G33: =IF(COUNT(E33:F33)=2,(E33+F33)/2,"") | H33: =IF(AND(ISNUMBER(D33),ISNUMBER(G33)),D33+G33,"") | I33: =IFERROR(D33/H33,"") | J33: =IF(AND(ISNUMBER(D33),ISNUMBER(G33)),D33-G33,"") | K33: 0 | L33: 0 | M33: 04 Jul
A34: 45843 | B34: 0.61 | C34: 0.66 | D34: =IF(COUNT(B34:C34)=2,(B34+C34)/2,"") | E34: 0.3 | F34: 0.35 | G34: =IF(COUNT(E34:F34)=2,(E34+F34)/2,"") | H34: =IF(AND(ISNUMBER(D34),ISNUMBER(G34)),D34+G34,"") | I34: =IFERROR(D34/H34,"") | J34: =IF(AND(ISNUMBER(D34),ISNUMBER(G34)),D34-G34,"") | K34: 0 | L34: 0 | M34: 05 Jul
A35: 45844 | B35: 0.61 | C35: 0.66 | D35: =IF(COUNT(B35:C35)=2,(B35+C35)/2,"") | E35: 0.31 | F35: 0.36 | G35: =IF(COUNT(E35:F35)=2,(E35+F35)/2,"") | H35: =IF(AND(ISNUMBER(D35),ISNUMBER(G35)),D35+G35,"") | I35: =IFERROR(D35/H35,"") | J35: =IF(AND(ISNUMBER(D35),ISNUMBER(G35)),D35-G35,"") | K35: 298 | L35: 152 | M35: 06 Jul
A36: 45845 | B36: 0.61 | C36: 0.66 | D36: =IF(COUNT(B36:C36)=2,(B36+C36)/2,"") | E36: 0.31 | F36: 0.36 | G36: =IF(COUNT(E36:F36)=2,(E36+F36)/2,"") | H36: =IF(AND(ISNUMBER(D36),ISNUMBER(G36)),D36+G36,"") | I36: =IFERROR(D36/H36,"") | J36: =IF(AND(ISNUMBER(D36),ISNUMBER(G36)),D36-G36,"") | K36: 0 | L36: 152 | M36: 07 Jul
A37: 45846 | B37: 0.61 | C37: 0.66 | D37: =IF(COUNT(B37:C37)=2,(B37+C37)/2,"") | E37: 0.31 | F37: 0.36 | G37: =IF(COUNT(E37:F37)=2,(E37+F37)/2,"") | H37: =IF(AND(ISNUMBER(D37),ISNUMBER(G37)),D37+G37,"") | I37: =IFERROR(D37/H37,"") | J37: =IF(AND(ISNUMBER(D37),ISNUMBER(G37)),D37-G37,"") | K37: 0 | L37: 152 | M37: 08 Jul
A38: 45847 | B38: 0.61 | C38: 0.66 | D38: =IF(COUNT(B38:C38)=2,(B38+C38)/2,"") | E38: 0.31 | F38: 0.36 | G38: =IF(COUNT(E38:F38)=2,(E38+F38)/2,"") | H38: =IF(AND(ISNUMBER(D38),ISNUMBER(G38)),D38+G38,"") | I38: =IFERROR(D38/H38,"") | J38: =IF(AND(ISNUMBER(D38),ISNUMBER(G38)),D38-G38,"") | K38: 0 | L38: 152 | M38: 09 Jul
A39: 45848 | B39: 0.61 | C39: 0.66 | D39: =IF(COUNT(B39:C39)=2,(B39+C39)/2,"") | E39: 0.31 | F39: 0.36 | G39: =IF(COUNT(E39:F39)=2,(E39+F39)/2,"") | H39: =IF(AND(ISNUMBER(D39),ISNUMBER(G39)),D39+G39,"") | I39: =IFERROR(D39/H39,"") | J39: =IF(AND(ISNUMBER(D39),ISNUMBER(G39)),D39-G39,"") | K39: 0 | L39: 152 | M39: 10 Jul
A40: 45849 | B40: 0.61 | C40: 0.66 | D40: =IF(COUNT(B40:C40)=2,(B40+C40)/2,"") | E40: 0.31 | F40: 0.36 | G40: =IF(COUNT(E40:F40)=2,(E40+F40)/2,"") | H40: =IF(AND(ISNUMBER(D40),ISNUMBER(G40)),D40+G40,"") | I40: =IFERROR(D40/H40,"") | J40: =IF(AND(ISNUMBER(D40),ISNUMBER(G40)),D40-G40,"") | K40: 0 | L40: 152 | M40: 11 Jul
A41: 45850 | B41: 0.61 | C41: 0.66 | D41: =IF(COUNT(B41:C41)=2,(B41+C41)/2,"") | E41: 0.31 | F41: 0.36 | G41: =IF(COUNT(E41:F41)=2,(E41+F41)/2,"") | H41: =IF(AND(ISNUMBER(D41),ISNUMBER(G41)),D41+G41,"") | I41: =IFERROR(D41/H41,"") | J41: =IF(AND(ISNUMBER(D41),ISNUMBER(G41)),D41-G41,"") | K41: 0 | L41: 152 | M41: 12 Jul
A42: 45851 | B42: 0.61 | C42: 0.66 | D42: =IF(COUNT(B42:C42)=2,(B42+C42)/2,"") | E42: 0.31 | F42: 0.36 | G42: =IF(COUNT(E42:F42)=2,(E42+F42)/2,"") | H42: =IF(AND(ISNUMBER(D42),ISNUMBER(G42)),D42+G42,"") | I42: =IFERROR(D42/H42,"") | J42: =IF(AND(ISNUMBER(D42),ISNUMBER(G42)),D42-G42,"") | K42: 0 | L42: 152 | M42: 13 Jul
... A267: 46076 | B267: 0.7 | C267: 0.74 | D267: =IF(COUNT(B267:C267)=2,(B267+C267)/2,"") | E267: 0.22 | F267: 0.26 | G267: =IF(COUNT(E267:F267)=2,(E267+F267)/2,"") | H267: =IF(AND(ISNUMBER(D267),ISNUMBER(G267)),D267+G267,"") | I267: =IFERROR(D267/H267,"") | J267: =IF(AND(ISNUMBER(D267),ISNUMBER(G267)),D267-G267,"") | K267: 0 | L267: 6710 | M267: 23 Feb
A268: 46077 | B268: 0.7 | C268: 0.74 | D268: =IF(COUNT(B268:C268)=2,(B268+C268)/2,"") | G268: =IF(COUNT(E268:F268)=2,(E268+F268)/2,"") | H268: =IF(AND(ISNUMBER(D268),ISNUMBER(G268)),D268+G268,"") | I268: =IFERROR(D268/H268,"") | J268: =IF(AND(ISNUMBER(D268),ISNUMBER(G268)),D268-G268,"") | K268: 0 | L268: 6710 | M268: 24 Feb
A269: 46078 | B269: 0.69 | C269: 0.75 | D269: =IF(COUNT(B269:C269)=2,(B269+C269)/2,"") | E269: 0.22 | F269: 0.26 | G269: =IF(COUNT(E269:F269)=2,(E269+F269)/2,"") | H269: =IF(AND(ISNUMBER(D269),ISNUMBER(G269)),D269+G269,"") | I269: =IFERROR(D269/H269,"") | J269: =IF(AND(ISNUMBER(D269),ISNUMBER(G269)),D269-G269,"") | K269: 55 | L269: 6743 | M269: 25 Feb
A270: 46079 | B270: 0.69 | C270: 0.75 | D270: =IF(COUNT(B270:C270)=2,(B270+C270)/2,"") | E270: 0.22 | F270: 0.26 | G270: =IF(COUNT(E270:F270)=2,(E270+F270)/2,"") | H270: =IF(AND(ISNUMBER(D270),ISNUMBER(G270)),D270+G270,"") | I270: =IFERROR(D270/H270,"") | J270: =IF(AND(ISNUMBER(D270),ISNUMBER(G270)),D270-G270,"") | K270: 46 | L270: 6760 | M270: 26 Feb
A271: 46080 | B271: 0.69 | C271: 0.75 | D271: =IF(COUNT(B271:C271)=2,(B271+C271)/2,"") | G271: =IF(COUNT(E271:F271)=2,(E271+F271)/2,"") | H271: =IF(AND(ISNUMBER(D271),ISNUMBER(G271)),D271+G271,"") | I271: =IFERROR(D271/H271,"") | J271: =IF(AND(ISNUMBER(D271),ISNUMBER(G271)),D271-G271,"") | K271: 0 | L271: 6760 | M271: 27 Feb
A272: 46081 | B272: 0.7 | C272: 0.75 | D272: =IF(COUNT(B272:C272)=2,(B272+C272)/2,"") | E272: 0.24 | F272: 0.27 | G272: =IF(COUNT(E272:F272)=2,(E272+F272)/2,"") | H272: =IF(AND(ISNUMBER(D272),ISNUMBER(G272)),D272+G272,"") | I272: =IFERROR(D272/H272,"") | J272: =IF(AND(ISNUMBER(D272),ISNUMBER(G272)),D272-G272,"") | K272: 18 | L272: 6760 | M272: 28 Feb
A273: 46082 | B273: 0.7 | C273: 0.75 | D273: =IF(COUNT(B273:C273)=2,(B273+C273)/2,"") | E273: 0.24 | F273: 0.27 | G273: =IF(COUNT(E273:F273)=2,(E273+F273)/2,"") | H273: =IF(AND(ISNUMBER(D273),ISNUMBER(G273)),D273+G273,"") | I273: =IFERROR(D273/H273,"") | J273: =IF(AND(ISNUMBER(D273),ISNUMBER(G273)),D273-G273,"") | K273: 0 | L273: 6760 | M273: 01 Mar
A274: 46083 | B274: 0.7 | C274: 0.74 | D274: =IF(COUNT(B274:C274)=2,(B274+C274)/2,"") | E274: 0.24 | F274: 0.27 | G274: =IF(COUNT(E274:F274)=2,(E274+F274)/2,"") | H274: =IF(AND(ISNUMBER(D274),ISNUMBER(G274)),D274+G274,"") | I274: =IFERROR(D274/H274,"") | J274: =IF(AND(ISNUMBER(D274),ISNUMBER(G274)),D274-G274,"") | K274: 0 | L274: 6760 | M274: 02 Mar
A275: 46084 | B275: 0.7 | C275: 0.74 | D275: =IF(COUNT(B275:C275)=2,(B275+C275)/2,"") | G275: =IF(COUNT(E275:F275)=2,(E275+F275)/2,"") | H275: =IF(AND(ISNUMBER(D275),ISNUMBER(G275)),D275+G275,"") | I275: =IFERROR(D275/H275,"") | J275: =IF(AND(ISNUMBER(D275),ISNUMBER(G275)),D275-G275,"") | K275: 0 | L275: 6760 | M275: 03 Mar
A276: 46085 | B276: 0.69 | C276: 0.73 | D276: =IF(COUNT(B276:C276)=2,(B276+C276)/2,"") | E276: 0.24 | F276: 0.28 | G276: =IF(COUNT(E276:F276)=2,(E276+F276)/2,"") | H276: =IF(AND(ISNUMBER(D276),ISNUMBER(G276)),D276+G276,"") | I276: =IFERROR(D276/H276,"") | J276: =IF(AND(ISNUMBER(D276),ISNUMBER(G276)),D276-G276,"") | K276: 262 | L276: 6760 | M276: 04 Mar
A277: 46086 | B277: 0.69 | C277: 0.73 | D277: =IF(COUNT(B277:C277)=2,(B277+C277)/2,"") | E277: 0.27 | F277: 0.28 | G277: =IF(COUNT(E277:F277)=2,(E277+F277)/2,"") | H277: =IF(AND(ISNUMBER(D277),ISNUMBER(G277)),D277+G277,"") | I277: =IFERROR(D277/H277,"") | J277: =IF(AND(ISNUMBER(D277),ISNUMBER(G277)),D277-G277,"") | K277: 4 | L277: 6760 | M277: 05 Mar
A278: 46087 | B278: 0.69 | C278: 0.74 | D278: =IF(COUNT(B278:C278)=2,(B278+C278)/2,"") | E278: 0.24 | F278: 0.28 | G278: =IF(COUNT(E278:F278)=2,(E278+F278)/2,"") | H278: =IF(AND(ISNUMBER(D278),ISNUMBER(G278)),D278+G278,"") | I278: =IFERROR(D278/H278,"") | J278: =IF(AND(ISNUMBER(D278),ISNUMBER(G278)),D278-G278,"") | K278: 0 | L278: 6760 | M278: 06 Mar
A279: 46088 | B279: 0.68 | C279: 0.73 | D279: =IF(COUNT(B279:C279)=2,(B279+C279)/2,"") | E279: 0.22 | F279: 0.27 | G279: =IF(COUNT(E279:F279)=2,(E279+F279)/2,"") | H279: =IF(AND(ISNUMBER(D279),ISNUMBER(G279)),D279+G279,"") | I279: =IFERROR(D279/H279,"") | J279: =IF(AND(ISNUMBER(D279),ISNUMBER(G279)),D279-G279,"") | K279: 34 | L279: 6760 | M279: 07 Mar
A280: 46089 | B280: 0.69 | C280: 0.74 | D280: =IF(COUNT(B280:C280)=2,(B280+C280)/2,"") | E280: 0.22 | F280: 0.27 | G280: =IF(COUNT(E280:F280)=2,(E280+F280)/2,"") | H280: =IF(AND(ISNUMBER(D280),ISNUMBER(G280)),D280+G280,"") | I280: =IFERROR(D280/H280,"") | J280: =IF(AND(ISNUMBER(D280),ISNUMBER(G280)),D280-G280,"") | K280: 262 | L280: 6760 | M280: 08 Mar
A281: 46090 | B281: 0.69 | C281: 0.74 | D281: =IF(COUNT(B281:C281)=2,(B281+C281)/2,"") | E281: 0.22 | F281: 0.27 | G281: =IF(COUNT(E281:F281)=2,(E281+F281)/2,"") | H281: =IF(AND(ISNUMBER(D281),ISNUMBER(G281)),D281+G281,"") | I281: =IFERROR(D281/H281,"") | J281: =IF(AND(ISNUMBER(D281),ISNUMBER(G281)),D281-G281,"") | K281: 34 | L281: 6793 | M281: 09 Mar
A282: 46091 | B282: 0.68 | C282: 0.74 | D282: =IF(COUNT(B282:C282)=2,(B282+C282)/2,"") | G282: =IF(COUNT(E282:F282)=2,(E282+F282)/2,"") | H282: =IF(AND(ISNUMBER(D282),ISNUMBER(G282)),D282+G282,"") | I282: =IFERROR(D282/H282,"") | J282: =IF(AND(ISNUMBER(D282),ISNUMBER(G282)),D282-G282,"") | K282: 0 | L282: 6793 | M282: 10 Mar
A283: 46092 | B283: 0.69 | C283: 0.74 | D283: =IF(COUNT(B283:C283)=2,(B283+C283)/2,"") | G283: =IF(COUNT(E283:F283)=2,(E283+F283)/2,"") | H283: =IF(AND(ISNUMBER(D283),ISNUMBER(G283)),D283+G283,"") | I283: =IFERROR(D283/H283,"") | J283: =IF(AND(ISNUMBER(D283),ISNUMBER(G283)),D283-G283,"") | K283: 0 | L283: 6793 | M283: 11 Mar
A284: 46093 | B284: 0.69 | C284: 0.74 | D284: =IF(COUNT(B284:C284)=2,(B284+C284)/2,"") | E284: 0.22 | F284: 0.27 | G284: =IF(COUNT(E284:F284)=2,(E284+F284)/2,"") | H284: =IF(AND(ISNUMBER(D284),ISNUMBER(G284)),D284+G284,"") | I284: =IFERROR(D284/H284,"") | J284: =IF(AND(ISNUMBER(D284),ISNUMBER(G284)),D284-G284,"") | K284: 130 | L284: 6836 | M284: 12 Mar
A285: 46094 | B285: 0.73 | C285: 0.74 | D285: =IF(COUNT(B285:C285)=2,(B285+C285)/2,"") | E285: 0.25 | F285: 0.27 | G285: =IF(COUNT(E285:F285)=2,(E285+F285)/2,"") | H285: =IF(AND(ISNUMBER(D285),ISNUMBER(G285)),D285+G285,"") | I285: =IFERROR(D285/H285,"") | J285: =IF(AND(ISNUMBER(D285),ISNUMBER(G285)),D285-G285,"") | K285: 0 | L285: 6836 | M285: 13 Mar
A286: 46095 | B286: 0.73 | C286: 0.74 | D286: =IF(COUNT(B286:C286)=2,(B286+C286)/2,"") | G286: =IF(COUNT(E286:F286)=2,(E286+F286)/2,"") | H286: =IF(AND(ISNUMBER(D286),ISNUMBER(G286)),D286+G286,"") | I286: =IFERROR(D286/H286,"") | J286: =IF(AND(ISNUMBER(D286),ISNUMBER(G286)),D286-G286,"") | K286: 0 | L286: 6836 | M286: 14 Mar
A287: 46096 | B287: 0.73 | C287: 0.74 | D287: =IF(COUNT(B287:C287)=2,(B287+C287)/2,"") | G287: =IF(COUNT(E287:F287)=2,(E287+F287)/2,"") | H287: =IF(AND(ISNUMBER(D287),ISNUMBER(G287)),D287+G287,"") | I287: =IFERROR(D287/H287,"") | J287: =IF(AND(ISNUMBER(D287),ISNUMBER(G287)),D287-G287,"") | K287: 0 | L287: 6836 | M287: 15 Mar
A288: 46097 | B288: 0.73 | C288: 0.74 | D288: =IF(COUNT(B288:C288)=2,(B288+C288)/2,"") | E288: 0.25 | F288: 0.27 | G288: =IF(COUNT(E288:F288)=2,(E288+F288)/2,"") | H288: =IF(AND(ISNUMBER(D288),ISNUMBER(G288)),D288+G288,"") | I288: =IFERROR(D288/H288,"") | J288: =IF(AND(ISNUMBER(D288),ISNUMBER(G288)),D288-G288,"") | K288: 0 | L288: 6836 | M288: 16 Mar
A289: 46098 | B289: 0.72 | C289: 0.74 | D289: =IF(COUNT(B289:C289)=2,(B289+C289)/2,"") | G289: =IF(COUNT(E289:F289)=2,(E289+F289)/2,"") | H289: =IF(AND(ISNUMBER(D289),ISNUMBER(G289)),D289+G289,"") | I289: =IFERROR(D289/H289,"") | J289: =IF(AND(ISNUMBER(D289),ISNUMBER(G289)),D289-G289,"") | K289: 0 | L289: 6836 | M289: 17 Mar
A290: 46099 | B290: 0.73 | C290: 0.74 | D290: =IF(COUNT(B290:C290)=2,(B290+C290)/2,"") | G290: =IF(COUNT(E290:F290)=2,(E290+F290)/2,"") | H290: =IF(AND(ISNUMBER(D290),ISNUMBER(G290)),D290+G290,"") | I290: =IFERROR(D290/H290,"") | J290: =IF(AND(ISNUMBER(D290),ISNUMBER(G290)),D290-G290,"") | K290: 0 | L290: 6836 | M290: 18 Mar
A291: 46100 | B291: 0.73 | C291: 0.74 | D291: =IF(COUNT(B291:C291)=2,(B291+C291)/2,"") | G291: =IF(COUNT(E291:F291)=2,(E291+F291)/2,"") | H291: =IF(AND(ISNUMBER(D291),ISNUMBER(G291)),D291+G291,"") | I291: =IFERROR(D291/H291,"") | J291: =IF(AND(ISNUMBER(D291),ISNUMBER(G291)),D291-G291,"") | K291: 0 | L291: 6836 | M291: 19 Mar
A292: 46101 | B292: 0.73 | C292: 0.74 | D292: =IF(COUNT(B292:C292)=2,(B292+C292)/2,"") | G292: =IF(COUNT(E292:F292)=2,(E292+F292)/2,"") | H292: =IF(AND(ISNUMBER(D292),ISNUMBER(G292)),D292+G292,"") | I292: =IFERROR(D292/H292,"") | J292: =IF(AND(ISNUMBER(D292),ISNUMBER(G292)),D292-G292,"") | K292: 0 | L292: 6836 | M292: 20 Mar
A293: 46102 | B293: 0.73 | C293: 0.74 | D293: =IF(COUNT(B293:C293)=2,(B293+C293)/2,"") | G293: =IF(COUNT(E293:F293)=2,(E293+F293)/2,"") | H293: =IF(AND(ISNUMBER(D293),ISNUMBER(G293)),D293+G293,"") | I293: =IFERROR(D293/H293,"") | J293: =IF(AND(ISNUMBER(D293),ISNUMBER(G293)),D293-G293,"") | K293: 0 | L293: 6836 | M293: 21 Mar
A294: 46103 | B294: 0.72 | C294: 0.74 | D294: =IF(COUNT(B294:C294)=2,(B294+C294)/2,"") | G294: =IF(COUNT(E294:F294)=2,(E294+F294)/2,"") | H294: =IF(AND(ISNUMBER(D294),ISNUMBER(G294)),D294+G294,"") | I294: =IFERROR(D294/H294,"") | J294: =IF(AND(ISNUMBER(D294),ISNUMBER(G294)),D294-G294,"") | K294: 0 | L294: 6836 | M294: 22 Mar
A295: 46104 | B295: 0.69 | C295: 0.7 | D295: =IF(COUNT(B295:C295)=2,(B295+C295)/2,"") | E295: 0.29 | F295: 0.33 | G295: =IF(COUNT(E295:F295)=2,(E295+F295)/2,"") | H295: =IF(AND(ISNUMBER(D295),ISNUMBER(G295)),D295+G295,"") | I295: =IFERROR(D295/H295,"") | J295: =IF(AND(ISNUMBER(D295),ISNUMBER(G295)),D295-G295,"") | K295: 1004 | L295: 6838 | M295: 23 Mar
A296: 46105 | B296: 0.69 | C296: 0.7 | D296: =IF(COUNT(B296:C296)=2,(B296+C296)/2,"") | G296: =IF(COUNT(E296:F296)=2,(E296+F296)/2,"") | H296: =IF(AND(ISNUMBER(D296),ISNUMBER(G296)),D296+G296,"") | I296: =IFERROR(D296/H296,"") | J296: =IF(AND(ISNUMBER(D296),ISNUMBER(G296)),D296-G296,"") | K296: 9 | L296: 6847 | M296: 24 Mar
A297: 46106 | B297: 0.69 | C297: 0.7 | D297: =IF(COUNT(B297:C297)=2,(B297+C297)/2,"") | G297: =IF(COUNT(E297:F297)=2,(E297+F297)/2,"") | H297: =IF(AND(ISNUMBER(D297),ISNUMBER(G297)),D297+G297,"") | I297: =IFERROR(D297/H297,"") | J297: =IF(AND(ISNUMBER(D297),ISNUMBER(G297)),D297-G297,"") | K297: 0 | L297: 6847 | M297: 25 Mar
A298: 46107 | B298: 0.69 | C298: 0.7 | D298: =IF(COUNT(B298:C298)=2,(B298+C298)/2,"") | G298: =IF(COUNT(E298:F298)=2,(E298+F298)/2,"") | H298: =IF(AND(ISNUMBER(D298),ISNUMBER(G298)),D298+G298,"") | I298: =IFERROR(D298/H298,"") | J298: =IF(AND(ISNUMBER(D298),ISNUMBER(G298)),D298-G298,"") | K298: 0 | L298: 6847 | M298: 26 Mar
A299: 46108 | B299: 0.68 | C299: 0.7 | D299: =IF(COUNT(B299:C299)=2,(B299+C299)/2,"") | G299: =IF(COUNT(E299:F299)=2,(E299+F299)/2,"") | H299: =IF(AND(ISNUMBER(D299),ISNUMBER(G299)),D299+G299,"") | I299: =IFERROR(D299/H299,"") | J299: =IF(AND(ISNUMBER(D299),ISNUMBER(G299)),D299-G299,"") | K299: 0 | L299: 6847 | M299: 27 Mar
A300: 46109 | B300: 0.68 | C300: 0.7 | D300: =IF(COUNT(B300:C300)=2,(B300+C300)/2,"") | G300: =IF(COUNT(E300:F300)=2,(E300+F300)/2,"") | H300: =IF(AND(ISNUMBER(D300),ISNUMBER(G300)),D300+G300,"") | I300: =IFERROR(D300/H300,"") | J300: =IF(AND(ISNUMBER(D300),ISNUMBER(G300)),D300-G300,"") | K300: 0 | L300: 6847 | M300: 28 Mar
A301: 46110 | B301: 0.68 | C301: 0.71 | D301: =IF(COUNT(B301:C301)=2,(B301+C301)/2,"") | E301: 0.28 | F301: 0.33 | G301: =IF(COUNT(E301:F301)=2,(E301+F301)/2,"") | H301: =IF(AND(ISNUMBER(D301),ISNUMBER(G301)),D301+G301,"") | I301: =IFERROR(D301/H301,"") | J301: =IF(AND(ISNUMBER(D301),ISNUMBER(G301)),D301-G301,"") | K301: 106 | L301: 6947 | M301: 29 Mar
A302: 46111 | B302: 0.68 | C302: 0.7 | D302: =IF(COUNT(B302:C302)=2,(B302+C302)/2,"") | E302: 0.28 | F302: 0.33 | G302: =IF(COUNT(E302:F302)=2,(E302+F302)/2,"") | H302: =IF(AND(ISNUMBER(D302),ISNUMBER(G302)),D302+G302,"") | I302: =IFERROR(D302/H302,"") | J302: =IF(AND(ISNUMBER(D302),ISNUMBER(G302)),D302-G302,"") | K302: 31 | L302: 6916 | M302: 30 Mar
A303: 46112 | B303: 0.68 | C303: 0.7 | D303: =IF(COUNT(B303:C303)=2,(B303+C303)/2,"") | E303: 0.28 | F303: 0.33 | G303: =IF(COUNT(E303:F303)=2,(E303+F303)/2,"") | H303: =IF(AND(ISNUMBER(D303),ISNUMBER(G303)),D303+G303,"") | I303: =IFERROR(D303/H303,"") | J303: =IF(AND(ISNUMBER(D303),ISNUMBER(G303)),D303-G303,"") | K303: 7 | L303: 6909 | M303: 31 Mar
A304: 46113 | B304: 0.7 | C304: 0.73 | D304: =IF(COUNT(B304:C304)=2,(B304+C304)/2,"") | E304: 0.27 | F304: 0.31 | G304: =IF(COUNT(E304:F304)=2,(E304+F304)/2,"") | H304: =IF(AND(ISNUMBER(D304),ISNUMBER(G304)),D304+G304,"") | I304: =IFERROR(D304/H304,"") | J304: =IF(AND(ISNUMBER(D304),ISNUMBER(G304)),D304-G304,"") | K304: 420 | L304: 7320 | M304: 01 Apr
A305: 46114 | B305: 0.71 | C305: 0.73 | D305: =IF(COUNT(B305:C305)=2,(B305+C305)/2,"") | E305: 0.27 | F305: 0.31 | G305: =IF(COUNT(E305:F305)=2,(E305+F305)/2,"") | H305: =IF(AND(ISNUMBER(D305),ISNUMBER(G305)),D305+G305,"") | I305: =IFERROR(D305/H305,"") | J305: =IF(AND(ISNUMBER(D305),ISNUMBER(G305)),D305-G305,"") | K305: 20 | L305: 7320 | M305: 02 Apr
A306: 46115 | B306: 0.71 | C306: 0.72 | D306: =IF(COUNT(B306:C306)=2,(B306+C306)/2,"") | E306: 0.27 | F306: 0.31 | G306: =IF(COUNT(E306:F306)=2,(E306+F306)/2,"") | H306: =IF(AND(ISNUMBER(D306),ISNUMBER(G306)),D306+G306,"") | I306: =IFERROR(D306/H306,"") | J306: =IF(AND(ISNUMBER(D306),ISNUMBER(G306)),D306-G306,"") | K306: 0 | L306: 7320 | M306: 03 Apr
A307: 46116 | B307: 0.71 | C307: 0.72 | D307: =IF(COUNT(B307:C307)=2,(B307+C307)/2,"") | E307: 0.27 | F307: 0.31 | G307: =IF(COUNT(E307:F307)=2,(E307+F307)/2,"") | H307: =IF(AND(ISNUMBER(D307),ISNUMBER(G307)),D307+G307,"") | I307: =IFERROR(D307/H307,"") | J307: =IF(AND(ISNUMBER(D307),ISNUMBER(G307)),D307-G307,"") | K307: 0 | L307: 7320 | M307: 04 Apr
A308: 46117 | B308: 0.71 | C308: 0.72 | D308: =IF(COUNT(B308:C308)=2,(B308+C308)/2,"") | E308: 0.27 | F308: 0.31 | G308: =IF(COUNT(E308:F308)=2,(E308+F308)/2,"") | H308: =IF(AND(ISNUMBER(D308),ISNUMBER(G308)),D308+G308,"") | I308: =IFERROR(D308/H308,"") | J308: =IF(AND(ISNUMBER(D308),ISNUMBER(G308)),D308-G308,"") | K308: 0 | L308: 7320 | M308: 05 Apr
A309: 46118 | B309: 0.71 | C309: 0.72 | D309: =IF(COUNT(B309:C309)=2,(B309+C309)/2,"") | E309: 0.27 | F309: 0.31 | G309: =IF(COUNT(E309:F309)=2,(E309+F309)/2,"") | H309: =IF(AND(ISNUMBER(D309),ISNUMBER(G309)),D309+G309,"") | I309: =IFERROR(D309/H309,"") | J309: =IF(AND(ISNUMBER(D309),ISNUMBER(G309)),D309-G309,"") | K309: 0 | L309: 7320 | M309: 06 Apr
A310: 46119 | B310: 0.71 | C310: 0.72 | D310: =IF(COUNT(B310:C310)=2,(B310+C310)/2,"") | E310: 0.27 | F310: 0.31 | G310: =IF(COUNT(E310:F310)=2,(E310+F310)/2,"") | H310: =IF(AND(ISNUMBER(D310),ISNUMBER(G310)),D310+G310,"") | I310: =IFERROR(D310/H310,"") | J310: =IF(AND(ISNUMBER(D310),ISNUMBER(G310)),D310-G310,"") | K310: 10 | L310: 7320 | M310: 07 Apr
A311: 46120 | B311: 0.71 | C311: 0.72 | D311: =IF(COUNT(B311:C311)=2,(B311+C311)/2,"") | E311: 0.27 | F311: 0.31 | G311: =IF(COUNT(E311:F311)=2,(E311+F311)/2,"") | H311: =IF(AND(ISNUMBER(D311),ISNUMBER(G311)),D311+G311,"") | I311: =IFERROR(D311/H311,"") | J311: =IF(AND(ISNUMBER(D311),ISNUMBER(G311)),D311-G311,"") | K311: 0 | L311: 7320 | M311: 08 Apr
A312: 46121 | B312: 0.71 | C312: 0.72 | D312: =IF(COUNT(B312:C312)=2,(B312+C312)/2,"") | E312: 0.27 | F312: 0.31 | G312: =IF(COUNT(E312:F312)=2,(E312+F312)/2,"") | H312: =IF(AND(ISNUMBER(D312),ISNUMBER(G312)),D312+G312,"") | I312: =IFERROR(D312/H312,"") | J312: =IF(AND(ISNUMBER(D312),ISNUMBER(G312)),D312-G312,"") | K312: 0 | L312: 7320 | M312: 09 Apr
... A321: 46130 | B321: 0.71 | C321: 0.73 | D321: =IF(COUNT(B321:C321)=2,(B321+C321)/2,"") | E321: 0.26 | F321: 0.3 | G321: =IF(COUNT(E321:F321)=2,(E321+F321)/2,"") | H321: =IF(AND(ISNUMBER(D321),ISNUMBER(G321)),D321+G321,"") | I321: =IFERROR(D321/H321,"") | J321: =IF(AND(ISNUMBER(D321),ISNUMBER(G321)),D321-G321,"") | K321: 0 | L321: 7347 | M321: 18 Apr
A322: 46131 | D322: =IF(COUNT(B322:C322)=2,(B322+C322)/2,"") | E322: 0.26 | F322: 0.3 | G322: =IF(COUNT(E322:F322)=2,(E322+F322)/2,"") | H322: =IF(AND(ISNUMBER(D322),ISNUMBER(G322)),D322+G322,"") | I322: =IFERROR(D322/H322,"") | J322: =IF(AND(ISNUMBER(D322),ISNUMBER(G322)),D322-G322,"") | K322: 0 | L322: 6467 | M322: 19 Apr
A323: 46132 | B323: 0.72 | C323: 0.73 | D323: =IF(COUNT(B323:C323)=2,(B323+C323)/2,"") | E323: 0.26 | F323: 0.3 | G323: =IF(COUNT(E323:F323)=2,(E323+F323)/2,"") | H323: =IF(AND(ISNUMBER(D323),ISNUMBER(G323)),D323+G323,"") | I323: =IFERROR(D323/H323,"") | J323: =IF(AND(ISNUMBER(D323),ISNUMBER(G323)),D323-G323,"") | K323: 4 | L323: 7347 | M323: 20 Apr
A324: 46133 | B324: 0.72 | C324: 0.73 | D324: =IF(COUNT(B324:C324)=2,(B324+C324)/2,"") | E324: 0.26 | F324: 0.3 | G324: =IF(COUNT(E324:F324)=2,(E324+F324)/2,"") | H324: =IF(AND(ISNUMBER(D324),ISNUMBER(G324)),D324+G324,"") | I324: =IFERROR(D324/H324,"") | J324: =IF(AND(ISNUMBER(D324),ISNUMBER(G324)),D324-G324,"") | K324: 0 | L324: 7347 | M324: 21 Apr
A325: 46134 | B325: 0.71 | C325: 0.73 | D325: =IF(COUNT(B325:C325)=2,(B325+C325)/2,"") | E325: 0.26 | F325: 0.3 | G325: =IF(COUNT(E325:F325)=2,(E325+F325)/2,"") | H325: =IF(AND(ISNUMBER(D325),ISNUMBER(G325)),D325+G325,"") | I325: =IFERROR(D325/H325,"") | J325: =IF(AND(ISNUMBER(D325),ISNUMBER(G325)),D325-G325,"") | K325: 0 | L325: 7347 | M325: 22 Apr
A326: 46135 | B326: 0.71 | C326: 0.73 | D326: =IF(COUNT(B326:C326)=2,(B326+C326)/2,"") | E326: 0.26 | F326: 0.3 | G326: =IF(COUNT(E326:F326)=2,(E326+F326)/2,"") | H326: =IF(AND(ISNUMBER(D326),ISNUMBER(G326)),D326+G326,"") | I326: =IFERROR(D326/H326,"") | J326: =IF(AND(ISNUMBER(D326),ISNUMBER(G326)),D326-G326,"") | K326: 0 | L326: 7347 | M326: 23 Apr
A327: 46136 | B327: 0.72 | C327: 0.73 | D327: =IF(COUNT(B327:C327)=2,(B327+C327)/2,"") | E327: 0.26 | F327: 0.3 | G327: =IF(COUNT(E327:F327)=2,(E327+F327)/2,"") | H327: =IF(AND(ISNUMBER(D327),ISNUMBER(G327)),D327+G327,"") | I327: =IFERROR(D327/H327,"") | J327: =IF(AND(ISNUMBER(D327),ISNUMBER(G327)),D327-G327,"") | K327: 0 | L327: 7347 | M327: 24 Apr
A328: 46137 | B328: 0.72 | C328: 0.73 | D328: =IF(COUNT(B328:C328)=2,(B328+C328)/2,"") | E328: 0.26 | F328: 0.3 | G328: =IF(COUNT(E328:F328)=2,(E328+F328)/2,"") | H328: =IF(AND(ISNUMBER(D328),ISNUMBER(G328)),D328+G328,"") | I328: =IFERROR(D328/H328,"") | J328: =IF(AND(ISNUMBER(D328),ISNUMBER(G328)),D328-G328,"") | K328: 0 | L328: 7347 | M328: 25 Apr
A329: 46138 | B329: 0.71 | C329: 0.73 | D329: =IF(COUNT(B329:C329)=2,(B329+C329)/2,"") | E329: 0.26 | F329: 0.3 | G329: =IF(COUNT(E329:F329)=2,(E329+F329)/2,"") | H329: =IF(AND(ISNUMBER(D329),ISNUMBER(G329)),D329+G329,"") | I329: =IFERROR(D329/H329,"") | J329: =IF(AND(ISNUMBER(D329),ISNUMBER(G329)),D329-G329,"") | K329: 0 | L329: 7347 | M329: 26 Apr
A330: 46139 | B330: 0.72 | C330: 0.73 | D330: =IF(COUNT(B330:C330)=2,(B330+C330)/2,"") | E330: 0.26 | F330: 0.3 | G330: =IF(COUNT(E330:F330)=2,(E330+F330)/2,"") | H330: =IF(AND(ISNUMBER(D330),ISNUMBER(G330)),D330+G330,"") | I330: =IFERROR(D330/H330,"") | J330: =IF(AND(ISNUMBER(D330),ISNUMBER(G330)),D330-G330,"") | K330: 0 | L330: 7347 | M330: 27 Apr
A331: 46140 | B331: 0.72 | C331: 0.73 | D331: =IF(COUNT(B331:C331)=2,(B331+C331)/2,"") | E331: 0.26 | F331: 0.3 | G331: =IF(COUNT(E331:F331)=2,(E331+F331)/2,"") | H331: =IF(AND(ISNUMBER(D331),ISNUMBER(G331)),D331+G331,"") | I331: =IFERROR(D331/H331,"") | J331: =IF(AND(ISNUMBER(D331),ISNUMBER(G331)),D331-G331,"") | K331: 0 | L331: 7347 | M331: 28 Apr
A332: 46141 | B332: 0.72 | C332: 0.73 | D332: =IF(COUNT(B332:C332)=2,(B332+C332)/2,"") | E332: 0.26 | F332: 0.3 | G332: =IF(COUNT(E332:F332)=2,(E332+F332)/2,"") | H332: =IF(AND(ISNUMBER(D332),ISNUMBER(G332)),D332+G332,"") | I332: =IFERROR(D332/H332,"") | J332: =IF(AND(ISNUMBER(D332),ISNUMBER(G332)),D332-G332,"") | K332: 0 | L332: 7347 | M332: 29 Apr
A333: 46142 | B333: 0.7 | C333: 0.72 | D333: =IF(COUNT(B333:C333)=2,(B333+C333)/2,"") | E333: 0.26 | F333: 0.3 | G333: =IF(COUNT(E333:F333)=2,(E333+F333)/2,"") | H333: =IF(AND(ISNUMBER(D333),ISNUMBER(G333)),D333+G333,"") | I333: =IFERROR(D333/H333,"") | J333: =IF(AND(ISNUMBER(D333),ISNUMBER(G333)),D333-G333,"") | K333: 50 | L333: 7322 | M333: 30 Apr
A334: 46143 | B334: 0.7 | C334: 0.73 | D334: =IF(COUNT(B334:C334)=2,(B334+C334)/2,"") | E334: 0.26 | F334: 0.3 | G334: =IF(COUNT(E334:F334)=2,(E334+F334)/2,"") | H334: =IF(AND(ISNUMBER(D334),ISNUMBER(G334)),D334+G334,"") | I334: =IFERROR(D334/H334,"") | J334: =IF(AND(ISNUMBER(D334),ISNUMBER(G334)),D334-G334,"") | K334: 20 | L334: 7336 | M334: 01 May
A335: 46144 | D335: =IF(COUNT(B335:C335)=2,(B335+C335)/2,"") | E335: 0.26 | F335: 0.3 | G335: =IF(COUNT(E335:F335)=2,(E335+F335)/2,"") | H335: =IF(AND(ISNUMBER(D335),ISNUMBER(G335)),D335+G335,"") | I335: =IFERROR(D335/H335,"") | J335: =IF(AND(ISNUMBER(D335),ISNUMBER(G335)),D335-G335,"") | K335: 0 | L335: 6463 | M335: 02 May
A336: 46145 | D336: =IF(COUNT(B336:C336)=2,(B336+C336)/2,"") | E336: 0.26 | F336: 0.3 | G336: =IF(COUNT(E336:F336)=2,(E336+F336)/2,"") | H336: =IF(AND(ISNUMBER(D336),ISNUMBER(G336)),D336+G336,"") | I336: =IFERROR(D336/H336,"") | J336: =IF(AND(ISNUMBER(D336),ISNUMBER(G336)),D336-G336,"") | K336: 0 | L336: 6463 | M336: 03 May
...

Sheet Margin of Victory
A1: Margin of Victory — PA-07 (Polymarket)
A2: The PA-07 winning margin, quoted on BOTH venues: Polymarket as exclusive brackets (below) and Kalshi as nested thresholds (further down, with the two compared). Pulled 2026-10-12 02:24 UTC.
A4: MARKET METADATA
A5: Event | B5: PA-07 House Election Margin of Victory
A6: Slug | B6: pa-07-house-margin-of-victory-2026
A7: Event id | B7: 834502
A8: Opened | B8: 2026-08-11
A9: Resolution date | B9: 2026-11-04
A10: Volume ($) | B10: 15737.082
A11: Liquidity ($) | B11: 162275.8
A12: Brackets listed | B12: 10
A14: LIVE BRACKET LADDER
A15: Bracket | B15: Signed Midpoint (pts) | C15: Best Bid | D15: Best Ask | E15: Mid | F15: Normalised Prob | G15: Cumulative | H15: Volume ($) | I15: Liquidity ($) | J15: Prob × Midpoint
A16: Republican 6%+ | B16: -8 | C16: 0.016 | D16: 0.078 | E16: =IF(COUNT(C16:D16)=2,(C16+D16)/2,"") | F16: =IFERROR(E16/$E$26,"") | G16: =IFERROR(SUM($F$16:F16),"") | H16: 1219.8912 | I16: 20139.616 | J16: =IFERROR(F16*B16,"")
A17: Republican 3-6% | B17: -4.5 | C17: 0.04 | D17: 0.041 | E17: =IF(COUNT(C17:D17)=2,(C17+D17)/2,"") | F17: =IFERROR(E17/$E$26,"") | G17: =IFERROR(SUM($F$16:F17),"") | H17: 934.03986 | I17: 20510.613 | J17: =IFERROR(F17*B17,"")
A18: Republican 0-3% | B18: -1.5 | C18: 0.09 | D18: 0.1 | E18: =IF(COUNT(C18:D18)=2,(C18+D18)/2,"") | F18: =IFERROR(E18/$E$26,"") | G18: =IFERROR(SUM($F$16:F18),"") | H18: 816.67293 | I18: 18363.776 | J18: =IFERROR(F18*B18,"")
A19: Democrat 0-3% | B19: 1.5 | C19: 0.11 | D19: 0.13 | E19: =IF(COUNT(C19:D19)=2,(C19+D19)/2,"") | F19: =IFERROR(E19/$E$26,"") | G19: =IFERROR(SUM($F$16:F19),"") | H19: 4100.8265 | I19: 20514.047 | J19: =IFERROR(F19*B19,"")
A20: Democrat 3-6% | B20: 4.5 | C20: 0.27 | D20: 0.28 | E20: =IF(COUNT(C20:D20)=2,(C20+D20)/2,"") | F20: =IFERROR(E20/$E$26,"") | G20: =IFERROR(SUM($F$16:F20),"") | H20: 2122.9772 | I20: 20684.719 | J20: =IFERROR(F20*B20,"")
A21: Democrat 6-9% | B21: 7.5 | C21: 0.167 | D21: 0.177 | E21: =IF(COUNT(C21:D21)=2,(C21+D21)/2,"") | F21: =IFERROR(E21/$E$26,"") | G21: =IFERROR(SUM($F$16:F21),"") | H21: 2661.0342 | I21: 19229.334 | J21: =IFERROR(F21*B21,"")
A22: Democrat 9-12% | B22: 10.5 | C22: 0.014 | D22: 0.207 | E22: =IF(COUNT(C22:D22)=2,(C22+D22)/2,"") | F22: =IFERROR(E22/$E$26,"") | G22: =IFERROR(SUM($F$16:F22),"") | H22: 986.28736 | I22: 10644.012 | J22: =IFERROR(F22*B22,"")
A23: Democrat 12-15% | B23: 13.5 | C23: 0.04 | D23: 0.08 | E23: =IF(COUNT(C23:D23)=2,(C23+D23)/2,"") | F23: =IFERROR(E23/$E$26,"") | G23: =IFERROR(SUM($F$16:F23),"") | H23: 1014.9916 | I23: 11808.655 | J23: =IFERROR(F23*B23,"")
A24: Democrat 15-18% | B24: 16.5 | C24: 0.016 | D24: 0.25 | E24: =IF(COUNT(C24:D24)=2,(C24+D24)/2,"") | F24: =IFERROR(E24/$E$26,"") | G24: =IFERROR(SUM($F$16:F24),"") | H24: 813.45533 | I24: 520.95803 | J24: =IFERROR(F24*B24,"")
A25: Democrat 18%+ | B25: 20 | C25: 0.031 | D25: 0.044 | E25: =IF(COUNT(C25:D25)=2,(C25+D25)/2,"") | F25: =IFERROR(E25/$E$26,"") | G25: =IFERROR(SUM($F$16:F25),"") | H25: 1066.9056 | I25: 19972.951 | J25: =IFERROR(F25*B25,"")
A26: TOTAL | E26: =SUM(E16:E25) | F26: =SUM(F16:F25) | H26: =SUM(H16:H25) | I26: =SUM(I16:I25) | J26: =SUM(J16:J25)
A28: IMPLIED DISTRIBUTION
A29: P(Democrat wins) — from ladder | B29: =IFERROR(SUMIF($A$16:$A$25,"Democrat*",$F$16:$F$25),"")
A30: P(Republican wins) — from ladder | B30: =IFERROR(SUMIF($A$16:$A$25,"Republican*",$F$16:$F$25),"")
A31: Expected margin (D−R) | B31: =IFERROR(SUM(J16:J25),"")
A32: P(margin under 3 pts either way) | B32: =IFERROR(SUMIFS($F$16:$F$25,$B$16:$B$25,">-3",$B$16:$B$25,"<3"),"")
A33: P(margin under 6 pts either way) | B33: =IFERROR(SUMIFS($F$16:$F$25,$B$16:$B$25,">-6",$B$16:$B$25,"<6"),"")
A35: CROSS-CHECK vs THE WINNER MARKET
A36: Winner market — Polymarket Dem mid | B36: =Polymarket!D19
A37: Margin ladder — P(Democrat wins) | B37: =B29
A38: Discrepancy (ladder − winner) | B38: =IFERROR(B29-B36,"")
A39: Both markets describe the same event on the same venue, so a large gap is a sign the thin margin ladder is mispriced rather than a signal about the race. The winner market carries far more volume; trust it first.
A41: DAILY BRACKET HISTORY
A42: Date | B42: Republican 6%+ | C42: Republican 3-6% | D42: Republican 0-3% | E42: Democrat 0-3% | F42: Democrat 3-6% | G42: Democrat 6-9% | H42: Democrat 9-12% | I42: Democrat 12-15% | J42: Democrat 15-18% | K42: Democrat 18%+
A43: 46246 | B43: 0.365 | C43: 0.365 | D43: 0.365 | E43: 0.365 | F43: 0.365 | G43: 0.365 | H43: 0.365 | I43: 0.365 | J43: 0.365 | K43: 0.365
A44: 46247 | B44: 0.365 | C44: 0.365 | D44: 0.365 | E44: 0.365 | F44: 0.365 | G44: 0.365 | H44: 0.365 | I44: 0.365 | J44: 0.365 | K44: 0.365
A45: 46248 | B45: 0.37 | C45: 0.37 | D45: 0.37 | E45: 0.37 | F45: 0.365 | G45: 0.365 | H45: 0.37 | I45: 0.37 | J45: 0.37 | K45: 0.37
A46: 46249 | B46: 0.365 | C46: 0.365 | D46: 0.365 | E46: 0.365 | F46: 0.365 | G46: 0.365 | H46: 0.365 | I46: 0.365 | J46: 0.365 | K46: 0.365
A47: 46250 | B47: 0.365 | C47: 0.365 | D47: 0.365 | E47: 0.365 | F47: 0.365 | G47: 0.365 | H47: 0.365 | I47: 0.365 | J47: 0.365 | K47: 0.365
A48: 46251 | B48: 0.365 | C48: 0.365 | D48: 0.365 | E48: 0.375 | F48: 0.365 | G48: 0.37 | H48: 0.365 | I48: 0.36 | J48: 0.365 | K48: 0.365
A49: 46252 | B49: 0.365 | C49: 0.365 | D49: 0.365 | E49: 0.365 | F49: 0.365 | G49: 0.365 | H49: 0.37 | I49: 0.375 | J49: 0.37 | K49: 0.37
A50: 46253 | B50: 0.365 | C50: 0.365 | D50: 0.365 | E50: 0.365 | F50: 0.365 | G50: 0.365 | H50: 0.365 | I50: 0.365 | J50: 0.365 | K50: 0.365
A51: 46254 | B51: 0.355 | C51: 0.365 | D51: 0.365 | E51: 0.355 | F51: 0.365 | G51: 0.365 | H51: 0.365 | I51: 0.365 | J51: 0.365 | K51: 0.345
A52: 46255 | B52: 0.105 | C52: 0.115 | D52: 0.11 | E52: 0.295 | F52: 0.25 | G52: 0.27 | H52: 0.315 | I52: 0.255 | J52: 0.255 | K52: 0.24
A53: 46256 | B53: 0.08 | C53: 0.4 | D53: 0.29 | E53: 0.36 | F53: 0.375 | G53: 0.265 | H53: 0.235 | I53: 0.375 | J53: 0.345 | K53: 0.355
A54: 46257 | B54: 0.08 | C54: 0.31 | D54: 0.315 | E54: 0.27 | F54: 0.38 | G54: 0.13 | H54: 0.245 | I54: 0.29 | J54: 0.295 | K54: 0.37
... A99: 46302 | B99: 0.058 | C99: 0.0365 | D99: 0.1 | E99: 0.165 | F99: 0.265 | G99: 0.176 | H99: 0.103 | I99: 0.105 | J99: 0.099 | K99: 0.035
A100: 46303 | B100: 0.058 | C100: 0.0365 | D100: 0.1 | E100: 0.165 | G100: 0.178 | H100: 0.077 | I100: 0.1 | J100: 0.18 | K100: 0.035
A101: 46304 | B101: 0.0605 | C101: 0.0365 | D101: 0.1 | E101: 0.275 | G101: 0.196 | H101: 0.077 | I101: 0.085 | K101: 0.0345
A102: 46305 | B102: 0.0575 | C102: 0.0175 | D102: 0.055 | E102: 0.26 | F102: 0.265 | G102: 0.173 | H102: 0.074 | I102: 0.085 | J102: 0.119 | K102: 0.0615
A103: 46306 | B103: 0.0545 | C103: 0.045 | D103: 0.08 | E103: 0.23 | F103: 0.265 | G103: 0.1395 | H103: 0.0735 | I103: 0.065 | J103: 0.0865 | K103: 0.0505
A104: 46307 | B104: 0.047 | C104: 0.0405 | D104: 0.095 | E104: 0.12 | F104: 0.275 | G104: 0.172 | H104: 0.1105 | I104: 0.06 | J104: 0.1365 | K104: 0.0375
A105: All ten brackets, daily closes from CLOB /prices-history at fidelity=1440. The market opened 11 Aug 2026, so the series is only 62 days long and the brackets are thin — read it as a sanity check on the ladder above, not as a trend.

Sheet Voter Turnout
A1: Voter Turnout — PA-07 (Kalshi)
A2: Kalshi KXMIDTERMVOTETURN-PA07: how many ballots the PA-07 House race draws on 3 Nov 2026, quoted as thresholds. Pulled 2026-10-12 02:24 UTC.
A4: MARKET METADATA
A5: Event | B5: KXMIDTERMVOTETURN-PA07
A6: Series | B6: KXMIDTERMVOTETURN
A7: Question | B7: Pennsylvania 07 House General Election: voter turnout
A8: Resolution | B8: 3 Nov 2026
A9: Thresholds quoted | B9: 8
A11: THRESHOLD LADDER
A12: Rung | B12: Threshold | C12: YES Bid | D12: YES Ask | E12: Mid P(turnout ≥ strike) | F12: Bucket | G12: Bucket Prob | H12: Representative Turnout | I12: Prob × Turnout
A13: Below 220K | F13: under 220K | G13: =IFERROR(MAX(0,1-E14),"") | H13: 295000 | I13: =IFERROR(G13*H13,"")
A14: Above 220K | B14: 220000 | C14: 0.94 | D14: 0.99 | E14: =IF(COUNT(C14:D14)=2,(C14+D14)/2,"") | F14: 220K–260K | G14: =IFERROR(MAX(0,E14-E15),"") | H14: 240000 | I14: =IFERROR(G14*H14,"")
A15: Above 260K | B15: 260000 | C15: 0.78 | D15: 0.87 | E15: =IF(COUNT(C15:D15)=2,(C15+D15)/2,"") | F15: 260K–280K | G15: =IFERROR(MAX(0,E15-E16),"") | H15: 270000 | I15: =IFERROR(G15*H15,"")
A16: Above 280K | B16: 280000 | C16: 0.64 | D16: 0.73 | E16: =IF(COUNT(C16:D16)=2,(C16+D16)/2,"") | F16: 280K–310K | G16: =IFERROR(MAX(0,E16-E17),"") | H16: 295000 | I16: =IFERROR(G16*H16,"")
A17: Above 310K | B17: 310000 | C17: 0.37 | D17: 0.46 | E17: =IF(COUNT(C17:D17)=2,(C17+D17)/2,"") | F17: 310K–320K | G17: =IFERROR(MAX(0,E17-E18),"") | H17: 315000 | I17: =IFERROR(G17*H17,"")
A18: Above 320K | B18: 320000 | C18: 0.32 | D18: 0.39 | E18: =IF(COUNT(C18:D18)=2,(C18+D18)/2,"") | F18: 320K–340K | G18: =IFERROR(MAX(0,E18-E19),"") | H18: 330000 | I18: =IFERROR(G18*H18,"")
A19: Above 340K | B19: 340000 | C19: 0.19 | D19: 0.28 | E19: =IF(COUNT(C19:D19)=2,(C19+D19)/2,"") | F19: 340K–360K | G19: =IFERROR(MAX(0,E19-E20),"") | H19: 350000 | I19: =IFERROR(G19*H19,"")
A20: Above 360K | B20: 360000 | C20: 0.11 | D20: 0.2 | E20: =IF(COUNT(C20:D20)=2,(C20+D20)/2,"") | F20: 360K–370K | G20: =IFERROR(MAX(0,E20-E21),"") | H20: 365000 | I20: =IFERROR(G20*H20,"")
A21: Above 370K | B21: 370000 | C21: 0.1 | D21: 0.17 | E21: =IF(COUNT(C21:D21)=2,(C21+D21)/2,"") | F21: above 370K | G21: =IFERROR(E21,"") | H21: 385000 | I21: =IFERROR(G21*H21,"")
A22: TOTAL | G22: =SUM(G13:G21) | I22: =SUM(I13:I21)
A24: IMPLIED READ
A25: Expected turnout | B25: =IFERROR(SUM(I13:I21),"")
A26: Modal bucket | B26: =IFERROR(INDEX($F$13:$F$21,MATCH(MAX($G$13:$G$21),$G$13:$G$21,0)),"")
A27: P(turnout above 340K) | B27: =IFERROR(INDEX($E$13:$E$21,MATCH(340000,$B$13:$B$21,0)),"")
A28: 2024 PA-07 House turnout | B28: 403314
A29: Implied change vs 2024 | B29: =IFERROR(B25/B28-1,"")
A30: Turnout is a genuine driver here, not trivia: PA-07 was decided by about a point in 2024, so which electorate shows up plausibly decides the seat.
A32: DAILY HISTORY (mid of closing bid and ask)
A33: Date | B33: Above 220K | C33: Above 260K | D33: Above 280K | E33: Above 310K | F33: Above 320K | G33: Above 340K | H33: Above 360K | I33: Above 370K
A34: 46150 | E34: 0.75 | F34: 0.63 | G34: 0.5 | H34: 0.375 | I34: 0.25
A35: 46156 | F35: 0.63 | G35: 0.5 | H35: 0.375 | I35: 0.25
A36: 46161 | F36: 0.63 | G36: 0.5 | H36: 0.375 | I36: 0.25
A37: 46164 | E37: 0.575 | F37: 0.63 | G37: 0.5 | H37: 0.375 | I37: 0.25
A38: 46165 | E38: 0.75 | F38: 0.63 | G38: 0.5 | H38: 0.375 | I38: 0.25
A39: 46170 | F39: 0.625 | H39: 0.375
A40: 46175 | E40: 0.75
A41: 46177 | F41: 0.625
A42: 46180 | E42: 0.75 | H42: 0.375 | I42: 0.25
A43: 46181 | E43: 0.75 | H43: 0.375 | I43: 0.25
A44: 46182 | E44: 0.75 | H44: 0.375 | I44: 0.25
A45: 46183 | E45: 0.75 | H45: 0.375 | I45: 0.25
A46: 46195 | E46: 0.75 | F46: 0.625 | I46: 0.215
A47: 46196 | I47: 0.25
A48: 46245 | E48: 0.75 | F48: 0.625 | G48: 0.5 | H48: 0.375 | I48: 0.25
A49: 46246 | E49: 0.75 | F49: 0.625 | G49: 0.5 | H49: 0.375 | I49: 0.25
A50: 46247 | E50: 0.75 | F50: 0.625 | G50: 0.5 | H50: 0.375 | I50: 0.25
A51: 46248 | E51: 0.75 | F51: 0.625 | G51: 0.5 | H51: 0.375 | I51: 0.25
A52: 46249 | E52: 0.75 | F52: 0.625 | G52: 0.5 | H52: 0.375 | I52: 0.25
A53: 46252 | E53: 0.75 | F53: 0.625 | G53: 0.5 | H53: 0.375 | I53: 0.25
A54: 46253 | E54: 0.75 | F54: 0.625 | G54: 0.5 | H54: 0.375 | I54: 0.25
A55: 46254 | E55: 0.75 | F55: 0.625 | G55: 0.5 | H55: 0.375 | I55: 0.25
A56: 46255 | E56: 0.75 | F56: 0.625 | G56: 0.5 | H56: 0.375 | I56: 0.25
A57: 46256 | E57: 0.755 | F57: 0.625 | G57: 0.505 | H57: 0.375 | I57: 0.255
A58: 46261 | E58: 0.755 | F58: 0.625 | G58: 0.505 | H58: 0.375 | I58: 0.255
A59: 46262 | E59: 0.755 | F59: 0.625 | G59: 0.505 | H59: 0.375 | I59: 0.255
... A76: 46291 | E76: 0.305 | F76: 0.245 | G76: 0.155 | H76: 0.095 | I76: 0.075
A77: 46293 | G77: 0.155 | H77: 0.095 | I77: 0.075
A78: 46295 | E78: 0.305 | F78: 0.245 | G78: 0.155 | H78: 0.095 | I78: 0.075
A79: 46296 | F79: 0.25
A80: 46297 | E80: 0.305 | F80: 0.25 | G80: 0.155 | H80: 0.095 | I80: 0.075
A81: 46302 | E81: 0.305 | F81: 0.25 | G81: 0.155 | H81: 0.095 | I81: 0.075
A82: 46304 | E82: 0.305 | F82: 0.25 | G82: 0.155 | H82: 0.095 | I82: 0.075
A83: 46305 | E83: 0.305 | F83: 0.25 | G83: 0.155 | H83: 0.095 | I83: 0.075
A84: 46306 | B84: 0.965 | C84: 0.815 | D84: 0.655 | E84: 0.375 | F84: 0.295 | G84: 0.175 | H84: 0.095 | I84: 0.065
A85: Columns are nested, not exclusive: each is P(turnout ≥ that threshold), so within a row they must fall from left to right. Kalshi began quoting this ladder on 2026-05-08.

Sheet PA Seat Count
A1: PA Democratic House Seats — Kalshi (KXHOUSEWINSTATE-PAD)
A2: How many of Pennsylvania's 17 House seats Democrats win on 3 Nov 2026. PA-07 is one of the seats in this count, so the ladder is a state-level read on the same question. Pulled 2026-10-12 02:24 UTC.
A4: MARKET METADATA
A5: Event | B5: KXHOUSEWINSTATE-PAD
A6: Question | B6: How many House seats will Democrats win in Pennsylvania?
A7: Resolution | B7: On Nov 3, 2026
A8: Series | B8: KXHOUSEWINSTATE
A9: Brackets listed | B9: 8
A11: LIVE BRACKET LADDER
A12: Bracket | B12: Seats (assumed) | C12: YES Bid | D12: NO Bid | E12: YES Ask | F12: Mid | G12: Normalised Prob | H12: Cumulative | I12: Prob × Seats
A13: Below 7 | B13: 6 | D13: 0.99 | E13: =IF(ISNUMBER(D13),1-D13,"") | F13: =IF(COUNT(C13,E13)=2,(C13+E13)/2,IF(ISNUMBER(E13),E13/2,"")) | G13: =IFERROR(F13/$F$21,"") | H13: =IFERROR(SUM($G$13:G13),"") | I13: =IFERROR(G13*B13,"")
A14: 7 | B14: 7 | C14: 0.02 | D14: 0.94 | E14: =IF(ISNUMBER(D14),1-D14,"") | F14: =IF(COUNT(C14,E14)=2,(C14+E14)/2,IF(ISNUMBER(E14),E14/2,"")) | G14: =IFERROR(F14/$F$21,"") | H14: =IFERROR(SUM($G$13:G14),"") | I14: =IFERROR(G14*B14,"")
A15: 8 | B15: 8 | C15: 0.03 | D15: 0.91 | E15: =IF(ISNUMBER(D15),1-D15,"") | F15: =IF(COUNT(C15,E15)=2,(C15+E15)/2,IF(ISNUMBER(E15),E15/2,"")) | G15: =IFERROR(F15/$F$21,"") | H15: =IFERROR(SUM($G$13:G15),"") | I15: =IFERROR(G15*B15,"")
A16: 9 | B16: 9 | C16: 0.19 | D16: 0.78 | E16: =IF(ISNUMBER(D16),1-D16,"") | F16: =IF(COUNT(C16,E16)=2,(C16+E16)/2,IF(ISNUMBER(E16),E16/2,"")) | G16: =IFERROR(F16/$F$21,"") | H16: =IFERROR(SUM($G$13:G16),"") | I16: =IFERROR(G16*B16,"")
A17: 10 | B17: 10 | C17: 0.21 | D17: 0.76 | E17: =IF(ISNUMBER(D17),1-D17,"") | F17: =IF(COUNT(C17,E17)=2,(C17+E17)/2,IF(ISNUMBER(E17),E17/2,"")) | G17: =IFERROR(F17/$F$21,"") | H17: =IFERROR(SUM($G$13:G17),"") | I17: =IFERROR(G17*B17,"")
A18: 11 | B18: 11 | C18: 0.38 | D18: 0.58 | E18: =IF(ISNUMBER(D18),1-D18,"") | F18: =IF(COUNT(C18,E18)=2,(C18+E18)/2,IF(ISNUMBER(E18),E18/2,"")) | G18: =IFERROR(F18/$F$21,"") | H18: =IFERROR(SUM($G$13:G18),"") | I18: =IFERROR(G18*B18,"")
A19: 12 | B19: 12 | C19: 0.02 | D19: 0.96 | E19: =IF(ISNUMBER(D19),1-D19,"") | F19: =IF(COUNT(C19,E19)=2,(C19+E19)/2,IF(ISNUMBER(E19),E19/2,"")) | G19: =IFERROR(F19/$F$21,"") | H19: =IFERROR(SUM($G$13:G19),"") | I19: =IFERROR(G19*B19,"")
A20: Above 12 | B20: 13 | C20: 0.02 | D20: 0.95 | E20: =IF(ISNUMBER(D20),1-D20,"") | F20: =IF(COUNT(C20,E20)=2,(C20+E20)/2,IF(ISNUMBER(E20),E20/2,"")) | G20: =IFERROR(F20/$F$21,"") | H20: =IFERROR(SUM($G$13:G20),"") | I20: =IFERROR(G20*B20,"")
A21: TOTAL | F21: =SUM(F13:F20) | G21: =SUM(G13:G20) | I21: =SUM(I13:I20)
A23: IMPLIED READ
A24: Expected Democratic seats | B24: =IFERROR(SUM(I13:I20),"")
A25: Modal bracket | B25: =IFERROR(INDEX($A$13:$A$20,MATCH(MAX($G$13:$G$20),$G$13:$G$20,0)),"")
A26: P(9 or more seats) | B26: =IFERROR(SUMIF($B$13:$B$20,">=9",$G$13:$G$20),"")
A27: PA seats held by Democrats now | B27: 8
A28: Implied net gain | B28: =IFERROR(B24-B27,"")
A29: PA's delegation is 17 seats. The 8-seat current baseline is entered by hand as the Democratic count going into the 2026 cycle — check it against the current delegation before relying on the net-gain line. A market expectation above that baseline is consistent with Democrats favoured to flip PA-07.
A31: DAILY BRACKET HISTORY (mid of YES bid and derived ask)
A32: Date | B32: Below 7 | C32: 7 | D32: 8 | E32: 9 | F32: 10 | G32: 11 | H32: 12 | I32: Above 12
A33: 46254 | B33: 0.015 | C33: 0.025 | D33: 0.13 | E33: 0.405 | F33: 0.295 | G33: 0.145 | H33: 0.025 | I33: 0.015
A34: 46255 | B34: 0.015 | C34: 0.025 | D34: 0.125 | E34: 0.355 | F34: 0.295 | G34: 0.215 | H34: 0.015 | I34: 0.015
A35: 46256 | B35: 0.015 | C35: 0.035 | D35: 0.125 | E35: 0.355 | F35: 0.295 | G35: 0.23 | H35: 0.015 | I35: 0.015
A36: 46257 | B36: 0.005 | C36: 0.04 | D36: 0.085 | E36: 0.3 | F36: 0.26 | G36: 0.26 | H36: 0.015 | I36: 0.01
A37: 46258 | B37: 0.005 | C37: 0.045 | D37: 0.065 | E37: 0.285 | F37: 0.235 | G37: 0.255 | H37: 0.035 | I37: 0.01
A38: 46259 | C38: 0.045 | D38: 0.06 | E38: 0.305 | F38: 0.235 | G38: 0.255 | H38: 0.035
A39: 46260 | C39: 0.04 | E39: 0.31 | F39: 0.235 | G39: 0.255 | H39: 0.035 | I39: 0.005
A40: 46261 | B40: 0.005 | C40: 0.045 | D40: 0.055 | E40: 0.31 | F40: 0.185 | G40: 0.27 | H40: 0.035 | I40: 0.01
A41: 46262 | C41: 0.045 | D41: 0.04 | E41: 0.3 | F41: 0.185 | G41: 0.325 | H41: 0.045
A42: 46263 | C42: 0.045 | D42: 0.035 | E42: 0.32 | F42: 0.195 | G42: 0.33 | H42: 0.055
A43: 46264 | C43: 0.045 | D43: 0.05 | E43: 0.33 | F43: 0.19 | G43: 0.335 | H43: 0.05
A44: 46265 | B44: 0.005 | C44: 0.05 | D44: 0.055 | E44: 0.325 | F44: 0.175 | G44: 0.34 | H44: 0.035
A45: 46266 | D45: 0.075 | E45: 0.325 | F45: 0.18 | G45: 0.33 | H45: 0.025
A46: 46267 | C46: 0.05 | D46: 0.065 | E46: 0.33 | F46: 0.175 | G46: 0.325 | H46: 0.025
A47: 46268 | C47: 0.05 | D47: 0.06 | E47: 0.325 | F47: 0.175 | G47: 0.33 | H47: 0.02
A48: 46269 | B48: 0.005 | C48: 0.05 | D48: 0.065 | E48: 0.33 | F48: 0.175 | G48: 0.315 | H48: 0.025
A49: 46270 | D49: 0.07 | E49: 0.33 | F49: 0.175 | G49: 0.32 | H49: 0.03
A50: 46271 | C50: 0.05 | D50: 0.07 | E50: 0.335 | F50: 0.175 | G50: 0.32
A51: 46272 | D51: 0.07 | E51: 0.335 | F51: 0.175 | G51: 0.3
A52: 46273 | D52: 0.07 | E52: 0.345 | F52: 0.175 | G52: 0.29
A53: 46274 | D53: 0.07 | E53: 0.335 | F53: 0.175 | G53: 0.29
A54: 46275 | D54: 0.07 | E54: 0.345 | F54: 0.18 | G54: 0.31
A55: 46276 | C55: 0.045 | D55: 0.075 | E55: 0.34 | F55: 0.185 | G55: 0.29
A56: 46277 | C56: 0.055 | D56: 0.07 | E56: 0.33 | F56: 0.175 | G56: 0.295
A57: 46278 | C57: 0.045 | D57: 0.06 | E57: 0.33 | F57: 0.175 | G57: 0.295 | I57: 0.005
A58: 46279 | C58: 0.05 | D58: 0.06 | E58: 0.33 | F58: 0.18 | G58: 0.29 | I58: 0.01
A59: 46280 | C59: 0.05 | D59: 0.08 | E59: 0.33 | F59: 0.175 | G59: 0.295
A60: 46281 | C60: 0.05 | D60: 0.07 | E60: 0.33 | F60: 0.165 | G60: 0.295
A61: 46282 | C61: 0.055 | D61: 0.06 | E61: 0.33 | F61: 0.16 | G61: 0.3
A62: 46283 | C62: 0.055 | D62: 0.06 | E62: 0.345 | F62: 0.165 | G62: 0.29
A63: 46284 | C63: 0.05 | D63: 0.06 | E63: 0.31 | F63: 0.26 | G63: 0.31 | I63: 0.005
A64: 46285 | C64: 0.05 | D64: 0.055 | E64: 0.325 | F64: 0.24 | G64: 0.325
A65: 46286 | C65: 0.045 | D65: 0.065 | E65: 0.32 | F65: 0.205 | G65: 0.295
A66: 46287 | C66: 0.03 | D66: 0.045 | E66: 0.31 | F66: 0.215 | G66: 0.315
A67: 46288 | C67: 0.03 | D67: 0.035 | E67: 0.315 | F67: 0.235 | G67: 0.32 | H67: 0.02
A68: 46289 | C68: 0.045 | D68: 0.135 | E68: 0.3 | F68: 0.26 | G68: 0.315 | H68: 0.03 | I68: 0.01
A69: 46290 | C69: 0.15 | D69: 0.11 | E69: 0.255 | F69: 0.265 | G69: 0.39 | H69: 0.03 | I69: 0.015
A70: 46291 | C70: 0.05 | D70: 0.11 | E70: 0.3 | F70: 0.265 | G70: 0.315 | H70: 0.025
A71: 46292 | C71: 0.045 | D71: 0.1 | E71: 0.315 | F71: 0.255 | G71: 0.305 | H71: 0.015
A72: 46293 | C72: 0.045 | D72: 0.1 | E72: 0.32 | F72: 0.21 | G72: 0.315 | H72: 0.02
A73: 46294 | C73: 0.045 | D73: 0.105 | E73: 0.32 | F73: 0.21 | G73: 0.28
A74: 46295 | C74: 0.04 | D74: 0.09 | E74: 0.31 | F74: 0.23 | G74: 0.28 | H74: 0.02
A75: 46296 | C75: 0.04 | D75: 0.085 | E75: 0.295 | F75: 0.205 | G75: 0.31 | H75: 0.02
A76: 46297 | C76: 0.035 | D76: 0.085 | E76: 0.305 | F76: 0.205 | G76: 0.285 | H76: 0.02
A77: 46298 | C77: 0.035 | D77: 0.06 | E77: 0.245 | F77: 0.265 | G77: 0.345 | H77: 0.02
A78: 46299 | C78: 0.035 | D78: 0.065 | E78: 0.2 | F78: 0.25 | G78: 0.38
A79: 46300 | C79: 0.04 | D79: 0.055 | E79: 0.19 | F79: 0.24 | G79: 0.355 | H79: 0.025 | I79: 0.035
A80: 46301 | C80: 0.035 | D80: 0.06 | E80: 0.185 | F80: 0.225 | G80: 0.385 | I80: 0.025
A81: 46302 | C81: 0.04 | D81: 0.055 | E81: 0.195 | F81: 0.18 | G81: 0.375 | H81: 0.025 | I81: 0.025
A82: 46303 | C82: 0.025 | D82: 0.05 | E82: 0.205 | F82: 0.25 | G82: 0.335 | H82: 0.03 | I82: 0.03
A83: 46304 | C83: 0.03 | D83: 0.055 | E83: 0.205 | F83: 0.22 | G83: 0.365 | H83: 0.03 | I83: 0.03
A84: 46305 | C84: 0.04 | D84: 0.055 | E84: 0.205 | F84: 0.195 | G84: 0.38 | H84: 0.03 | I84: 0.03
A85: 46306 | C85: 0.035 | D85: 0.06 | E85: 0.215 | F85: 0.24 | G85: 0.41 | H85: 0.025 | I85: 0.03
A86: Kalshi began quoting this ladder on 20 Aug 2026, so the history is only 53 days long. Values are the mid of the daily closing YES bid and the ask derived from the closing NO bid; where only one side closed, the same fallback as the live ladder applies.

Sheet Polls
A1: Polls — PA-07
A2: General-election and Democratic-primary polling for Pennsylvania's 7th, from the NYT/538 house-poll file (house.csv), plus the district and incumbent profile from GovTrack. Percentages stored as fractions. Compiled 2026-10-12 02:24 UTC.
A4: HOW TO USE THIS SHEET
A5: • Add a general-election poll by typing into the next blank blue row of the log below — rows are pre-formulated to row 28, so columns L to O fill themselves.
A6: • Percentages are percent-formatted, so type 47% (not 47). Sponsor Lean must be D, R or None.
A7: • The three yellow cells in POLLING AVERAGE drive the weighting. Change them and everything downstream updates.
A8: • A greyed EXAMPLE row at the bottom shows the expected format. It sits outside every averaged range and can be deleted.
A10: GENERAL ELECTION POLL LOG — Brooks (D) vs Mackenzie (R)
A11: Pollster | B11: Sponsor / Client | C11: Sponsor Lean | D11: Field Start | E11: Field End | F11: Sample | G11: Pop. | H11: MoE | I11: Brooks (D) | J11: Mackenzie (R) | K11: Other / Undecided | L11: Margin (D−R) | M11: Days Ago | N11: Recency Weight | O11: Poll Weight
A12: GBAO | B12: House Majority PAC | C12: D | D12: 46202 | E12: 46205 | F12: 550 | G12: LV | I12: 0.47 | J12: 0.43 | L12: =IF(COUNT(I12:J12)=2,I12-J12,"") | M12: =IF(ISNUMBER(E12),$B$28-E12,"") | N12: =IF(ISNUMBER(M12),0.5^(M12/$B$29),"") | O12: =IF(AND(ISNUMBER(F12),ISNUMBER(N12)),F12*N12,"")
L13: =IF(COUNT(I13:J13)=2,I13-J13,"") | M13: =IF(ISNUMBER(E13),$B$28-E13,"") | N13: =IF(ISNUMBER(M13),0.5^(M13/$B$29),"") | O13: =IF(AND(ISNUMBER(F13),ISNUMBER(N13)),F13*N13,"")
L14: =IF(COUNT(I14:J14)=2,I14-J14,"") | M14: =IF(ISNUMBER(E14),$B$28-E14,"") | N14: =IF(ISNUMBER(M14),0.5^(M14/$B$29),"") | O14: =IF(AND(ISNUMBER(F14),ISNUMBER(N14)),F14*N14,"")
L15: =IF(COUNT(I15:J15)=2,I15-J15,"") | M15: =IF(ISNUMBER(E15),$B$28-E15,"") | N15: =IF(ISNUMBER(M15),0.5^(M15/$B$29),"") | O15: =IF(AND(ISNUMBER(F15),ISNUMBER(N15)),F15*N15,"")
L16: =IF(COUNT(I16:J16)=2,I16-J16,"") | M16: =IF(ISNUMBER(E16),$B$28-E16,"") | N16: =IF(ISNUMBER(M16),0.5^(M16/$B$29),"") | O16: =IF(AND(ISNUMBER(F16),ISNUMBER(N16)),F16*N16,"")
L17: =IF(COUNT(I17:J17)=2,I17-J17,"") | M17: =IF(ISNUMBER(E17),$B$28-E17,"") | N17: =IF(ISNUMBER(M17),0.5^(M17/$B$29),"") | O17: =IF(AND(ISNUMBER(F17),ISNUMBER(N17)),F17*N17,"")
L18: =IF(COUNT(I18:J18)=2,I18-J18,"") | M18: =IF(ISNUMBER(E18),$B$28-E18,"") | N18: =IF(ISNUMBER(M18),0.5^(M18/$B$29),"") | O18: =IF(AND(ISNUMBER(F18),ISNUMBER(N18)),F18*N18,"")
L19: =IF(COUNT(I19:J19)=2,I19-J19,"") | M19: =IF(ISNUMBER(E19),$B$28-E19,"") | N19: =IF(ISNUMBER(M19),0.5^(M19/$B$29),"") | O19: =IF(AND(ISNUMBER(F19),ISNUMBER(N19)),F19*N19,"")
L20: =IF(COUNT(I20:J20)=2,I20-J20,"") | M20: =IF(ISNUMBER(E20),$B$28-E20,"") | N20: =IF(ISNUMBER(M20),0.5^(M20/$B$29),"") | O20: =IF(AND(ISNUMBER(F20),ISNUMBER(N20)),F20*N20,"")
L21: =IF(COUNT(I21:J21)=2,I21-J21,"") | M21: =IF(ISNUMBER(E21),$B$28-E21,"") | N21: =IF(ISNUMBER(M21),0.5^(M21/$B$29),"") | O21: =IF(AND(ISNUMBER(F21),ISNUMBER(N21)),F21*N21,"")
L22: =IF(COUNT(I22:J22)=2,I22-J22,"") | M22: =IF(ISNUMBER(E22),$B$28-E22,"") | N22: =IF(ISNUMBER(M22),0.5^(M22/$B$29),"") | O22: =IF(AND(ISNUMBER(F22),ISNUMBER(N22)),F22*N22,"")
L23: =IF(COUNT(I23:J23)=2,I23-J23,"") | M23: =IF(ISNUMBER(E23),$B$28-E23,"") | N23: =IF(ISNUMBER(M23),0.5^(M23/$B$29),"") | O23: =IF(AND(ISNUMBER(F23),ISNUMBER(N23)),F23*N23,"")
L24: =IF(COUNT(I24:J24)=2,I24-J24,"") | M24: =IF(ISNUMBER(E24),$B$28-E24,"") | N24: =IF(ISNUMBER(M24),0.5^(M24/$B$29),"") | O24: =IF(AND(ISNUMBER(F24),ISNUMBER(N24)),F24*N24,"")
A25: Source: house.csv (NYT / 538 house-poll file), rows filtered to state = PA and seat_number = 7, stage = general. The pollster-rating fields (numeric_grade, pollscore, transparency_score) are empty for every PA-07 poll in that file.
A27: POLLING AVERAGE
A28: Reference date (as of) | B28: 46307
A29: Recency half-life (days) | B29: 45
A30: Partisan house-effect haircut | B30: 0.03
A32: Polls in average | B32: =COUNT(L12:L24)
A33: Weighted Brooks (D) | B33: =IFERROR(SUMPRODUCT(I12:I24,O12:O24)/SUM(O12:O24),"")
A34: Weighted Mackenzie (R) | B34: =IFERROR(SUMPRODUCT(J12:J24,O12:O24)/SUM(O12:O24),"")
A35: Weighted margin (D−R) | B35: =IFERROR(B33-B34,"")
A36: Net partisan sponsorship | B36: =IFERROR((SUMIF($C$12:$C$24,"D",$O$12:$O$24)-SUMIF($C$12:$C$24,"R",$O$12:$O$24))/SUM($O$12:$O$24),"")
A37: Adjusted margin (D−R) | B37: =IFERROR(B35-B36*B30,"")
A38: Simple (unweighted) margin | B38: =IFERROR(AVERAGE(L12:L24),"")
A39: Most recent poll date | B39: =IFERROR(MAX(E12:E24),"")
A40: Days since most recent poll | B40: =IFERROR($B$28-MAX(E12:E24),"")
A41: Only one public general-election poll exists for PA-07 so far, and it is Democratic-sponsored. The average is a single data point wearing a weighting scheme — read the adjusted margin, and lean on the market sheets.
A43: DEMOCRATIC PRIMARY POLLS (settled 19 May 2026) — for calibration
A44: Pollster | B44: Sponsor / Client | C44: Lean | D44: Field Start | E44: Field End | F44: Sample | G44: Pop. | H44: Brooks | I44: McClure | J44: Crosswell | K44: Obando-Derstine | L44: Undecided | M44: Other | N44: Brooks Lead | O44: Leader
A45: Change Research | B45: (none) | C45: None | D45: 46007 | E45: 46010 | F45: 892 | G45: LV | H45: 0.11 | I45: 0.17 | J45: 0.05 | K45: 0.1 | L45: 0.53 | M45: 0.03 | N45: =IF(COUNT(H45:K45)>1,H45-MAX(I45:K45),"") | O45: =IF(COUNT(H45:K45)=0,"",INDEX($H$44:$K$44,MATCH(MAX(H45:K45),H45:K45,0)))
A46: GBAO | B46: Congressional Progressive Caucus PAC (CPC PAC) | C46: D | D46: 46078 | E46: 46082 | F46: 500 | G46: LV | H46: 0.13 | I46: 0.19 | J46: 0.08 | K46: 0.13 | L46: 0.44 | M46: 0.03 | N46: =IF(COUNT(H46:K46)>1,H46-MAX(I46:K46),"") | O46: =IF(COUNT(H46:K46)=0,"",INDEX($H$44:$K$44,MATCH(MAX(H46:K46),H46:K46,0)))
A47: GBAO | B47: Congressional Progressive Caucus PAC (CPC PAC) | C47: D | D47: 46128 | E47: 46131 | F47: 400 | G47: LV | H47: 0.24 | I47: 0.17 | J47: 0.09 | K47: 0.12 | L47: 0.36 | M47: 0.02 | N47: =IF(COUNT(H47:K47)>1,H47-MAX(I47:K47),"") | O47: =IF(COUNT(H47:K47)=0,"",INDEX($H$44:$K$44,MATCH(MAX(H47:K47),H47:K47,0)))
A48: Tavern Research | B48: (none) | C48: None | D48: 46159 | E48: 46159 | F48: 613 | G48: LV | H48: 0.26 | I48: 0.17 | J48: 0.16 | K48: 0.08 | L48: 0.31 | M48: 0.01 | N48: =IF(COUNT(H48:K48)>1,H48-MAX(I48:K48),"") | O48: =IF(COUNT(H48:K48)=0,"",INDEX($H$44:$K$44,MATCH(MAX(H48:K48),H48:K48,0)))
A49: ACTUAL RESULT | B49: Primary, 19 May 2026 | C49: — | E49: 46161 | H49: 0.414
A50: Source: house.csv, stage = primary. Undecided is the "Don't know" answer; Other pools "Someone else" and "Would not vote". These markets are settled — the section is kept for calibration, not tracking.
A52: DISTRICT & INCUMBENT PROFILE — GovTrack
A53: Incumbent | B53: Ryan Mackenzie (R)
A54: GovTrack profile | B54: govtrack.us/congress/members/ryan_mackenzie/457017
A55: Serving since | B55: 2025-01-03
A56: Term ends | B56: 2027-01-03
A57: Age | B57: 44
A58: Next election | B58: 2026
A59: Caucus | B59: Main Street Caucus
A60: Committees | B60: Education & Workforce (Chair, Workforce Protections subcttee); Foreign Affairs; Homeland Security
A61: Missed votes | B61: 13 of 645 roll calls, Jan 2025 – Jul 2026 (2.0%) — on par with the 2.0% median among sitting representatives
A62: Top sponsorship areas | B62: Taxation 23%; Armed Forces & National Security 23%; Government Operations 18%; Health 9%
A63: PA senators | B63: John Fetterman (D, since 2023); Dave McCormick (R, since 2025)
A64: Redistricting caveat | B64: GovTrack notes some states are changing districts for 2026; its map reflects the 2024 lines. Confirm PA-07's boundaries before treating district-level history as like-for-like.
A66: SUPPLEMENTARY DISTRICT NUMBERS (no head-to-head)
A67: Source | B67: Sponsor | C67: Metric | E67: Favourable / Approve | F67: Unfavourable / Disapprove | G67: Net
A68: GBAO (29 Jun – 2 Jul 2026) | B68: House Majority PAC | C68: Trump favourability in PA-07 | E68: 0.44 | F68: 0.51 | G68: =E68-F68
A69: GBAO (29 Jun – 2 Jul 2026) | B69: House Majority PAC | C69: 2024 recall: Trump vs Harris | E69: 0.47 | F69: 0.46 | G69: =E69-F69
A70: House Majority Forward (n/d) | B70: House Majority Forward | C70: Mackenzie job approval | E70: 0.27 | F70: 0.41 | G70: =E70-F70
A71: House Majority Forward (n/d) | B71: House Majority Forward | C71: Trump favourability in PA-07 | E71: 0.4 | F71: 0.56 | G71: =E71-F71
A72: House Majority Forward (n/d) | B72: House Majority Forward | C72: Trump job approval in PA-07 | E72: 0.41 | F72: 0.57 | G72: =E72-F72
A73: The 2024 recall line is the sample's remembered 2024 presidential vote, so its net reads as Trump's recalled margin. House Majority Forward figures were reported by PoliticsPA without field dates, sample size or MoE, and predate the May primary. Neither source appears in house.csv.
A75: EXAMPLE ROW — format reference only, delete before use
A76: Pollster | B76: Sponsor / Client | C76: Sponsor Lean | D76: Field Start | E76: Field End | F76: Sample | G76: Pop. | H76: MoE | I76: Brooks (D) | J76: Mackenzie (R) | K76: Other / Undecided | L76: Margin (D−R) | M76: Days Ago | N76: Recency Weight | O76: Poll Weight
A77: Emerson College | B77: Emerson / The Hill | C77: None | D77: 46279 | E77: 46282 | F77: 700 | G77: LV | H77: 0.037 | I77: 0.485 | J77: 0.455 | K77: 0.06 | L77: =I77-J77 | M77: =$B$28-E77 | N77: =0.5^(M77/$B$29) | O77: =F77*N77

Sheet Forecast & Aggregators
A1: Forecast & Aggregators
A2: Outside views of PA-07: a statistical forecast, a third-party odds tracker, and what each disagrees with the markets about. Compiled 2026-10-12 02:24 UTC.
A4: MODEL vs MARKET — the headline disagreement
A5: Market consensus P(Dem) | B5: =AVERAGE(Polymarket!D19,Kalshi!E17) | D5: Equal-weighted mean of the two venue mids, read directly from their APIs.
A6: PollsMax model P(Dem) | B6: 0.595 | D6: Polls plus fundamentals through a Monte Carlo, not a traded price.
A7: Gap (market − model) | B7: =IF(AND(ISNUMBER(B5),ISNUMBER(B6)),B5-B6,"")
A8: Projected margin (model) | B8: 0.6 | D8: Model's central vote-margin estimate, D positive.
A9: Rating (model)
A10: A gap this wide is the single most interesting number in this workbook: the model projects a roughly one-point race yet the markets price the Democrat far above even odds. Either the market knows something the fundamentals do not, or it is overconfident about a tossup.
A12: POLLSMAX — forecast detail
A13: Brooks (D) win probability | B13: 0.595
A14: Mackenzie (R) win probability | B14: 0.405
A15: Projected margin (D−R) | B15: 0.6
A16: Polling average — Brooks | B16: 0.47
A17: Polling average — Mackenzie | B17: 0.43
A18: Polling average margin | B18: 0.04
A19: Polls in their average | B19: 1
A20: Average as of | B20: August 30, 2026
A21: Retrieved | B21: 2026-08-30T16:21:45Z
A22: Uncertainty band: Site plots a daily Upper/Lower simulation band around both the projected vote share and the win-probability trend lines, but does not disclose what confidence/percentile level those bands represent. As of the last plotted day (2026-08-19): projected vote share Brooks 50.3% [48.49-52.12] / Mackenzie 49.7% [47.88-51.51]; win probability Brooks 59.53% [54.53-64.53] / Mackenzie 40.47% [35.47-45.47].
A24: POLLSMAX — methodology, in their words
A25: Summary | B25: Pollsmax runs two linked systems: (1) a polling-average model that produces a time-weighted, partisanship-adjusted mean of all polls for a race, and (2) a forecast model that blends that polling average with structural 'fundamentals' (generic ballot, presidential approval, incumbency, prior results, partisan lean/PVI, and Pollsmax's own editorial rating) into a composite margin, which is then run through 10,000-100,000 daily Monte Carlo simulations to produce win probabilities, a projected margin, and projected vote shares.
A26: Weighting | B26: Race-page polling averages are a recency-weighted mean of all polls dated on or before each chart day, with the recency curve adapting to how many polls exist so sparse races (like this one, with only 1 poll) do not overreact to a single survey. Forecasts blend polling with fundamentals; at full poll depth (6+ polls for House) the standardized House weights are: Polling 30%, Editorial rating 40%, PVI 10%, prior House result 10%, incumbency 5%, generic ballot 2.5%, Trump approval 2.5%. Below the poll-count threshold, 'the polling share drops by five percentage points for each missing poll and the non-polling factors are rescaled proportionally.' For this specific PA-7 race (1 poll, well below the 6-poll threshold), the site's own displayed input-weight breakdown shows no separate polling-margin line at all: Trump Approval 3.6%, Generic Ballot 3.6%, Past Race Results 14.3%, Incumbency 7.1%, Partisan Lean 14.3%, Editorial Rating 57.1% (sums to 100%).
A27: Recency | B27: 'More recent surveys receive higher weight' in the polling average. Trump approval and the generic ballot use a rolling ~28-day sample-size-weighted window rather than the race-specific recency curve.
A28: Pollster quality | B28: No explicit per-pollster letter grade or quality score is shown on the race, forecast, or methodology pages, and no separate 'pollster ratings' page was found linked from the site. The only pollster-side adjustment described is the partisan-sponsor tag adjustment (see house_effects).
A29: House effects | B29: 'Before averaging, polls from pollsters tagged with a party sponsor, (D) or (R) in the pollster name, receive a fixed margin adjustment on the modeled values. This adjustment is applied whenever the tag is present.' Separately, when 3+ paired polls exist, Pollsmax computes 'a robust consensus margin (median Democratic minus Republican)' and downweights (but does not delete) outliers via a median-absolute-deviation (MAD) scale; with only 1 poll in this race that outlier step cannot engage.
A30: Forecast model | B30: The composite expected Democratic margin from the weighted blend of polling and fundamentals 'is converted to a win probability using a calibrated margin-to-odds curve, ... slightly steeper than a pure linear scale.' House races use 'a steeper House-specific curve' than Senate/governor. A Monte Carlo simulation (10,000 draws per House district daily) then draws 'from a normal distribution centered on a calibrated target margin' that 'blends the odds-implied margin from the composite win probability with the raw composite margin itself.' 'Simulation spread (sigma) is calibrated so the model's win probability matches anchor points at standard rating tiers; for example, roughly 95% for a safe seat and 75% for a likely seat.' The displayed race rating (e.g. 'Tilt D') is 'derived from the composite win probability using fixed probability breakpoints aligned with Pollsmax editorial tiers.'
A31: Input weights (PA-07) | B31: trump_approval_pct = 3.6; trump_approval_lean = Democratic-leaning; generic_ballot_pct = 3.6; generic_ballot_lean = Democratic-leaning; past_race_results_pct = 14.3; past_race_results_lean = Republican-leaning; incumbency_pct = 7.1; incumbency_lean = Republican-leaning; partisan_lean_pct = 14.3; partisan_lean_lean = Democratic-leaning; editorial_rating_pct = 57.1; editorial_rating_lean = None
A32: Their polling average rests on ONE poll, and that poll is Democratic-sponsored. By their own description the forecast leans mostly on fundamentals and an editorial rating rather than on polling, which is worth knowing before treating it as an independent check on the market.
A34: POLLSMAX — daily forecast trend
A35: Date | B35: Brooks win prob (model) | C35: Upper | D35: Lower | E35: Brooks vote share | F35: Mackenzie vote share | G35: Polymarket P(Dem) same day | H35: Model − market | I35: Axis label
A36: 46023 | B36: 0.5063 | C36: 0.5563 | D36: 0.4563 | E36: 0.5 | F36: 0.5 | G36: =IFERROR(IF(INDEX(Polymarket!$B$25:$B$303,MATCH($A36,Polymarket!$A$25:$A$303,0))=0,"",INDEX(Polymarket!$B$25:$B$303,MATCH($A36,Polymarket!$A$25:$A$303,0))),"") | H36: =IF(AND(ISNUMBER(B36),ISNUMBER(G36)),B36-G36,"") | I36: 01 Jan
A37: 46024 | B37: 0.5016 | C37: 0.5516 | D37: 0.4516 | E37: 0.5 | F37: 0.5 | G37: =IFERROR(IF(INDEX(Polymarket!$B$25:$B$303,MATCH($A37,Polymarket!$A$25:$A$303,0))=0,"",INDEX(Polymarket!$B$25:$B$303,MATCH($A37,Polymarket!$A$25:$A$303,0))),"") | H37: =IF(AND(ISNUMBER(B37),ISNUMBER(G37)),B37-G37,"") | I37: 02 Jan
A38: 46025 | B38: 0.5082 | C38: 0.5582 | D38: 0.4582 | E38: 0.5 | F38: 0.5 | G38: =IFERROR(IF(INDEX(Polymarket!$B$25:$B$303,MATCH($A38,Polymarket!$A$25:$A$303,0))=0,"",INDEX(Polymarket!$B$25:$B$303,MATCH($A38,Polymarket!$A$25:$A$303,0))),"") | H38: =IF(AND(ISNUMBER(B38),ISNUMBER(G38)),B38-G38,"") | I38: 03 Jan
A39: 46026 | B39: 0.5019 | C39: 0.5519 | D39: 0.4519 | E39: 0.5 | F39: 0.5 | G39: =IFERROR(IF(INDEX(Polymarket!$B$25:$B$303,MATCH($A39,Polymarket!$A$25:$A$303,0))=0,"",INDEX(Polymarket!$B$25:$B$303,MATCH($A39,Polymarket!$A$25:$A$303,0))),"") | H39: =IF(AND(ISNUMBER(B39),ISNUMBER(G39)),B39-G39,"") | I39: 04 Jan
A40: 46027 | B40: 0.4969 | C40: 0.5469 | D40: 0.4469 | E40: 0.5 | F40: 0.5 | G40: =IFERROR(IF(INDEX(Polymarket!$B$25:$B$303,MATCH($A40,Polymarket!$A$25:$A$303,0))=0,"",INDEX(Polymarket!$B$25:$B$303,MATCH($A40,Polymarket!$A$25:$A$303,0))),"") | H40: =IF(AND(ISNUMBER(B40),ISNUMBER(G40)),B40-G40,"") | I40: 05 Jan
A41: 46028 | B41: 0.5075 | C41: 0.5575 | D41: 0.4575 | E41: 0.5 | F41: 0.5 | G41: =IFERROR(IF(INDEX(Polymarket!$B$25:$B$303,MATCH($A41,Polymarket!$A$25:$A$303,0))=0,"",INDEX(Polymarket!$B$25:$B$303,MATCH($A41,Polymarket!$A$25:$A$303,0))),"") | H41: =IF(AND(ISNUMBER(B41),ISNUMBER(G41)),B41-G41,"") | I41: 06 Jan
A42: 46029 | B42: 0.5191 | C42: 0.5691 | D42: 0.4691 | E42: 0.501 | F42: 0.5 | G42: =IFERROR(IF(INDEX(Polymarket!$B$25:$B$303,MATCH($A42,Polymarket!$A$25:$A$303,0))=0,"",INDEX(Polymarket!$B$25:$B$303,MATCH($A42,Polymarket!$A$25:$A$303,0))),"") | H42: =IF(AND(ISNUMBER(B42),ISNUMBER(G42)),B42-G42,"") | I42: 07 Jan
A43: 46030 | B43: 0.5055 | C43: 0.5555 | D43: 0.4555 | E43: 0.5 | F43: 0.5 | G43: =IFERROR(IF(INDEX(Polymarket!$B$25:$B$303,MATCH($A43,Polymarket!$A$25:$A$303,0))=0,"",INDEX(Polymarket!$B$25:$B$303,MATCH($A43,Polymarket!$A$25:$A$303,0))),"") | H43: =IF(AND(ISNUMBER(B43),ISNUMBER(G43)),B43-G43,"") | I43: 08 Jan
A44: 46031 | B44: 0.5111 | C44: 0.5611 | D44: 0.4611 | E44: 0.501 | F44: 0.5 | G44: =IFERROR(IF(INDEX(Polymarket!$B$25:$B$303,MATCH($A44,Polymarket!$A$25:$A$303,0))=0,"",INDEX(Polymarket!$B$25:$B$303,MATCH($A44,Polymarket!$A$25:$A$303,0))),"") | H44: =IF(AND(ISNUMBER(B44),ISNUMBER(G44)),B44-G44,"") | I44: 09 Jan
A45: 46032 | B45: 0.5078 | C45: 0.5578 | D45: 0.4578 | E45: 0.5 | F45: 0.5 | G45: =IFERROR(IF(INDEX(Polymarket!$B$25:$B$303,MATCH($A45,Polymarket!$A$25:$A$303,0))=0,"",INDEX(Polymarket!$B$25:$B$303,MATCH($A45,Polymarket!$A$25:$A$303,0))),"") | H45: =IF(AND(ISNUMBER(B45),ISNUMBER(G45)),B45-G45,"") | I45: 10 Jan
A46: 46033 | B46: 0.5042 | C46: 0.5542 | D46: 0.4542 | E46: 0.5 | F46: 0.5 | G46: =IFERROR(IF(INDEX(Polymarket!$B$25:$B$303,MATCH($A46,Polymarket!$A$25:$A$303,0))=0,"",INDEX(Polymarket!$B$25:$B$303,MATCH($A46,Polymarket!$A$25:$A$303,0))),"") | H46: =IF(AND(ISNUMBER(B46),ISNUMBER(G46)),B46-G46,"") | I46: 11 Jan
A47: 46034 | B47: 0.5131 | C47: 0.5631 | D47: 0.4631 | E47: 0.501 | F47: 0.5 | G47: =IFERROR(IF(INDEX(Polymarket!$B$25:$B$303,MATCH($A47,Polymarket!$A$25:$A$303,0))=0,"",INDEX(Polymarket!$B$25:$B$303,MATCH($A47,Polymarket!$A$25:$A$303,0))),"") | H47: =IF(AND(ISNUMBER(B47),ISNUMBER(G47)),B47-G47,"") | I47: 12 Jan
... A266: 46253 | B266: 0.5953 | C266: 0.6453 | D266: 0.5453 | E266: 0.503 | F266: 0.497 | G266: =IFERROR(IF(INDEX(Polymarket!$B$25:$B$303,MATCH($A266,Polymarket!$A$25:$A$303,0))=0,"",INDEX(Polymarket!$B$25:$B$303,MATCH($A266,Polymarket!$A$25:$A$303,0))),"") | H266: =IF(AND(ISNUMBER(B266),ISNUMBER(G266)),B266-G266,"") | I266: 19 Aug
A267: Series runs 2026-01-01 to 2026-08-19. NOTE: PollsMax's own page claims a later 'last updated' time than the final plotted point — their chart data stops at 2026-08-19, so the headline figures above may be fresher than this trend.
A269: THIRD-PARTY ODDS TRACKERS — treat as a data-quality check, not a price
A270: Tracker | B270: Their P(Dem) | C270: Venue claimed | D270: Our direct read | E270: Gap vs ours | F270: As of
A271: City & State PA | B271: 0.72 | C271: Kalshi | D271: =Kalshi!E17 | E271: =IFERROR(B271-D271,"") | F271: not stated
A272: • The Republican candidate, Rep. Ryan Mackenzie, is never named anywhere on cityandstatepa.com's prediction-markets section (race page, candidates index, or candidate profile pages). The PA-07 'Party to Win' card labels his side simply 'Republican' with no photo.
A273: • Two different Brooks probabilities appear on the same race page and are inconsistent with each other: the race-level 'General Election · PARTY TO WIN' gauge shows Bob Brooks (D) 72% vs. generic Republican 28%; the 'Pennsylvania Congressional Candidates' card directly below it shows Bob Brooks 'MARKET ODDS' at 78%. The page does not explain the discrepancy (e.g., whether one reflects a party-control market and the other a candidate-specific market). market_odds.dem_prob/rep_prob above use the race-level 72/28 'Party to Win' figures; the 78% candidate-card figure is flagged here rather than silently discarded.
A274: • No 'as of' or last-updated timestamp is shown for the PA-07 odds specifically; only a generic sitewide claim of 30-minute refresh cadence.
A275: • No historical odds chart, sparkline, or time series is published for this race (or any race) on the site.
A276: • No PA-07-specific polling exists anywhere on the site. The dedicated /prediction-markets/polls page contains only Pennsylvania Governor race polls (Shapiro vs. Garrity); it has zero mentions of Brooks, Mackenzie, or PA-07.
A277: • No formal race rating/handicapping (e.g., Cook Political Report, Sabato's Crystal Ball, Inside Elections) is cited for PA-07 anywhere on the site.
A278: ⚠ The City & State prediction-markets section is labelled SPONSORED CONTENT — its publisher states editorial staff were not involved, and its calls to action are affiliate trading links. Nothing here is used as an input to any figure in this workbook; it is logged so the discrepancy is visible.

Sheet Campaign Finance
A1: Campaign Finance — PA-07 (FEC)
A2: Money raised and spent in the 2026 PA-07 race, from the OpenFEC API. This is finance, not polling. Compiled 2026-10-12 02:24 UTC.
A4: COVERAGE
A5: Figures current through | B5: 2026-06-30
A6: Retrieved | B6: 2026-08-30T16:22:43Z
A8: CANDIDATE TOTALS — 2026 cycle
A9: Candidate | B9: Party | C9: Receipts | D9: Disbursements | E9: Cash on Hand | F9: Individual | G9: PAC | H9: Filed? | I9: Through
A10: Bob Brooks | B10: DEM | C10: 2392215.2 | D10: 1373792.4 | E10: 1018422.8 | F10: 1942165.5 | G10: 403000.03 | H10: yes | I10: 2026-06-30
A11: Ryan Mackenzie | B11: REP | C11: 4357405.1 | D11: 1521927.9 | E11: 2938717.2 | F11: 1493241 | G11: 1042912.8 | H11: yes | I11: 2026-06-30
A12: Frank Golden | B12: UN | H12: never filed | I12: —
A13: Aiden Alexander Gonzalez | B13: DEM | H13: never filed | I13: —
A14: Michael Ramon Granados Jr. | B14: IND | H14: never filed | I14: —
A15: Lewis Shupe | B15: IND | H15: never filed | I15: —
A16: TOTAL | C16: =SUM(C10:C15) | D16: =SUM(D10:D15) | E16: =SUM(E10:E15) | F16: =SUM(F10:F15) | G16: =SUM(G10:G15)
A18: DERIVED
A19: Cash advantage: Bob Brooks (D) - Ryan Mackenzie (R) | B19: =IFERROR(INDEX($E$10:$E$15,MATCH("Bob Brooks",$A$10:$A$15,0))-INDEX($E$10:$E$15,MATCH("Ryan Mackenzie",$A$10:$A$15,0)),"") | D19: Negative means the Republican holds more cash.
A20: Combined receipts | B20: =SUM(C10:C15)
A21: Burn rate (disbursed / raised) | B21: =IFERROR(SUM(D10:D15)/SUM(C10:C15),"")
A23: INDEPENDENT EXPENDITURES
A24: Target | B24: Support / Oppose | C24: Amount | D24: Committee | E24: As of
A25: Bob Brooks | B25: Support | C25: 140300 | D25: CONGRESSIONAL PROGRESSIVE CAUCUS PAC | E25: 2026-06-30
A26: Bob Brooks | B26: Support | C26: 3556.19 | D26: WORKING FAMILIES PARTY PAC | E26: 2026-06-30
A27: Bob Brooks | B27: Support | C27: 157.07 | D27: RURAL FREEDOM NETWORK | E27: 2026-06-30
A28: Bob Brooks | B28: Support | C28: 4500 | D28: FF PAC | E28: 2026-06-30
A29: Bob Brooks | B29: Support | C29: 99625 | D29: MEDICARE FOR ALL | E29: 2026-06-30
A30: Bob Brooks | B30: Support | C30: 30559.95 | D30: MAKE THE ROAD ACTION POLITICAL COMMITTEE | E30: 2026-06-30
A31: Bob Brooks | B31: Support | C31: 9116.67 | D31: BLUE BATTLEGROUND PROJECT | E31: 2026-06-30
A32: Bob Brooks | B32: Support | C32: 187.51 | D32: SURJ PAC | E32: 2026-06-30
A33: Bob Brooks | B33: Support | C33: 50 | D33: THE PEOPLE UNITED PAC | E33: 2026-06-30
A34: Bob Brooks | B34: Support | C34: 36.54 | D34: GIVEGREEN UNITED ACTION | E34: 2026-06-30
A35: Bob Brooks | B35: Support | C35: 88321.5 | D35: DLP PAC | E35: 2026-06-30
A36: Bob Brooks | B36: Support | C36: 16643.34 | D36: BLUE MAJORITY PROJECT | E36: 2026-06-30
... A53: Bob Brooks | B53: Support | C53: 11000 | D53: SENIORS EMPOWERING AN EFFECTIVE DEMOCRACY (SEED-PAC) | E53: 2026-08-19
A54: TOTAL | C54: =SUM(C25:C53)
A56: Outside money is reported continuously rather than quarterly, so these figures are usually fresher than the candidate totals above — the two are not as-of the same date.
A58: READ THE MONEY WITH THESE TWO FACTS
A59: 1. TIMING. Candidate totals above come from the July Quarterly and are current only through 2026-06-30 — roughly two months stale on arrival, widening until the October Quarterly. Independent expenditures below report continuously and are FRESHER. The two halves of this sheet are not as-of the same date.
A60: 2. WHAT THE MONEY WAS FOR. Most of the outside spending logged here was spent in May 2026 inside the contested Democratic PRIMARY, not against Mackenzie in the general — so it is not evidence of general-election engagement. And a large share of Mackenzie's receipts is a transfer from a wound-down joint fundraising committee rather than fresh donor money, which inflates his receipts line relative to actual fundraising.
A62: • Coverage_through (2026-06-30) reflects the most recent PERIODIC financial report (FEC Form 3, 'JULY QUARTERLY 2026', filed 2026-07-15) for both major-party nominees' principal committees. As of retrieval (2026-08-30), that is roughly 2 months stale; the next scheduled disclosure is the OCTOBER QUARTERLY report (due on/around 2026-10-15, covering through 2026-09-30).
A63: • Both candidates have filed newer non-financial-summary documents since June 30, 2026 (e.g. Brooks filed a Statement of Organization amendment on 2026-08-20; both campaigns have filed periodic 48-Hour Notices of Contributions/Loans around the primary), but these do not update the aggregate receipts/disbursements/cash-on-hand totals shown here.
A64: • Bob Brooks (D) won a contested 5-candidate Democratic primary; the other Democratic primary candidates (Ryan Crosswell, Lamont McClure, Carol Obando-Derstine, Mark Pinsley) are not included as candidate entries above because they are not on the 2026 general-election ballot, but their FEC candidate IDs are C00907667/H6PA07162, C00898544/H6PA07147, C00903963/H6PA07154, and C00913947/H6PA07170 respectively, for reference.
A65: • Ryan Mackenzie (R) is the incumbent, having defeated then-Rep. Susan Wild (D) in 2024; Wild is not a 2026 candidate (FEC candidate_status = prior-cycle candidate, H8PA15229).
A66: • Independent-expenditure totals in 'independent_expenditures' come from OpenFEC's schedules/schedule_e/by_candidate aggregate (deduplicated, i.e. amendments/superseding filings already reconciled), queried for cycle=2026. A naive sum of raw itemized schedule_e line items for these two candidates totals roughly $5.9M, materially higher than the ~$2.76M deduplicated aggregate, because raw itemized records include amended/superseded filings; the deduplicated by_candidate totals are the ones used here.
A67: • Spot-checking the underlying itemized Schedule E records for the largest committees (e.g. STRONGER TOGETHER PA supporting Brooks, LEAD LEFT PAC opposing Brooks) shows expenditure dates clustered between 2026-05-06 and 2026-05-18 -- i.e. immediately before Pennsylvania's 2026 primary (inferred to be mid-May 2026 based on FEC 'PRE-PRIMARY 2026' reports covering periods ending 2026-04-29). This strongly suggests the great majority of the ~$2.76M in outside spending found here was primary-season spending (aimed at the multi-candidate Democratic primary), not general-election spending in the Brooks-vs-Mackenzie race. Post-primary (after 2026-05-19) itemized IE activity located for these two candidates was comparatively minor: a handful of small-dollar entries in June 2026 (e.g. Field Team 6 $638.30 and GiveGreen United Action $36.54 supporting Brooks; Planned Parenthood Votes $85.38 opposing Mackenzie) plus one larger, more recent item: an $11,000 pro-Brooks independent expenditure by Seniors Empowering an Effective Democracy (SEED-PAC), reported via a 24-hour notice filed 2026-08-19 (not yet reflected in the by_candidate aggregate; listed separately in independent_expenditures).
A68: • No independent expenditures supporting Ryan Mackenzie were found in FEC records as of retrieval; all $12,352.62 in IE activity referencing him was in opposition (mostly small-dollar and primary-period).
A69: • No independent expenditure activity was found for the four no-fundraising minor/independent candidates (Golden, Gonzalez, Granados, Shupe).
A70: Extraction problems: Precise dollar split of independent-expenditure spending between the primary period and the general-election period could not be computed exhaustively (would require reconciling all itemized Schedule E records, including amendments, against exact PA primary election-day boundaries); the primary-vs-general characterization above is based on spot-checking the top committees' itemized records, not a full reconciliation.; OpenFEC's schedules/schedule_e/by_candidate aggregate had not yet incorporated the 2026-08-19 SEED-PAC $11,000 pro-Brooks 24-hour notice at the time of retrieval; it was added to independent_expenditures manually from the itemized schedule_e record rather than the aggregate endpoint.; No FEC financial totals exist for declared candidates Frank Golden, Aiden Alexander Gonzalez, Michael Ramon Granados Jr., and Lewis Shupe (empty results from /candidate/{id}/totals/); their financial fields are null rather than 0, since 'no report filed' is not the same as a confirmed zero.

Sheet Venue Comparison
A1: Venue Comparison — Polymarket vs Kalshi
A2: Daily Democratic win probability on both venues, joined on date with INDEX/MATCH so the join survives a data refresh. Built 2026-10-12 02:24 UTC.
A4: DIVERGENCE SUMMARY
A5: Current Polymarket Dem (mid) | B5: =Polymarket!D19
A6: Current Kalshi Dem (mid) | B6: =Kalshi!E17
A7: Current divergence (PM − Kalshi) | B7: =B5-B6
A8: Mean absolute divergence (overlap) | B8: =IFERROR(AVERAGE(E15:E293),"")
A9: Max absolute divergence | B9: =IFERROR(MAX(E15:E293),"")
A10: Overlapping days | B10: =COUNT(D15:D293)
A11: Days listed but not comparable | B11: =COUNT(A15:A293)-COUNT(D15:D293)
A13: DAILY SERIES
A14: Date | B14: Polymarket Dem | C14: Kalshi Dem (mid) | D14: Divergence (PM − K) | E14: Abs Divergence | F14: Polymarket Rep | G14: Kalshi Rep (mid) | H14: Cheapest Dem | I14: Cheapest Rep | J14: Pair Total | K14: Even odds | L14: Axis label
A15: 46008 | B15: =IFERROR(IF(INDEX(Polymarket!$B$25:$B$303,MATCH($A15,Polymarket!$A$25:$A$303,0))=0,"",INDEX(Polymarket!$B$25:$B$303,MATCH($A15,Polymarket!$A$25:$A$303,0))),"") | C15: =IFERROR(IF(INDEX(Kalshi!$D$31:$D$485,MATCH($A15,Kalshi!$A$31:$A$485,0))=0,"",INDEX(Kalshi!$D$31:$D$485,MATCH($A15,Kalshi!$A$31:$A$485,0))),"") | D15: =IF(AND(ISNUMBER(B15),ISNUMBER(C15)),B15-C15,"") | E15: =IF(ISNUMBER(D15),ABS(D15),"") | F15: =IFERROR(IF(INDEX(Polymarket!$C$25:$C$303,MATCH($A15,Polymarket!$A$25:$A$303,0))=0,"",INDEX(Polymarket!$C$25:$C$303,MATCH($A15,Polymarket!$A$25:$A$303,0))),"") | G15: =IFERROR(IF(INDEX(Kalshi!$G$31:$G$485,MATCH($A15,Kalshi!$A$31:$A$485,0))=0,"",INDEX(Kalshi!$G$31:$G$485,MATCH($A15,Kalshi!$A$31:$A$485,0))),"") | H15: =IF(AND(ISNUMBER(B15),ISNUMBER(C15)),MIN(B15,C15),"") | I15: =IF(AND(ISNUMBER(F15),ISNUMBER(G15)),MIN(F15,G15),"") | J15: =IF(AND(ISNUMBER(H15),ISNUMBER(I15)),H15+I15,"") | K15: 0.5 | L15: 17 Dec
A16: 46009 | B16: =IFERROR(IF(INDEX(Polymarket!$B$25:$B$303,MATCH($A16,Polymarket!$A$25:$A$303,0))=0,"",INDEX(Polymarket!$B$25:$B$303,MATCH($A16,Polymarket!$A$25:$A$303,0))),"") | C16: =IFERROR(IF(INDEX(Kalshi!$D$31:$D$485,MATCH($A16,Kalshi!$A$31:$A$485,0))=0,"",INDEX(Kalshi!$D$31:$D$485,MATCH($A16,Kalshi!$A$31:$A$485,0))),"") | D16: =IF(AND(ISNUMBER(B16),ISNUMBER(C16)),B16-C16,"") | E16: =IF(ISNUMBER(D16),ABS(D16),"") | F16: =IFERROR(IF(INDEX(Polymarket!$C$25:$C$303,MATCH($A16,Polymarket!$A$25:$A$303,0))=0,"",INDEX(Polymarket!$C$25:$C$303,MATCH($A16,Polymarket!$A$25:$A$303,0))),"") | G16: =IFERROR(IF(INDEX(Kalshi!$G$31:$G$485,MATCH($A16,Kalshi!$A$31:$A$485,0))=0,"",INDEX(Kalshi!$G$31:$G$485,MATCH($A16,Kalshi!$A$31:$A$485,0))),"") | H16: =IF(AND(ISNUMBER(B16),ISNUMBER(C16)),MIN(B16,C16),"") | I16: =IF(AND(ISNUMBER(F16),ISNUMBER(G16)),MIN(F16,G16),"") | J16: =IF(AND(ISNUMBER(H16),ISNUMBER(I16)),H16+I16,"") | K16: 0.5 | L16: 18 Dec
A17: 46010 | B17: =IFERROR(IF(INDEX(Polymarket!$B$25:$B$303,MATCH($A17,Polymarket!$A$25:$A$303,0))=0,"",INDEX(Polymarket!$B$25:$B$303,MATCH($A17,Polymarket!$A$25:$A$303,0))),"") | C17: =IFERROR(IF(INDEX(Kalshi!$D$31:$D$485,MATCH($A17,Kalshi!$A$31:$A$485,0))=0,"",INDEX(Kalshi!$D$31:$D$485,MATCH($A17,Kalshi!$A$31:$A$485,0))),"") | D17: =IF(AND(ISNUMBER(B17),ISNUMBER(C17)),B17-C17,"") | E17: =IF(ISNUMBER(D17),ABS(D17),"") | F17: =IFERROR(IF(INDEX(Polymarket!$C$25:$C$303,MATCH($A17,Polymarket!$A$25:$A$303,0))=0,"",INDEX(Polymarket!$C$25:$C$303,MATCH($A17,Polymarket!$A$25:$A$303,0))),"") | G17: =IFERROR(IF(INDEX(Kalshi!$G$31:$G$485,MATCH($A17,Kalshi!$A$31:$A$485,0))=0,"",INDEX(Kalshi!$G$31:$G$485,MATCH($A17,Kalshi!$A$31:$A$485,0))),"") | H17: =IF(AND(ISNUMBER(B17),ISNUMBER(C17)),MIN(B17,C17),"") | I17: =IF(AND(ISNUMBER(F17),ISNUMBER(G17)),MIN(F17,G17),"") | J17: =IF(AND(ISNUMBER(H17),ISNUMBER(I17)),H17+I17,"") | K17: 0.5 | L17: 19 Dec
A18: 46011 | B18: =IFERROR(IF(INDEX(Polymarket!$B$25:$B$303,MATCH($A18,Polymarket!$A$25:$A$303,0))=0,"",INDEX(Polymarket!$B$25:$B$303,MATCH($A18,Polymarket!$A$25:$A$303,0))),"") | C18: =IFERROR(IF(INDEX(Kalshi!$D$31:$D$485,MATCH($A18,Kalshi!$A$31:$A$485,0))=0,"",INDEX(Kalshi!$D$31:$D$485,MATCH($A18,Kalshi!$A$31:$A$485,0))),"") | D18: =IF(AND(ISNUMBER(B18),ISNUMBER(C18)),B18-C18,"") | E18: =IF(ISNUMBER(D18),ABS(D18),"") | F18: =IFERROR(IF(INDEX(Polymarket!$C$25:$C$303,MATCH($A18,Polymarket!$A$25:$A$303,0))=0,"",INDEX(Polymarket!$C$25:$C$303,MATCH($A18,Polymarket!$A$25:$A$303,0))),"") | G18: =IFERROR(IF(INDEX(Kalshi!$G$31:$G$485,MATCH($A18,Kalshi!$A$31:$A$485,0))=0,"",INDEX(Kalshi!$G$31:$G$485,MATCH($A18,Kalshi!$A$31:$A$485,0))),"") | H18: =IF(AND(ISNUMBER(B18),ISNUMBER(C18)),MIN(B18,C18),"") | I18: =IF(AND(ISNUMBER(F18),ISNUMBER(G18)),MIN(F18,G18),"") | J18: =IF(AND(ISNUMBER(H18),ISNUMBER(I18)),H18+I18,"") | K18: 0.5 | L18: 20 Dec
A19: 46012 | B19: =IFERROR(IF(INDEX(Polymarket!$B$25:$B$303,MATCH($A19,Polymarket!$A$25:$A$303,0))=0,"",INDEX(Polymarket!$B$25:$B$303,MATCH($A19,Polymarket!$A$25:$A$303,0))),"") | C19: =IFERROR(IF(INDEX(Kalshi!$D$31:$D$485,MATCH($A19,Kalshi!$A$31:$A$485,0))=0,"",INDEX(Kalshi!$D$31:$D$485,MATCH($A19,Kalshi!$A$31:$A$485,0))),"") | D19: =IF(AND(ISNUMBER(B19),ISNUMBER(C19)),B19-C19,"") | E19: =IF(ISNUMBER(D19),ABS(D19),"") | F19: =IFERROR(IF(INDEX(Polymarket!$C$25:$C$303,MATCH($A19,Polymarket!$A$25:$A$303,0))=0,"",INDEX(Polymarket!$C$25:$C$303,MATCH($A19,Polymarket!$A$25:$A$303,0))),"") | G19: =IFERROR(IF(INDEX(Kalshi!$G$31:$G$485,MATCH($A19,Kalshi!$A$31:$A$485,0))=0,"",INDEX(Kalshi!$G$31:$G$485,MATCH($A19,Kalshi!$A$31:$A$485,0))),"") | H19: =IF(AND(ISNUMBER(B19),ISNUMBER(C19)),MIN(B19,C19),"") | I19: =IF(AND(ISNUMBER(F19),ISNUMBER(G19)),MIN(F19,G19),"") | J19: =IF(AND(ISNUMBER(H19),ISNUMBER(I19)),H19+I19,"") | K19: 0.5 | L19: 21 Dec
A20: 46013 | B20: =IFERROR(IF(INDEX(Polymarket!$B$25:$B$303,MATCH($A20,Polymarket!$A$25:$A$303,0))=0,"",INDEX(Polymarket!$B$25:$B$303,MATCH($A20,Polymarket!$A$25:$A$303,0))),"") | C20: =IFERROR(IF(INDEX(Kalshi!$D$31:$D$485,MATCH($A20,Kalshi!$A$31:$A$485,0))=0,"",INDEX(Kalshi!$D$31:$D$485,MATCH($A20,Kalshi!$A$31:$A$485,0))),"") | D20: =IF(AND(ISNUMBER(B20),ISNUMBER(C20)),B20-C20,"") | E20: =IF(ISNUMBER(D20),ABS(D20),"") | F20: =IFERROR(IF(INDEX(Polymarket!$C$25:$C$303,MATCH($A20,Polymarket!$A$25:$A$303,0))=0,"",INDEX(Polymarket!$C$25:$C$303,MATCH($A20,Polymarket!$A$25:$A$303,0))),"") | G20: =IFERROR(IF(INDEX(Kalshi!$G$31:$G$485,MATCH($A20,Kalshi!$A$31:$A$485,0))=0,"",INDEX(Kalshi!$G$31:$G$485,MATCH($A20,Kalshi!$A$31:$A$485,0))),"") | H20: =IF(AND(ISNUMBER(B20),ISNUMBER(C20)),MIN(B20,C20),"") | I20: =IF(AND(ISNUMBER(F20),ISNUMBER(G20)),MIN(F20,G20),"") | J20: =IF(AND(ISNUMBER(H20),ISNUMBER(I20)),H20+I20,"") | K20: 0.5 | L20: 22 Dec
A21: 46014 | B21: =IFERROR(IF(INDEX(Polymarket!$B$25:$B$303,MATCH($A21,Polymarket!$A$25:$A$303,0))=0,"",INDEX(Polymarket!$B$25:$B$303,MATCH($A21,Polymarket!$A$25:$A$303,0))),"") | C21: =IFERROR(IF(INDEX(Kalshi!$D$31:$D$485,MATCH($A21,Kalshi!$A$31:$A$485,0))=0,"",INDEX(Kalshi!$D$31:$D$485,MATCH($A21,Kalshi!$A$31:$A$485,0))),"") | D21: =IF(AND(ISNUMBER(B21),ISNUMBER(C21)),B21-C21,"") | E21: =IF(ISNUMBER(D21),ABS(D21),"") | F21: =IFERROR(IF(INDEX(Polymarket!$C$25:$C$303,MATCH($A21,Polymarket!$A$25:$A$303,0))=0,"",INDEX(Polymarket!$C$25:$C$303,MATCH($A21,Polymarket!$A$25:$A$303,0))),"") | G21: =IFERROR(IF(INDEX(Kalshi!$G$31:$G$485,MATCH($A21,Kalshi!$A$31:$A$485,0))=0,"",INDEX(Kalshi!$G$31:$G$485,MATCH($A21,Kalshi!$A$31:$A$485,0))),"") | H21: =IF(AND(ISNUMBER(B21),ISNUMBER(C21)),MIN(B21,C21),"") | I21: =IF(AND(ISNUMBER(F21),ISNUMBER(G21)),MIN(F21,G21),"") | J21: =IF(AND(ISNUMBER(H21),ISNUMBER(I21)),H21+I21,"") | K21: 0.5 | L21: 23 Dec
A22: 46015 | B22: =IFERROR(IF(INDEX(Polymarket!$B$25:$B$303,MATCH($A22,Polymarket!$A$25:$A$303,0))=0,"",INDEX(Polymarket!$B$25:$B$303,MATCH($A22,Polymarket!$A$25:$A$303,0))),"") | C22: =IFERROR(IF(INDEX(Kalshi!$D$31:$D$485,MATCH($A22,Kalshi!$A$31:$A$485,0))=0,"",INDEX(Kalshi!$D$31:$D$485,MATCH($A22,Kalshi!$A$31:$A$485,0))),"") | D22: =IF(AND(ISNUMBER(B22),ISNUMBER(C22)),B22-C22,"") | E22: =IF(ISNUMBER(D22),ABS(D22),"") | F22: =IFERROR(IF(INDEX(Polymarket!$C$25:$C$303,MATCH($A22,Polymarket!$A$25:$A$303,0))=0,"",INDEX(Polymarket!$C$25:$C$303,MATCH($A22,Polymarket!$A$25:$A$303,0))),"") | G22: =IFERROR(IF(INDEX(Kalshi!$G$31:$G$485,MATCH($A22,Kalshi!$A$31:$A$485,0))=0,"",INDEX(Kalshi!$G$31:$G$485,MATCH($A22,Kalshi!$A$31:$A$485,0))),"") | H22: =IF(AND(ISNUMBER(B22),ISNUMBER(C22)),MIN(B22,C22),"") | I22: =IF(AND(ISNUMBER(F22),ISNUMBER(G22)),MIN(F22,G22),"") | J22: =IF(AND(ISNUMBER(H22),ISNUMBER(I22)),H22+I22,"") | K22: 0.5 | L22: 24 Dec
A23: 46016 | B23: =IFERROR(IF(INDEX(Polymarket!$B$25:$B$303,MATCH($A23,Polymarket!$A$25:$A$303,0))=0,"",INDEX(Polymarket!$B$25:$B$303,MATCH($A23,Polymarket!$A$25:$A$303,0))),"") | C23: =IFERROR(IF(INDEX(Kalshi!$D$31:$D$485,MATCH($A23,Kalshi!$A$31:$A$485,0))=0,"",INDEX(Kalshi!$D$31:$D$485,MATCH($A23,Kalshi!$A$31:$A$485,0))),"") | D23: =IF(AND(ISNUMBER(B23),ISNUMBER(C23)),B23-C23,"") | E23: =IF(ISNUMBER(D23),ABS(D23),"") | F23: =IFERROR(IF(INDEX(Polymarket!$C$25:$C$303,MATCH($A23,Polymarket!$A$25:$A$303,0))=0,"",INDEX(Polymarket!$C$25:$C$303,MATCH($A23,Polymarket!$A$25:$A$303,0))),"") | G23: =IFERROR(IF(INDEX(Kalshi!$G$31:$G$485,MATCH($A23,Kalshi!$A$31:$A$485,0))=0,"",INDEX(Kalshi!$G$31:$G$485,MATCH($A23,Kalshi!$A$31:$A$485,0))),"") | H23: =IF(AND(ISNUMBER(B23),ISNUMBER(C23)),MIN(B23,C23),"") | I23: =IF(AND(ISNUMBER(F23),ISNUMBER(G23)),MIN(F23,G23),"") | J23: =IF(AND(ISNUMBER(H23),ISNUMBER(I23)),H23+I23,"") | K23: 0.5 | L23: 25 Dec
A24: 46017 | B24: =IFERROR(IF(INDEX(Polymarket!$B$25:$B$303,MATCH($A24,Polymarket!$A$25:$A$303,0))=0,"",INDEX(Polymarket!$B$25:$B$303,MATCH($A24,Polymarket!$A$25:$A$303,0))),"") | C24: =IFERROR(IF(INDEX(Kalshi!$D$31:$D$485,MATCH($A24,Kalshi!$A$31:$A$485,0))=0,"",INDEX(Kalshi!$D$31:$D$485,MATCH($A24,Kalshi!$A$31:$A$485,0))),"") | D24: =IF(AND(ISNUMBER(B24),ISNUMBER(C24)),B24-C24,"") | E24: =IF(ISNUMBER(D24),ABS(D24),"") | F24: =IFERROR(IF(INDEX(Polymarket!$C$25:$C$303,MATCH($A24,Polymarket!$A$25:$A$303,0))=0,"",INDEX(Polymarket!$C$25:$C$303,MATCH($A24,Polymarket!$A$25:$A$303,0))),"") | G24: =IFERROR(IF(INDEX(Kalshi!$G$31:$G$485,MATCH($A24,Kalshi!$A$31:$A$485,0))=0,"",INDEX(Kalshi!$G$31:$G$485,MATCH($A24,Kalshi!$A$31:$A$485,0))),"") | H24: =IF(AND(ISNUMBER(B24),ISNUMBER(C24)),MIN(B24,C24),"") | I24: =IF(AND(ISNUMBER(F24),ISNUMBER(G24)),MIN(F24,G24),"") | J24: =IF(AND(ISNUMBER(H24),ISNUMBER(I24)),H24+I24,"") | K24: 0.5 | L24: 26 Dec
A25: 46018 | B25: =IFERROR(IF(INDEX(Polymarket!$B$25:$B$303,MATCH($A25,Polymarket!$A$25:$A$303,0))=0,"",INDEX(Polymarket!$B$25:$B$303,MATCH($A25,Polymarket!$A$25:$A$303,0))),"") | C25: =IFERROR(IF(INDEX(Kalshi!$D$31:$D$485,MATCH($A25,Kalshi!$A$31:$A$485,0))=0,"",INDEX(Kalshi!$D$31:$D$485,MATCH($A25,Kalshi!$A$31:$A$485,0))),"") | D25: =IF(AND(ISNUMBER(B25),ISNUMBER(C25)),B25-C25,"") | E25: =IF(ISNUMBER(D25),ABS(D25),"") | F25: =IFERROR(IF(INDEX(Polymarket!$C$25:$C$303,MATCH($A25,Polymarket!$A$25:$A$303,0))=0,"",INDEX(Polymarket!$C$25:$C$303,MATCH($A25,Polymarket!$A$25:$A$303,0))),"") | G25: =IFERROR(IF(INDEX(Kalshi!$G$31:$G$485,MATCH($A25,Kalshi!$A$31:$A$485,0))=0,"",INDEX(Kalshi!$G$31:$G$485,MATCH($A25,Kalshi!$A$31:$A$485,0))),"") | H25: =IF(AND(ISNUMBER(B25),ISNUMBER(C25)),MIN(B25,C25),"") | I25: =IF(AND(ISNUMBER(F25),ISNUMBER(G25)),MIN(F25,G25),"") | J25: =IF(AND(ISNUMBER(H25),ISNUMBER(I25)),H25+I25,"") | K25: 0.5 | L25: 27 Dec
A26: 46019 | B26: =IFERROR(IF(INDEX(Polymarket!$B$25:$B$303,MATCH($A26,Polymarket!$A$25:$A$303,0))=0,"",INDEX(Polymarket!$B$25:$B$303,MATCH($A26,Polymarket!$A$25:$A$303,0))),"") | C26: =IFERROR(IF(INDEX(Kalshi!$D$31:$D$485,MATCH($A26,Kalshi!$A$31:$A$485,0))=0,"",INDEX(Kalshi!$D$31:$D$485,MATCH($A26,Kalshi!$A$31:$A$485,0))),"") | D26: =IF(AND(ISNUMBER(B26),ISNUMBER(C26)),B26-C26,"") | E26: =IF(ISNUMBER(D26),ABS(D26),"") | F26: =IFERROR(IF(INDEX(Polymarket!$C$25:$C$303,MATCH($A26,Polymarket!$A$25:$A$303,0))=0,"",INDEX(Polymarket!$C$25:$C$303,MATCH($A26,Polymarket!$A$25:$A$303,0))),"") | G26: =IFERROR(IF(INDEX(Kalshi!$G$31:$G$485,MATCH($A26,Kalshi!$A$31:$A$485,0))=0,"",INDEX(Kalshi!$G$31:$G$485,MATCH($A26,Kalshi!$A$31:$A$485,0))),"") | H26: =IF(AND(ISNUMBER(B26),ISNUMBER(C26)),MIN(B26,C26),"") | I26: =IF(AND(ISNUMBER(F26),ISNUMBER(G26)),MIN(F26,G26),"") | J26: =IF(AND(ISNUMBER(H26),ISNUMBER(I26)),H26+I26,"") | K26: 0.5 | L26: 28 Dec
... A293: 46307 | B293: =IFERROR(IF(INDEX(Polymarket!$B$25:$B$303,MATCH($A293,Polymarket!$A$25:$A$303,0))=0,"",INDEX(Polymarket!$B$25:$B$303,MATCH($A293,Polymarket!$A$25:$A$303,0))),"") | C293: =IFERROR(IF(INDEX(Kalshi!$D$31:$D$485,MATCH($A293,Kalshi!$A$31:$A$485,0))=0,"",INDEX(Kalshi!$D$31:$D$485,MATCH($A293,Kalshi!$A$31:$A$485,0))),"") | D293: =IF(AND(ISNUMBER(B293),ISNUMBER(C293)),B293-C293,"") | E293: =IF(ISNUMBER(D293),ABS(D293),"") | F293: =IFERROR(IF(INDEX(Polymarket!$C$25:$C$303,MATCH($A293,Polymarket!$A$25:$A$303,0))=0,"",INDEX(Polymarket!$C$25:$C$303,MATCH($A293,Polymarket!$A$25:$A$303,0))),"") | G293: =IFERROR(IF(INDEX(Kalshi!$G$31:$G$485,MATCH($A293,Kalshi!$A$31:$A$485,0))=0,"",INDEX(Kalshi!$G$31:$G$485,MATCH($A293,Kalshi!$A$31:$A$485,0))),"") | H293: =IF(AND(ISNUMBER(B293),ISNUMBER(C293)),MIN(B293,C293),"") | I293: =IF(AND(ISNUMBER(F293),ISNUMBER(G293)),MIN(F293,G293),"") | J293: =IF(AND(ISNUMBER(H293),ISNUMBER(I293)),H293+I293,"") | K293: 0.5 | L293: 12 Oct

Sheet Notes & Sources
A1: Notes, Sources & Refresh
A2: Everything behind the numbers: where each cell came from, what is assumed, and how to pull it again. Built 2026-10-12 02:24 UTC.
A4: COLOUR CONVENTION
A5: Blue text | B5: A hardcoded value - pulled from an API, read out of house.csv, or typed in from a cited source. These are the only cells you overwrite when refreshing.
A6: Black text | B6: A formula. Do not overwrite; it recalculates from the blue and green cells.
A7: Green text | B7: A link to another sheet in this workbook.
A8: Yellow fill | B8: Either a key output worth reading first, or an assumption you are meant to change.
A10: SHEETS
A11: Summary | B11: Dashboard. Consensus probability, market-implied margin, race facts, live snapshot, every subject tracked, cross-venue arbitrage check, momentum, and markets-vs-polls.
A12: Polymarket | B12: Winner market: metadata, live order book, and 233 days of daily prices for the Democratic and Republican YES contracts.
A13: Kalshi | B13: Winner market: metadata, live order book with five levels of depth, and 410 days of daily candlesticks.
A14: Margin of Victory | B14: Polymarket's ten-bracket ladder on the winning margin, with the implied distribution, expected margin, and a cross-check against the winner market.
A15: PA Seat Count | B15: Kalshi's ladder on how many of Pennsylvania's 17 House seats Democrats win. PA-07 is one of them, so it is a state-level read on the same question.
A16: Polls | B16: General-election and Democratic-primary polling from house.csv, a recency-weighted average, the district and incumbent profile from GovTrack, and supplementary approval numbers.
A17: Venue Comparison | B17: The two venues' daily Democratic probability joined on date, with divergence and an indicative historical pair-cost column.
A19: SUBJECT INVENTORY - what each venue actually lists for PA-07
A20: Winner (party) | B20: Polymarket 'PA-07 House Election Winner' (event 106187) and Kalshi HOUSEPA7-26. Both venues, both liquid. This is the workbook's spine.
A21: Margin of victory | B21: BOTH venues. Polymarket 'PA-07 House Election Margin of Victory' (event 834502), ten exclusive brackets. Kalshi KXMIDTERMMOV-PA07D and -PA07R, eight threshold rungs ('Democrats, 3+ pts'). CORRECTION: an earlier version of this workbook said Kalshi had no PA-07 margin market. That was wrong - the search behind it matched series tickers, and Kalshi files these under a national series (KXMIDTERMMOV) with per-district EVENT tickers, so a series-level search cannot find them.
A22: Voter turnout | B22: Kalshi KXMIDTERMVOTETURN-PA07, five thresholds from 310K to 370K. Kalshi-only; Polymarket lists no turnout market for this district. PA-07 was decided by about a point in 2024, so turnout is a plausible decider rather than trivia.
A23: Threshold vs bracket | B23: The two venues sell different instruments for the same question. Polymarket sells mutually exclusive brackets that sum to 100%. Kalshi sells nested thresholds, where each rung is P(value >= strike) and probabilities must FALL as the strike rises. Differencing adjacent Kalshi rungs recovers buckets; collect3.py checks the monotonicity that makes that valid.
A24: Democratic nominee | B24: Kalshi KXPA07D-26 and Polymarket 'PA-07 Democratic Primary Winner' (event 287013). Settled on 19 May 2026; the Kalshi event returns no tradeable markets now. Kept as polling calibration on the Polls sheet, not tracked live.
A25: 2024 PA-07 race | B25: Kalshi HOUSEPA7-24 exists as an event but returns no markets. Not tracked.
A26: Closest House race | B26: Kalshi KXCLOSESTHOUSE-27JAN03 lists 34 districts for 2026. PA-01 is included; PA-07 is NOT, so there is nothing to track here.
A27: PA Democratic seat count | B27: Kalshi KXHOUSEWINSTATE-PAD, eight brackets. Tracked on its own sheet as state-level context.
A28: Placeholder outcomes | B28: The Polymarket winner event also carries outcomes A-E and 'Other', and the margin event carries 'Person A', 'Person B' and 'Other'. All are inactive with zero volume and are excluded.
A30: MARKET IDENTIFIERS
A31: Polymarket winner | B31: event 106187, slug pa-07-house-election-winner; markets will-the-democratic-party-win-the-pa-07-house-seat / will-the-republican-party-win-the-pa-07-house-seat
A32: Polymarket margin | B32: event 834502, slug pa-07-house-margin-of-victory-2026
A33: Kalshi winner | B33: series HOUSEPA7, event HOUSEPA7-26, markets HOUSEPA7-26-D (Bob Brooks) and HOUSEPA7-26-R (Ryan Mackenzie)
A34: Kalshi seat count | B34: series KXHOUSEWINSTATE, event KXHOUSEWINSTATE-PAD, markets -B7, -E7 through -E12, -A12
A35: Kalshi margin | B35: series KXMIDTERMMOV, events KXMIDTERMMOV-PA07D (rungs P3/P6/P9/P12/P15) and -PA07R (P3/P6/P9)
A36: Kalshi turnout | B36: series KXMIDTERMVOTETURN, event KXMIDTERMVOTETURN-PA07, markets -310000/-320000/-340000/-360000/-370000
A37: Kalshi close time | B37: HOUSEPA7-26 closes 2027-11-03, a year after the election - a settlement backstop, not the election date. Days-to-election counts to 2026-11-03.
A39: API CALLS BEHIND THE BLUE CELLS
A40: Polymarket metadata | B40: GET https://gamma-api.polymarket.com/events/<event_id>
A41: Polymarket book | B41: GET https://clob.polymarket.com/book?token_id=<token>
A42: Polymarket history | B42: GET https://clob.polymarket.com/prices-history?market=<token>&interval=max&fidelity=1440
A43: fidelity | B43: In minutes; 1440 gives one point per day. Returns {history: [{t: unix_seconds, p: price}]}.
A44: Dem winner token | B44: 37713776886536763857380242322222367371582682723176215910322979366716585040762
A45: Rep winner token | B45: 56412855186822728853119072474894085602768054645914780515455268260878947887549
A46: Kalshi base | B46: https://api.elections.kalshi.com
A47: Kalshi auth | B47: Every request signed with RSA-PSS / SHA-256 over (timestamp_ms + method + path), sent as KALSHI-ACCESS-KEY, KALSHI-ACCESS-SIGNATURE and KALSHI-ACCESS-TIMESTAMP headers. Salt length = digest length.
A48: Kalshi market | B48: GET /trade-api/v2/markets/<ticker>
A49: Kalshi book | B49: GET /trade-api/v2/markets/<ticker>/orderbook?depth=10
A50: Kalshi history | B50: GET /trade-api/v2/series/<series>/markets/<ticker>/candlesticks?start_ts=&end_ts=&period_interval=1440
A51: Kalshi discovery | B51: GET /trade-api/v2/series then filter locally - there is no keyword search endpoint, and /trade-api/v2/search/series returns 404.
A52: discovery caveat | B52: Filtering SERIES by ticker or title misses any market filed under a national series with per-district events - which is how margin and turnout are filed. Enumerate /trade-api/v2/events per candidate series and match on the EVENT ticker. Beware word-boundary regexes too: PA-?0?7\b does not match 'PA07D', which is exactly how the margin market was missed the first time.
A54: POLLING SOURCE - house.csv
A55: File | B55: /Users/charlieweinstein/Downloads/house.csv - the NYT / 538 house-poll file, 5,041 rows covering every 2026 House race.
A56: Filter | B56: state = PA and seat_number = 7, which yields 26 rows across 5 distinct poll_ids: 1 general-election poll and 4 Democratic-primary polls.
A57: Shape | B57: The file is one row per candidate per question, so rows were pivoted by poll_id into one row per poll.
A58: General poll | B58: GBAO for House Majority PAC, 29 June - 2 July 2026, likely voters, Brooks 47 - Mackenzie 43. Marked partisan = DEM in the file.
A59: Primary polls | B59: Change Research (Dec 2025), GBAO/CPC PAC (Feb-Mar and Apr 2026), Tavern Research (May 2026). All four understated Brooks, who took ~41.4%; each poll carried 31-53% undecided.
A60: Empty fields | B60: numeric_grade, pollscore, transparency_score and MoE are empty for every PA-07 poll in the file, so no pollster-quality weighting is applied. sample_size is also empty for the general poll - see the assumption below.
A61: Coverage caveat | B61: One public general-election poll exists for this race, and it is Democratic-sponsored. The polling average is a single data point wearing a weighting scheme; the market sheets are far better populated.
A63: GOVTRACK
A64: Page | B64: govtrack.us/congress/members/PA/7 and the member profile at govtrack.us/congress/members/ryan_mackenzie/457017
A65: Used for | B65: The district and incumbent profile on the Polls sheet: tenure, age, caucus, committee assignments, sponsorship mix and the missed-votes record.
A66: Missed votes | B66: 13 of 645 roll calls between Jan 2025 and Jul 2026 (2.0%), which GovTrack calls on par with the 2.0% median among sitting representatives.
A67: Access note | B67: The page rejects a plain fetch with HTTP 403; it was retrieved with a normal browser user-agent.
A68: Redistricting caveat | B68: GovTrack warns that some states are changing districts for 2026 and that its map reflects the 2024 lines. Confirm PA-07's boundaries before treating district-level history as like-for-like.
A70: METHOD NOTES
A71: Price as probability | B71: A contract paying $1 if the outcome happens trades at its implied probability, so $0.755 reads as 75.5%. Every price column is percent-formatted for that reason.
A72: Mid price | B72: (best bid + best ask) / 2. Used rather than last trade, which on thin markets can be stale by days.
A73: Kalshi YES ask | B73: Kalshi's REST market object returned null for yes_bid, yes_ask, volume and open_interest on these markets, so top-of-book comes from the orderbook endpoint. A YES ask is derived as 1 minus the best NO bid, since buying YES at p and selling NO at 1-p are the same trade.
A74: Normalised probability | B74: Each outcome's mid divided by the sum of mids across the group, which strips out the overround so the set sums to 100%.
A75: Overround / vig | B75: Sum of mids minus 1. On the margin ladder this runs far above 100% because several thin brackets are quoted with very wide spreads, which inflates their mid - read the normalised column, not the raw one.
A76: Expected margin | B76: Sum of (normalised probability x signed bracket midpoint) across the ladder, in percentage points, positive for a Democratic win.
A77: Kalshi volume column | B77: The winner history sums Democratic and Republican contract volume; open interest takes the larger of the two legs rather than the sum, since they are two sides of one race.
A78: Date alignment | B78: All dates are UTC days. Venue Comparison joins with INDEX/MATCH on the date value, so the join survives a refresh that changes row counts.
A79: Missing cells | B79: Some early Kalshi days have no closing bid or ask. Those cells are left blank and every dependent formula is guarded, so gaps propagate as blanks rather than as zeros or errors.
A81: ASSUMPTIONS - values not taken from any source
A82: Margin bracket midpoints | B82: Margin of Victory, column B. Closed brackets use their true centre (0-3% -> 1.5). The open-ended ones are judgement calls: 'Democrat 18%+' = +20.0, 'Republican 6%+' = -8.0. They drive the expected-margin figure.
A83: Seat bracket midpoints | B83: PA Seat Count, column B. Exact brackets use their own number; 'Below 7' = 6 and 'Above 12' = 13.
A84: Seat ladder mid fallback | B84: 'Below 7' and 'Above 12' have an ask but no resting bid, so their mid falls back to half the ask. Both quote at 1-2c, so this barely moves the expected-seats figure.
A85: Current PA Democratic seats | B85: 8, entered by hand on the PA Seat Count sheet as the baseline for the net-gain line. Verify against the current delegation before relying on it.
A86: General poll sample size | B86: 550 likely voters, used because the sample_size field is empty in house.csv; it is the figure Pollsmax reports for the same GBAO survey. Sample size only affects weighting, and with one poll in the log it changes nothing.
A87: Poll recency half-life | B87: 45 days. A poll's weight halves every 45 days - a reasonable default for a race still ten weeks out, not a fitted value.
A88: Partisan house-effect haircut | B88: 3.0 pp, subtracted from the weighted margin in proportion to net partisan sponsorship. This matters here: the only general-election poll is Democratic-sponsored, so the adjusted margin is the more conservative read.
A89: Consensus weighting | B89: Equal weight between the two venues on the winner market. Polymarket carries materially more volume, so a liquidity weighting would tilt toward it.
A91: OUTSIDE SOURCES ADDED 30 AUG 2026
A92: PollsMax | B92: pollsmax.com/2026-us-house/pennsylvania-7/ — swept with Playwright, since the content is client-side rendered and a plain fetch returns almost nothing. Supplies a statistical forecast (win probability, projected vote share, 231 daily trend points with simulation bands) and a documented methodology. Its polling average rests on the SAME single GBAO poll already in house.csv, so it adds no new polling — its value is the model, not the polls.
A93: PollsMax caveats | B93: Their page labels the GBAO poll '(B)' in embedded JSON but '(D)' elsewhere, and their own methodology admits only (D)/(R) as partisan tags. Their forecast page also claims a 'last updated' timestamp 11 days newer than the last plotted data point. Both are logged in sources/pollsmax.json under extraction_problems.
A94: City & State PA | B94: cityandstatepa.com/prediction-markets/races/pa-07-house — a third-party odds tracker. Recorded as a DATA-QUALITY observation, never as an input. It resells a Kalshi feed via an aggregator (PredictionEdge) yet disagrees with Kalshi's own API by roughly 9 points, and shows two different Brooks probabilities on the same page (72% and 78%). It carries no PA-07 polling at all, never names the Republican candidate, and publishes no timestamps.
A95: sponsorship | B95: That entire section of the site is labelled SPONSORED CONTENT, its publisher states editorial staff were not involved, and its calls to action are affiliate trading links. Nothing from it feeds any calculation here.
A96: FEC / OpenFEC | B96: api.open.fec.gov — campaign finance for the 2026 cycle, NOT polling. Candidate receipts, disbursements, cash on hand, and independent expenditures. API key lives in fec_key.txt (mode 600) and never appears in any output file.
A97: FEC staleness | B97: Periodic totals come from the July Quarterly, covering through 30 JUNE 2026 — roughly two months stale on arrival, and widening until the October Quarterly (~15 Oct, covering through 30 Sep). Independent expenditures report continuously and are fresher than the candidate totals, so the two halves of the Campaign Finance sheet are not as-of the same date.
A98: FEC caveat | B98: Most of the ~$2.76M in outside spending logged against this race was spent 6-18 May 2026 inside the contested Democratic PRIMARY, not the Brooks-vs-Mackenzie general. And $1.78M of Mackenzie's receipts is a transfer from a wound-down joint fundraising committee, not fresh donor money. Read the totals with both facts in hand.
A100: OTHER SOURCES
A101: Race ratings | B101: Cook Political Report (race 483941), Sabato's Crystal Ball and Inside Elections - all Toss-up as of February 2026.
A102: Aggregators | B102: pollsmax.com/2026-us-house/pennsylvania-7/ and pollingsource.com/house/PA-07
A103: Primary result | B103: Ballotpedia's 19 May 2026 report: Brooks ~41.4% at about 74% counted, ahead of Crosswell, McClure and Obando-Derstine.
A104: Supplementary numbers | B104: House Majority Forward figures reported by PoliticsPA without field dates, sample size or MoE, and predating the May primary. Not in house.csv; logged as supplementary only.
A106: REFRESHING
A107: What to overwrite | B107: Only blue cells. On the market sheets that means the order-book blocks and the newest rows of each history table; append new dates at the bottom and copy the formula columns down.
A108: Adding a poll | B108: Type into the next blank blue row of the general-election log on the Polls sheet. Columns L-O are already formulated through the end of the block.
A109: Extending formulas | B109: Venue Comparison covers the Polymarket date range. If you append rows to the market sheets, extend that sheet's summary ranges and its MATCH ranges to match.
A110: Recalculation | B110: This file was written by openpyxl, which stores formulas without cached results, so it is flagged to recalculate on open. Excel, LibreOffice and Numbers will compute every cell the moment you open it.
A111: Credential note | B111: The Kalshi RSA private key used to pull this data was shared in plaintext chat. Rotate it in your Kalshi account settings and keep the replacement in a key file or environment variable, never in a document.
